{
  "type": "Feature",
  "properties": {
    "gn:admin1_code":"3.0",
    "gn:asciiname":"Villa Quince de Julio",
    "gn:country_code":"NI",
    "gn:dem":23,
    "gn:feature_class":"P",
    "gn:feature_code":"PPL",
    "gn:name":"Villa Quince de Julio",
    "gn:population":0,
    "gn:timezone":"America/Managua",
    "iso:country":"NI",
    "name:und_x_variant":[
        "El Puente",
        "Puente Real",
        "Villa Salvadorita",
        "Villa 15 de Julio",
        "Villa 15 de Junio",
        "Villa Quince de Julio"
    ],
    "wof:name":"Villa Quince de Julio",
    "wof:placetype":"locality"
},
  "geometry": {"coordinates":[-86.94518000000002,12.79115],"type":"Point"}
}