{
  "type": "Feature",
  "properties": {
    "gn:admin1_code":"8.0",
    "gn:asciiname":"El Salitre",
    "gn:country_code":"NI",
    "gn:dem":179,
    "gn:feature_class":"P",
    "gn:feature_code":"PPL",
    "gn:name":"El Salitre",
    "gn:population":0,
    "gn:timezone":"America/Managua",
    "iso:country":"NI",
    "name:und_x_variant":[
        "Salitre",
        "El Salitre"
    ],
    "wof:name":"El Salitre",
    "wof:placetype":"locality"
},
  "geometry": {"coordinates":[-86.54046,12.90822],"type":"Point"}
}