{
  "type": "Feature",
  "properties": {
    "gn:admin1_code":"10.0",
    "gn:asciiname":"Zambrano",
    "gn:country_code":"NI",
    "gn:dem":78,
    "gn:feature_class":"P",
    "gn:feature_code":"PPL",
    "gn:name":"Zambrano",
    "gn:population":0,
    "gn:timezone":"America/Managua",
    "iso:country":"NI",
    "name:srp_x_preferred":[
        "\u0417\u0430\u043c\u0431\u0440\u0430\u043d\u043e"
    ],
    "name:ukr_x_preferred":[
        "\u0421\u0430\u043c\u0431\u0440\u0430\u043d\u043e"
    ],
    "name:und_x_variant":[
        "Zambrana",
        "Zambrano"
    ],
    "wof:name":"Zambrano",
    "wof:placetype":"locality"
},
  "geometry": {"coordinates":[-86.07816,12.14587],"type":"Point"}
}