{
  "type": "Feature",
  "properties": {
    "gn:admin1_code":"2.0",
    "gn:asciiname":"La Palmerita",
    "gn:country_code":"NI",
    "gn:dem":193,
    "gn:feature_class":"P",
    "gn:feature_code":"PPL",
    "gn:name":"La Palmerita",
    "gn:population":0,
    "gn:timezone":"America/Managua",
    "iso:country":"NI",
    "name:spa_x_preferred":[
        "La Palmerita"
    ],
    "wof:name":"La Palmerita",
    "wof:placetype":"locality"
},
  "geometry": {"coordinates":[-86.16668,11.72225],"type":"Point"}
}