{
  "type": "Feature",
  "properties": {
    "gn:admin1_code":"2.0",
    "gn:asciiname":"Las Enramadas",
    "gn:country_code":"NI",
    "gn:dem":273,
    "gn:feature_class":"P",
    "gn:feature_code":"PPL",
    "gn:name":"Las Enramadas",
    "gn:population":0,
    "gn:timezone":"America/Managua",
    "iso:country":"NI",
    "wof:name":"Las Enramadas",
    "wof:placetype":"locality"
},
  "geometry": {"coordinates":[-86.18803,11.76197],"type":"Point"}
}