{
  "type": "Feature",
  "properties": {
    "gn:admin1_code":"2.0",
    "gn:asciiname":"Las Brenas",
    "gn:country_code":"NI",
    "gn:dem":20,
    "gn:feature_class":"P",
    "gn:feature_code":"PPL",
    "gn:name":"Las Bre\u00f1as",
    "gn:population":0,
    "gn:timezone":"America/Managua",
    "iso:country":"NI",
    "name:spa_x_preferred":[
        "Las Bre\u00f1as"
    ],
    "wof:name":"Las Brenas",
    "wof:placetype":"locality"
},
  "geometry": {"coordinates":[-86.44122,11.72718],"type":"Point"}
}