{
  "type": "Feature",
  "properties": {
    "gn:admin1_code":"8.0",
    "gn:asciiname":"Corre Viento",
    "gn:country_code":"NI",
    "gn:dem":97,
    "gn:feature_class":"P",
    "gn:feature_code":"PPL",
    "gn:name":"Corre Viento",
    "gn:population":0,
    "gn:timezone":"America/Managua",
    "iso:country":"NI",
    "name:und_x_variant":[
        "Caser\u00edo Corre Viento",
        "Corre Viento"
    ],
    "wof:name":"Corre Viento",
    "wof:placetype":"locality"
},
  "geometry": {"coordinates":[-86.68943,12.61694],"type":"Point"}
}