{
  "type": "Feature",
  "properties": {
    "gn:admin1_code":"2.0",
    "gn:asciiname":"Emperatriz",
    "gn:country_code":"NI",
    "gn:dem":782,
    "gn:feature_class":"P",
    "gn:feature_code":"PPL",
    "gn:name":"Emperatriz",
    "gn:population":0,
    "gn:timezone":"America/Managua",
    "iso:country":"NI",
    "wof:name":"Emperatriz",
    "wof:placetype":"locality"
},
  "geometry": {"coordinates":[-86.30248,11.93792],"type":"Point"}
}