{
  "type": "Feature",
  "properties": {
    "gn:admin1_code":"10.0",
    "gn:asciiname":"Los Angeles",
    "gn:country_code":"NI",
    "gn:dem":442,
    "gn:feature_class":"P",
    "gn:feature_code":"PPL",
    "gn:name":"Los \u00c1ngeles",
    "gn:population":0,
    "gn:timezone":"America/Managua",
    "iso:country":"NI",
    "wof:name":"Los Angeles",
    "wof:placetype":"locality"
},
  "geometry": {"coordinates":[-86.04889,12.53806],"type":"Point"}
}