{
  "type": "Feature",
  "properties": {
    "gn:admin1_code":"17.0",
    "gn:asciiname":"Bachilaya",
    "gn:country_code":"NI",
    "gn:dem":25,
    "gn:feature_class":"P",
    "gn:feature_code":"PPL",
    "gn:name":"Bachilaya",
    "gn:population":0,
    "gn:timezone":"America/Managua",
    "iso:country":"NI",
    "name:und_x_variant":[
        "Batsilaya",
        "Bachilaya"
    ],
    "wof:name":"Bachilaya",
    "wof:placetype":"locality"
},
  "geometry": {"coordinates":[-83.82018000000002,14.78969],"type":"Point"}
}