{
  "type": "Feature",
  "properties": {
    "gn:admin1_code":"10.0",
    "gn:asciiname":"San Jose del Cardon",
    "gn:country_code":"NI",
    "gn:dem":864,
    "gn:feature_class":"P",
    "gn:feature_code":"PPL",
    "gn:name":"San Jos\u00e9 del Card\u00f3n",
    "gn:population":0,
    "gn:timezone":"America/Managua",
    "iso:country":"NI",
    "wof:name":"San Jose del Cardon",
    "wof:placetype":"locality"
},
  "geometry": {"coordinates":[-86.31688,11.99951],"type":"Point"}
}