{
  "type": "Feature",
  "properties": {
    "gn:admin1_code":"3.0",
    "gn:asciiname":"Las Enramadas",
    "gn:country_code":"NI",
    "gn:dem":9,
    "gn:feature_class":"P",
    "gn:feature_code":"PPL",
    "gn:name":"Las Enramadas",
    "gn:population":0,
    "gn:timezone":"America/Managua",
    "iso:country":"NI",
    "wof:name":"Las Enramadas",
    "wof:placetype":"locality"
},
  "geometry": {"coordinates":[-87.58228000000003,12.83469],"type":"Point"}
}