{
  "type": "Feature",
  "properties": {
    "gn:admin1_code":"10.0",
    "gn:asciiname":"Las Banderas",
    "gn:country_code":"NI",
    "gn:dem":87,
    "gn:feature_class":"P",
    "gn:feature_code":"PPL",
    "gn:name":"Las Banderas",
    "gn:population":0,
    "gn:timezone":"America/Managua",
    "iso:country":"NI",
    "name:und_x_variant":[
        "Banderas",
        "Las Banderas"
    ],
    "wof:name":"Las Banderas",
    "wof:placetype":"locality"
},
  "geometry": {"coordinates":[-85.95496999999997,12.33036],"type":"Point"}
}