{
  "type": "Feature",
  "properties": {
    "gn:admin1_code":"6.0",
    "gn:asciiname":"San Joaquin",
    "gn:country_code":"NI",
    "gn:dem":658,
    "gn:feature_class":"P",
    "gn:feature_code":"PPL",
    "gn:name":"San Joaqu\u00edn",
    "gn:population":0,
    "gn:timezone":"America/Managua",
    "iso:country":"NI",
    "name:ceb_x_preferred":[
        "San Joaquin"
    ],
    "name:deu_x_preferred":[
        "San Joaquin"
    ],
    "name:fra_x_preferred":[
        "San Joaquin"
    ],
    "name:ita_x_preferred":[
        "San Joaquin"
    ],
    "name:nds_x_preferred":[
        "San Joaquin"
    ],
    "name:nld_x_preferred":[
        "San Joaquin"
    ],
    "name:pol_x_preferred":[
        "San Joaquin"
    ],
    "name:por_x_preferred":[
        "San Joaquin"
    ],
    "name:swe_x_preferred":[
        "San Joaquin"
    ],
    "name:war_x_preferred":[
        "San Joaquin"
    ],
    "wof:name":"San Joaquin",
    "wof:placetype":"locality"
},
  "geometry": {"coordinates":[-85.98808000000002,11.82579],"type":"Point"}
}