{
  "type": "Feature",
  "properties": {
    "gn:admin1_code":"7.0",
    "gn:asciiname":"La Esperanza",
    "gn:country_code":"NI",
    "gn:dem":996,
    "gn:feature_class":"P",
    "gn:feature_code":"PPL",
    "gn:name":"La Esperanza",
    "gn:population":0,
    "gn:timezone":"America/Managua",
    "iso:country":"NI",
    "name:und_x_variant":[
        "Esperanza",
        "La Esperanza"
    ],
    "wof:name":"La Esperanza",
    "wof:placetype":"locality"
},
  "geometry": {"coordinates":[-85.88491999999999,13.23655],"type":"Point"}
}