{
  "type": "Feature",
  "properties": {
    "gn:admin1_code":"6.0",
    "gn:asciiname":"La Calera",
    "gn:country_code":"NI",
    "gn:dem":146,
    "gn:feature_class":"P",
    "gn:feature_code":"PPL",
    "gn:name":"La Calera",
    "gn:population":0,
    "gn:timezone":"America/Managua",
    "iso:country":"NI",
    "name:und_x_variant":[
        "Calera",
        "La Calera"
    ],
    "wof:name":"La Calera",
    "wof:placetype":"locality"
},
  "geometry": {"coordinates":[-86.09919000000002,11.7288],"type":"Point"}
}