{
  "type": "Feature",
  "properties": {
    "gn:admin1_code":"8.0",
    "gn:asciiname":"Vigias",
    "gn:country_code":"NI",
    "gn:dem":66,
    "gn:feature_class":"P",
    "gn:feature_code":"PPL",
    "gn:name":"Vig\u00edas",
    "gn:population":0,
    "gn:timezone":"America/Managua",
    "iso:country":"NI",
    "wof:name":"Vigias",
    "wof:placetype":"locality"
},
  "geometry": {"coordinates":[-86.73333000000002,12.33333],"type":"Point"}
}