{
  "type": "Feature",
  "properties": {
    "gn:admin1_code":"8.0",
    "gn:asciiname":"Rio Grande",
    "gn:country_code":"NI",
    "gn:dem":45,
    "gn:feature_class":"P",
    "gn:feature_code":"PPL",
    "gn:name":"R\u00edo Grande",
    "gn:population":0,
    "gn:timezone":"America/Managua",
    "iso:country":"NI",
    "wof:name":"Rio Grande",
    "wof:placetype":"locality"
},
  "geometry": {"coordinates":[-86.35823000000001,12.49064],"type":"Point"}
}