{
  "type": "Feature",
  "properties": {
    "gn:admin1_code":"10.0",
    "gn:asciiname":"El Obraje",
    "gn:country_code":"NI",
    "gn:dem":166,
    "gn:feature_class":"P",
    "gn:feature_code":"PPL",
    "gn:name":"El Obraje",
    "gn:population":0,
    "gn:timezone":"America/Managua",
    "iso:country":"NI",
    "wof:name":"El Obraje",
    "wof:placetype":"locality"
},
  "geometry": {"coordinates":[-86.29519000000001,12.59569],"type":"Point"}
}