{
  "type": "Feature",
  "properties": {
    "gn:admin1_code":"17.0",
    "gn:asciiname":"Tichan",
    "gn:country_code":"NI",
    "gn:dem":9,
    "gn:feature_class":"P",
    "gn:feature_code":"PPL",
    "gn:name":"Tich\u00e1n",
    "gn:population":0,
    "gn:timezone":"America/Managua",
    "iso:country":"NI",
    "wof:name":"Tichan",
    "wof:placetype":"locality"
},
  "geometry": {"coordinates":[-83.46666999999999,14.98333],"type":"Point"}
}