{
  "type": "Feature",
  "properties": {
    "gn:admin1_code":"1.0",
    "gn:asciiname":"Masapia",
    "gn:country_code":"NI",
    "gn:dem":41,
    "gn:feature_class":"P",
    "gn:feature_code":"PPL",
    "gn:name":"Masap\u00eda",
    "gn:population":0,
    "gn:timezone":"America/Managua",
    "iso:country":"NI",
    "name:und_x_variant":[
        "Masapa",
        "Masap\u00eda"
    ],
    "wof:name":"Masapia",
    "wof:placetype":"locality"
},
  "geometry": {"coordinates":[-85.74087,12.17277],"type":"Point"}
}