{
  "type": "Feature",
  "properties": {
    "gn:admin1_code":"17.0",
    "gn:asciiname":"Kum",
    "gn:country_code":"NI",
    "gn:dem":22,
    "gn:feature_class":"P",
    "gn:feature_code":"PPL",
    "gn:name":"Kum",
    "gn:population":0,
    "gn:timezone":"America/Managua",
    "iso:country":"NI",
    "name:und_x_variant":[
        "Coom",
        "Cum",
        "Kum"
    ],
    "wof:name":"Kum",
    "wof:placetype":"locality"
},
  "geometry": {"coordinates":[-83.71422,14.81099],"type":"Point"}
}