{
  "type": "Feature",
  "properties": {
    "gn:admin1_code":"17.0",
    "gn:asciiname":"Greystown",
    "gn:country_code":"NI",
    "gn:dem":8,
    "gn:feature_class":"P",
    "gn:feature_code":"PPL",
    "gn:name":"Greystown",
    "gn:population":0,
    "gn:timezone":"America/Managua",
    "iso:country":"NI",
    "name:und_x_variant":[
        "Graytown",
        "Greystown"
    ],
    "wof:name":"Greystown",
    "wof:placetype":"locality"
},
  "geometry": {"coordinates":[-83.28348000000003,14.45966],"type":"Point"}
}