{
  "type": "Feature",
  "properties": {
    "gn:admin1_code":"1.0",
    "gn:asciiname":"Tecolostote",
    "gn:country_code":"NI",
    "gn:dem":94,
    "gn:feature_class":"P",
    "gn:feature_code":"PPL",
    "gn:name":"Tecolostote",
    "gn:population":0,
    "gn:timezone":"America/Managua",
    "iso:country":"NI",
    "wof:name":"Tecolostote",
    "wof:placetype":"locality"
},
  "geometry": {"coordinates":[-85.64229,12.25305],"type":"Point"}
}