{
  "type": "Feature",
  "properties": {
    "gn:admin1_code":"4.0",
    "gn:asciiname":"Paso de Lajas",
    "gn:country_code":"NI",
    "gn:dem":86,
    "gn:feature_class":"P",
    "gn:feature_code":"PPL",
    "gn:name":"Paso de Lajas",
    "gn:population":0,
    "gn:timezone":"America/Managua",
    "iso:country":"NI",
    "wof:name":"Paso de Lajas",
    "wof:placetype":"locality"
},
  "geometry": {"coordinates":[-85.35319,12.13118],"type":"Point"}
}