{
  "type": "Feature",
  "properties": {
    "gn:admin1_code":"17.0",
    "gn:asciiname":"Asang",
    "gn:country_code":"NI",
    "gn:dem":81,
    "gn:feature_class":"P",
    "gn:feature_code":"PPL",
    "gn:name":"Asang",
    "gn:population":0,
    "gn:timezone":"America/Managua",
    "iso:country":"NI",
    "name:und_x_variant":[
        "Asan",
        "Asaog",
        "Asang"
    ],
    "wof:name":"Asang",
    "wof:placetype":"locality"
},
  "geometry": {"coordinates":[-84.75058,14.7257],"type":"Point"}
}