{
  "type": "Feature",
  "properties": {
    "gn:admin1_code":"18.0",
    "gn:asciiname":"Salto Grande",
    "gn:country_code":"NI",
    "gn:dem":83,
    "gn:feature_class":"P",
    "gn:feature_code":"PPL",
    "gn:name":"Salto Grande",
    "gn:population":0,
    "gn:timezone":"America/Managua",
    "iso:country":"NI",
    "name:ceb_x_preferred":[
        "Salto Grande"
    ],
    "name:fra_x_preferred":[
        "Salto Grande"
    ],
    "name:nld_x_preferred":[
        "Salto Grande"
    ],
    "name:por_x_preferred":[
        "Salto Grande"
    ],
    "name:rus_x_preferred":[
        "\u0421\u0430\u043b\u044c\u0442\u043e-\u0413\u0440\u0430\u043d\u0434\u0435"
    ],
    "name:spa_x_preferred":[
        "Salto Grande"
    ],
    "name:srp_x_preferred":[
        "\u0421\u0430\u043b\u0442\u043e \u0413\u0440\u0430\u043d\u0434\u0435"
    ],
    "name:swe_x_preferred":[
        "Salto Grande"
    ],
    "wof:name":"Salto Grande",
    "wof:placetype":"locality"
},
  "geometry": {"coordinates":[-84.60191,12.53602],"type":"Point"}
}