{
  "type": "Feature",
  "properties": {
    "gn:admin1_code":"4.0",
    "gn:asciiname":"San Gregorio",
    "gn:country_code":"NI",
    "gn:dem":390,
    "gn:feature_class":"P",
    "gn:feature_code":"PPL",
    "gn:name":"San Gregorio",
    "gn:population":0,
    "gn:timezone":"America/Managua",
    "iso:country":"NI",
    "name:ceb_x_preferred":[
        "San Gregorio"
    ],
    "name:ces_x_preferred":[
        "San Gregorio"
    ],
    "name:deu_x_preferred":[
        "San Gregorio"
    ],
    "name:fra_x_preferred":[
        "San Gregorio"
    ],
    "name:glg_x_preferred":[
        "San Gregorio"
    ],
    "name:ita_x_preferred":[
        "San Gregorio"
    ],
    "name:nld_x_preferred":[
        "San Gregorio"
    ],
    "name:por_x_preferred":[
        "San Gregorio"
    ],
    "name:sco_x_preferred":[
        "San Gregorio"
    ],
    "name:spa_x_preferred":[
        "San Gregorio"
    ],
    "name:srp_x_preferred":[
        "San Gregorio"
    ],
    "name:swe_x_preferred":[
        "San Gregorio"
    ],
    "name:und_x_variant":[
        "Gregorio",
        "San Gregorio"
    ],
    "wof:name":"San Gregorio",
    "wof:placetype":"locality"
},
  "geometry": {"coordinates":[-85.08493,12.28995],"type":"Point"}
}