{
  "type": "Feature",
  "properties": {
    "gn:admin1_code":"17.0",
    "gn:asciiname":"Sagua",
    "gn:country_code":"NI",
    "gn:dem":8,
    "gn:feature_class":"P",
    "gn:feature_code":"PPL",
    "gn:name":"Sagua",
    "gn:population":0,
    "gn:timezone":"America/Managua",
    "iso:country":"NI",
    "name:und_x_variant":[
        "Sawa",
        "Sahua Leven",
        "Sagua"
    ],
    "wof:name":"Sagua",
    "wof:placetype":"locality"
},
  "geometry": {"coordinates":[-83.56059999999999,14.92492],"type":"Point"}
}