{
  "type": "Feature",
  "properties": {
    "gn:admin1_code":"12.0",
    "gn:asciiname":"Las Minitas",
    "gn:country_code":"NI",
    "gn:dem":429,
    "gn:feature_class":"P",
    "gn:feature_code":"PPL",
    "gn:name":"Las Minitas",
    "gn:population":0,
    "gn:timezone":"America/Managua",
    "iso:country":"NI",
    "wof:name":"Las Minitas",
    "wof:placetype":"locality"
},
  "geometry": {"coordinates":[-85.38333,12.83333],"type":"Point"}
}