{
  "type": "Feature",
  "properties": {
    "gn:admin1_code":"3.0",
    "gn:asciiname":"Los Valdivia",
    "gn:country_code":"NI",
    "gn:dem":295,
    "gn:feature_class":"P",
    "gn:feature_code":"PPL",
    "gn:name":"Los Valdivia",
    "gn:population":0,
    "gn:timezone":"America/Managua",
    "iso:country":"NI",
    "wof:name":"Los Valdivia",
    "wof:placetype":"locality"
},
  "geometry": {"coordinates":[-86.96666999999999,12.63333],"type":"Point"}
}