{
  "type": "Feature",
  "properties": {
    "gn:admin1_code":"18.0",
    "gn:asciiname":"Barra del Rio Maiz",
    "gn:country_code":"NI",
    "gn:dem":12,
    "gn:feature_class":"P",
    "gn:feature_code":"PPL",
    "gn:name":"Barra del R\u00edo Ma\u00edz",
    "gn:population":0,
    "gn:timezone":"America/Managua",
    "iso:country":"NI",
    "wof:name":"Barra del Rio Maiz",
    "wof:placetype":"locality"
},
  "geometry": {"coordinates":[-83.88333,11.28333],"type":"Point"}
}