{
  "type": "Feature",
  "properties": {
    "gn:admin1_code":"6.0",
    "gn:asciiname":"La Pedrera",
    "gn:country_code":"NI",
    "gn:dem":143,
    "gn:feature_class":"P",
    "gn:feature_code":"PPL",
    "gn:name":"La Pedrera",
    "gn:population":0,
    "gn:timezone":"America/Managua",
    "iso:country":"NI",
    "name:spa_x_preferred":[
        "La Pedrera"
    ],
    "wof:name":"La Pedrera",
    "wof:placetype":"locality"
},
  "geometry": {"coordinates":[-85.98535,11.90226],"type":"Point"}
}