{
  "type": "Feature",
  "properties": {
    "gn:admin1_code":"3.0",
    "gn:asciiname":"Cosmapa",
    "gn:country_code":"NI",
    "gn:dem":66,
    "gn:feature_class":"P",
    "gn:feature_code":"PPL",
    "gn:name":"Cosmapa",
    "gn:population":0,
    "gn:timezone":"America/Managua",
    "iso:country":"NI",
    "wof:name":"Cosmapa",
    "wof:placetype":"locality"
},
  "geometry": {"coordinates":[-87.06667,12.58333],"type":"Point"}
}