{
  "type": "Feature",
  "properties": {
    "gn:admin1_code":"11.0",
    "gn:asciiname":"La Ceibita",
    "gn:country_code":"NI",
    "gn:dem":237,
    "gn:feature_class":"P",
    "gn:feature_code":"PPL",
    "gn:name":"La Ceibita",
    "gn:population":0,
    "gn:timezone":"America/Managua",
    "iso:country":"NI",
    "name:und_x_variant":[
        "Comej\u00e9n",
        "Comejon",
        "El Comej\u00e9n",
        "Caser\u00edo El Comej\u00e9n",
        "La Ceibita"
    ],
    "wof:name":"La Ceibita",
    "wof:placetype":"locality"
},
  "geometry": {"coordinates":[-86.07055,12.01742],"type":"Point"}
}