{
  "type": "Feature",
  "properties": {
    "gn:admin1_code":"17.0",
    "gn:asciiname":"Auas Tingni",
    "gn:country_code":"NI",
    "gn:dem":49,
    "gn:feature_class":"P",
    "gn:feature_code":"PPL",
    "gn:name":"Auas Tingni",
    "gn:population":0,
    "gn:timezone":"America/Managua",
    "iso:country":"NI",
    "name:und_x_variant":[
        "Awastingni",
        "Auas Tingni"
    ],
    "wof:name":"Auas Tingni",
    "wof:placetype":"locality"
},
  "geometry": {"coordinates":[-83.94991999999998,14.38272],"type":"Point"}
}