{
  "type": "Feature",
  "properties": {
    "gn:admin1_code":"8.0",
    "gn:asciiname":"La Calera",
    "gn:country_code":"NI",
    "gn:dem":193,
    "gn:feature_class":"P",
    "gn:feature_code":"PPL",
    "gn:name":"La Calera",
    "gn:population":0,
    "gn:timezone":"America/Managua",
    "iso:country":"NI",
    "name:ceb_x_preferred":[
        "La Calera"
    ],
    "name:deu_x_preferred":[
        "La Calera"
    ],
    "name:ita_x_preferred":[
        "La Calera"
    ],
    "name:nld_x_preferred":[
        "La Calera"
    ],
    "name:pol_x_preferred":[
        "La Calera"
    ],
    "name:rus_x_preferred":[
        "\u041b\u0430-\u041a\u0430\u043b\u0435\u0440\u0430"
    ],
    "name:sco_x_preferred":[
        "La Calera"
    ],
    "name:spa_x_preferred":[
        "La Calera"
    ],
    "name:swe_x_preferred":[
        "La Calera"
    ],
    "wof:name":"La Calera",
    "wof:placetype":"locality"
},
  "geometry": {"coordinates":[-86.62862,12.69102],"type":"Point"}
}