{
  "type": "Feature",
  "properties": {
    "gn:admin1_code":"8.0",
    "gn:asciiname":"La Calera",
    "gn:country_code":"NI",
    "gn:dem":193,
    "gn:feature_class":"P",
    "gn:feature_code":"PPL",
    "gn:name":"La Calera",
    "gn:population":0,
    "gn:timezone":"America/Managua",
    "iso:country":"NI",
    "wof:name":"La Calera",
    "wof:placetype":"locality"
},
  "geometry": {"coordinates":[-86.62862,12.69102],"type":"Point"}
}