{
  "type": "Feature",
  "properties": {
    "gn:admin1_code":"2.0",
    "gn:asciiname":"Santa Emilia",
    "gn:country_code":"NI",
    "gn:dem":23,
    "gn:feature_class":"P",
    "gn:feature_code":"PPL",
    "gn:name":"Santa Emilia",
    "gn:population":0,
    "gn:timezone":"America/Managua",
    "iso:country":"NI",
    "name:spa_x_preferred":[
        "Santa Emilia"
    ],
    "wof:name":"Santa Emilia",
    "wof:placetype":"locality"
},
  "geometry": {"coordinates":[-86.43725999999999,11.73335],"type":"Point"}
}