{
  "type": "Feature",
  "properties": {
    "gn:admin1_code":"6.0",
    "gn:asciiname":"Santa Cruz de Buenaviata",
    "gn:country_code":"NI",
    "gn:dem":209,
    "gn:feature_class":"P",
    "gn:feature_code":"PPL",
    "gn:name":"Santa Cruz de Buenaviata",
    "gn:population":0,
    "gn:timezone":"America/Managua",
    "iso:country":"NI",
    "name:spa_x_preferred":[
        "Santa Cruz de Buenaviata"
    ],
    "wof:name":"Santa Cruz de Buenaviata",
    "wof:placetype":"locality"
},
  "geometry": {"coordinates":[-85.99483000000002,11.88809],"type":"Point"}
}