{
  "type": "Feature",
  "properties": {
    "gn:admin1_code":"15.0",
    "gn:asciiname":"Canas Gordas",
    "gn:country_code":"NI",
    "gn:dem":45,
    "gn:feature_class":"P",
    "gn:feature_code":"PPL",
    "gn:name":"Ca\u00f1as Gordas",
    "gn:population":0,
    "gn:timezone":"America/Managua",
    "iso:country":"NI",
    "wof:name":"Canas Gordas",
    "wof:placetype":"locality"
},
  "geometry": {"coordinates":[-85.68652,11.29713],"type":"Point"}
}