{
  "type": "Feature",
  "properties": {
    "gn:admin1_code":"8.0",
    "gn:asciiname":"San Antonio del Condadillo",
    "gn:country_code":"NI",
    "gn:dem":195,
    "gn:feature_class":"P",
    "gn:feature_code":"PPL",
    "gn:name":"San Antonio del Condadillo",
    "gn:population":0,
    "gn:timezone":"America/Managua",
    "iso:country":"NI",
    "wof:name":"San Antonio del Condadillo",
    "wof:placetype":"locality"
},
  "geometry": {"coordinates":[-86.44991,12.75206],"type":"Point"}
}