{
  "type": "Feature",
  "properties": {
    "gn:admin1_code":"3.0",
    "gn:asciiname":"San Jose de Agua Fria",
    "gn:country_code":"NI",
    "gn:dem":138,
    "gn:feature_class":"P",
    "gn:feature_code":"PPL",
    "gn:name":"San Jos\u00e9 de Agua Fr\u00eda",
    "gn:population":0,
    "gn:timezone":"America/Managua",
    "iso:country":"NI",
    "name:und_x_variant":[
        "San Jos\u00e9",
        "San Jos\u00e9 de Agua Fr\u00eda"
    ],
    "wof:name":"San Jose de Agua Fria",
    "wof:placetype":"locality"
},
  "geometry": {"coordinates":[-87.28485999999999,12.77337],"type":"Point"}
}