{
  "type": "Feature",
  "properties": {
    "gn:admin1_code":"18.0",
    "gn:asciiname":"Walpa",
    "gn:country_code":"NI",
    "gn:dem":6,
    "gn:feature_class":"P",
    "gn:feature_code":"PPL",
    "gn:name":"Walpa",
    "gn:population":0,
    "gn:timezone":"America/Managua",
    "iso:country":"NI",
    "name:und_x_variant":[
        "Hualpa",
        "Wualpa",
        "Walpa"
    ],
    "wof:name":"Walpa",
    "wof:placetype":"locality"
},
  "geometry": {"coordinates":[-83.53461,12.93954],"type":"Point"}
}