{
  "type": "Feature",
  "properties": {
    "gn:admin1_code":"12.0",
    "gn:asciiname":"Ilapo",
    "gn:country_code":"NI",
    "gn:dem":670,
    "gn:feature_class":"P",
    "gn:feature_code":"PPL",
    "gn:name":"Ilapo",
    "gn:population":0,
    "gn:timezone":"America/Managua",
    "iso:country":"NI",
    "wof:name":"Ilapo",
    "wof:placetype":"locality"
},
  "geometry": {"coordinates":[-85.79279,12.99315],"type":"Point"}
}