{
  "type": "Feature",
  "properties": {
    "gn:admin1_code":"1.0",
    "gn:asciiname":"La Penita",
    "gn:country_code":"NI",
    "gn:dem":77,
    "gn:feature_class":"P",
    "gn:feature_code":"PPL",
    "gn:name":"La Pe\u00f1ita",
    "gn:population":0,
    "gn:timezone":"America/Managua",
    "iso:country":"NI",
    "wof:name":"La Penita",
    "wof:placetype":"locality"
},
  "geometry": {"coordinates":[-85.66954,12.20813],"type":"Point"}
}