{
  "type": "Feature",
  "properties": {
    "gn:admin1_code":"2.0",
    "gn:asciiname":"Dulce Nombre",
    "gn:country_code":"NI",
    "gn:dem":370,
    "gn:feature_class":"P",
    "gn:feature_code":"PPL",
    "gn:name":"Dulce Nombre",
    "gn:population":0,
    "gn:timezone":"America/Managua",
    "iso:country":"NI",
    "name:ceb_x_preferred":[
        "Dulce Nombre"
    ],
    "name:fra_x_preferred":[
        "Dulce Nombre"
    ],
    "name:ita_x_preferred":[
        "Dulce Nombre"
    ],
    "name:nld_x_preferred":[
        "Dulce Nombre"
    ],
    "name:pol_x_preferred":[
        "Dulce Nombre"
    ],
    "name:por_x_preferred":[
        "Dulce Nombre"
    ],
    "name:spa_x_preferred":[
        "Dulce Nombre"
    ],
    "name:swe_x_preferred":[
        "Dulce Nombre"
    ],
    "name:zho_x_preferred":[
        "\u675c\u723e\u585e\u8fb2\u5e03\u96f7"
    ],
    "wof:name":"Dulce Nombre",
    "wof:placetype":"locality"
},
  "geometry": {"coordinates":[-86.34316,11.8596],"type":"Point"}
}