{
  "type": "Feature",
  "properties": {
    "gn:admin1_code":"18.0",
    "gn:asciiname":"El Aparejo",
    "gn:country_code":"NI",
    "gn:dem":58,
    "gn:feature_class":"P",
    "gn:feature_code":"PPL",
    "gn:name":"El Aparejo",
    "gn:population":0,
    "gn:timezone":"America/Managua",
    "iso:country":"NI",
    "wof:name":"El Aparejo",
    "wof:placetype":"locality"
},
  "geometry": {"coordinates":[-84.44497,12.11936],"type":"Point"}
}