{
  "type": "Feature",
  "properties": {
    "gn:admin1_code":"14.0",
    "gn:asciiname":"Morrillo",
    "gn:country_code":"NI",
    "gn:dem":42,
    "gn:feature_class":"P",
    "gn:feature_code":"PPL",
    "gn:name":"Morrillo",
    "gn:population":0,
    "gn:timezone":"America/Managua",
    "iso:country":"NI",
    "wof:name":"Morrillo",
    "wof:placetype":"locality"
},
  "geometry": {"coordinates":[-84.79098,11.24243],"type":"Point"}
}