{
  "type": "Feature",
  "properties": {
    "gn:admin1_code":"18.0",
    "gn:asciiname":"Banco Brown Abajo",
    "gn:country_code":"NI",
    "gn:dem":10,
    "gn:feature_class":"P",
    "gn:feature_code":"PPL",
    "gn:name":"Banco Brown Abajo",
    "gn:population":0,
    "gn:timezone":"America/Managua",
    "iso:country":"NI",
    "name:und_x_variant":[
        "Brown Bank Bottom",
        "Banco Brown Abajo"
    ],
    "wof:name":"Banco Brown Abajo",
    "wof:placetype":"locality"
},
  "geometry": {"coordinates":[-83.73021999999997,12.44599],"type":"Point"}
}