{
  "type": "Feature",
  "properties": {
    "gn:admin1_code":"8.0",
    "gn:asciiname":"Poneloya",
    "gn:country_code":"NI",
    "gn:dem":10,
    "gn:feature_class":"P",
    "gn:feature_code":"PPL",
    "gn:name":"Poneloya",
    "gn:population":0,
    "gn:timezone":"America/Managua",
    "iso:country":"NI",
    "name:und_x_variant":[
        "Paneloya",
        "Poneloya"
    ],
    "wof:name":"Poneloya",
    "wof:placetype":"locality"
},
  "geometry": {"coordinates":[-87.03793,12.37404],"type":"Point"}
}