{
  "type": "Feature",
  "properties": {
    "gn:admin1_code":"10.0",
    "gn:asciiname":"El Tamarindo",
    "gn:country_code":"NI",
    "gn:dem":68,
    "gn:feature_class":"P",
    "gn:feature_code":"PPL",
    "gn:name":"El Tamarindo",
    "gn:population":0,
    "gn:timezone":"America/Managua",
    "iso:country":"NI",
    "wof:name":"El Tamarindo",
    "wof:placetype":"locality"
},
  "geometry": {"coordinates":[-86.48198000000002,11.84364],"type":"Point"}
}