{
  "type": "Feature",
  "properties": {
    "gn:admin1_code":"15.0",
    "gn:asciiname":"Iguana",
    "gn:country_code":"NI",
    "gn:dem":9,
    "gn:feature_class":"P",
    "gn:feature_code":"PPL",
    "gn:name":"Iguana",
    "gn:population":0,
    "gn:timezone":"America/Managua",
    "iso:country":"NI",
    "wof:name":"Iguana",
    "wof:placetype":"locality"
},
  "geometry": {"coordinates":[-86.04977,11.41567],"type":"Point"}
}