{
  "type": "Feature",
  "properties": {
    "gn:admin1_code":"12.0",
    "gn:asciiname":"La Pitahaya",
    "gn:country_code":"NI",
    "gn:dem":599,
    "gn:feature_class":"P",
    "gn:feature_code":"PPL",
    "gn:name":"La Pitahaya",
    "gn:population":0,
    "gn:timezone":"America/Managua",
    "iso:country":"NI",
    "wof:name":"La Pitahaya",
    "wof:placetype":"locality"
},
  "geometry": {"coordinates":[-86.1909,12.75361],"type":"Point"}
}