{
  "type": "Feature",
  "properties": {
    "gn:admin1_code":"3.0",
    "gn:asciiname":"Merida",
    "gn:country_code":"NI",
    "gn:dem":104,
    "gn:feature_class":"P",
    "gn:feature_code":"PPL",
    "gn:name":"M\u00e9rida",
    "gn:population":0,
    "gn:timezone":"America/Managua",
    "iso:country":"NI",
    "wof:name":"Merida",
    "wof:placetype":"locality"
},
  "geometry": {"coordinates":[-87.08333,12.61667],"type":"Point"}
}