{
  "type": "Feature",
  "properties": {
    "gn:admin1_code":"10.0",
    "gn:asciiname":"La Avellana",
    "gn:country_code":"NI",
    "gn:dem":447,
    "gn:feature_class":"P",
    "gn:feature_code":"PPL",
    "gn:name":"La Avellana",
    "gn:population":0,
    "gn:timezone":"America/Managua",
    "iso:country":"NI",
    "wof:name":"La Avellana",
    "wof:placetype":"locality"
},
  "geometry": {"coordinates":[-85.99248,12.50293],"type":"Point"}
}