{
  "type": "Feature",
  "properties": {
    "gn:admin1_code":"11.0",
    "gn:asciiname":"Veracruz",
    "gn:country_code":"NI",
    "gn:dem":127,
    "gn:feature_class":"P",
    "gn:feature_code":"PPL",
    "gn:name":"Veracruz",
    "gn:population":0,
    "gn:timezone":"America/Managua",
    "iso:country":"NI",
    "wof:name":"Veracruz",
    "wof:placetype":"locality"
},
  "geometry": {"coordinates":[-86.1671,12.08576],"type":"Point"}
}