{
  "type": "Feature",
  "properties": {
    "gn:admin1_code":"15.0",
    "gn:asciiname":"Zapatera Archipelago National Park",
    "gn:country_code":"NI",
    "gn:dem":331,
    "gn:feature_class":"P",
    "gn:feature_code":"PPL",
    "gn:name":"Zapatera Archipelago National Park",
    "gn:population":0,
    "gn:timezone":"America/Managua",
    "iso:country":"NI",
    "name:spa_x_preferred":[
        "Parque Nacional Archipi\u00e9lago Zapatera"
    ],
    "wof:name":"Zapatera Archipelago National Park",
    "wof:placetype":"locality"
},
  "geometry": {"coordinates":[-85.8403,11.73432],"type":"Point"}
}