{
  "type": "Feature",
  "properties": {
    "gn:admin1_code":"17.0",
    "gn:asciiname":"Aserradero Sanders",
    "gn:country_code":"NI",
    "gn:dem":10,
    "gn:feature_class":"P",
    "gn:feature_code":"PPL",
    "gn:name":"Aserradero Sanders",
    "gn:population":0,
    "gn:timezone":"America/Managua",
    "iso:country":"NI",
    "name:und_x_variant":[
        "Aserr\u00edo Bum",
        "Aserradero Sanders"
    ],
    "wof:name":"Aserradero Sanders",
    "wof:placetype":"locality"
},
  "geometry": {"coordinates":[-83.55368,14.10515],"type":"Point"}
}