{
  "type": "Feature",
  "properties": {
    "gn:admin1_code":"17.0",
    "gn:asciiname":"Lamlaya",
    "gn:country_code":"NI",
    "gn:dem":8,
    "gn:feature_class":"P",
    "gn:feature_code":"PPL",
    "gn:name":"Lamlaya",
    "gn:population":0,
    "gn:timezone":"America/Managua",
    "iso:country":"NI",
    "name:und_x_variant":[
        "Lama Laya",
        "Lumlel",
        "Lamblaya",
        "Lumlei",
        "Lamlaya"
    ],
    "wof:name":"Lamlaya",
    "wof:placetype":"locality"
},
  "geometry": {"coordinates":[-83.41984000000002,14.0236],"type":"Point"}
}