{
  "type": "Feature",
  "properties": {
    "gn:admin1_code":"7.0",
    "gn:asciiname":"Quebrada Arriba",
    "gn:country_code":"NI",
    "gn:dem":850,
    "gn:feature_class":"P",
    "gn:feature_code":"PPL",
    "gn:name":"Quebrada Arriba",
    "gn:population":0,
    "gn:timezone":"America/Managua",
    "iso:country":"NI",
    "name:und_x_variant":[
        "Quebrada",
        "Quebrado",
        "Quebrada Arriba"
    ],
    "wof:name":"Quebrada Arriba",
    "wof:placetype":"locality"
},
  "geometry": {"coordinates":[-86.22533,13.28438],"type":"Point"}
}