{
  "type": "Feature",
  "properties": {
    "gn:admin1_code":"3.0",
    "gn:asciiname":"Los Camarones",
    "gn:country_code":"NI",
    "gn:dem":11,
    "gn:feature_class":"P",
    "gn:feature_code":"PPL",
    "gn:name":"Los Camarones",
    "gn:population":0,
    "gn:timezone":"America/Managua",
    "iso:country":"NI",
    "wof:name":"Los Camarones",
    "wof:placetype":"locality"
},
  "geometry": {"coordinates":[-87.06329000000002,12.99858],"type":"Point"}
}