{
  "type": "Feature",
  "properties": {
    "gn:admin1_code":"5.0",
    "gn:asciiname":"Los Calpules",
    "gn:country_code":"NI",
    "gn:dem":859,
    "gn:feature_class":"P",
    "gn:feature_code":"PPL",
    "gn:name":"Los Calpules",
    "gn:population":0,
    "gn:timezone":"America/Managua",
    "iso:country":"NI",
    "name:und_x_variant":[
        "Capules",
        "Calpules",
        "Los Calpules"
    ],
    "wof:name":"Los Calpules",
    "wof:placetype":"locality"
},
  "geometry": {"coordinates":[-86.55768,13.40231],"type":"Point"}
}