{
  "type": "Feature",
  "properties": {
    "gn:admin1_code":"10.0",
    "gn:asciiname":"Las Tinajas",
    "gn:country_code":"NI",
    "gn:dem":41,
    "gn:feature_class":"P",
    "gn:feature_code":"PPL",
    "gn:name":"Las Tinajas",
    "gn:population":0,
    "gn:timezone":"America/Managua",
    "iso:country":"NI",
    "wof:name":"Las Tinajas",
    "wof:placetype":"locality"
},
  "geometry": {"coordinates":[-86.16849000000001,12.31765],"type":"Point"}
}