{
  "type": "Feature",
  "properties": {
    "gn:admin1_code":"7.0",
    "gn:asciiname":"Las Mesitas",
    "gn:country_code":"NI",
    "gn:dem":1016,
    "gn:feature_class":"P",
    "gn:feature_code":"PPL",
    "gn:name":"Las Mesitas",
    "gn:population":0,
    "gn:timezone":"America/Managua",
    "iso:country":"NI",
    "name:und_x_variant":[
        "Mesita",
        "Las Mesitas"
    ],
    "wof:name":"Las Mesitas",
    "wof:placetype":"locality"
},
  "geometry": {"coordinates":[-86.03986,13.08321],"type":"Point"}
}