{
  "type": "Feature",
  "properties": {
    "gn:admin1_code":"12.0",
    "gn:asciiname":"Piedra Larga",
    "gn:country_code":"NI",
    "gn:dem":469,
    "gn:feature_class":"P",
    "gn:feature_code":"PPL",
    "gn:name":"Piedra Larga",
    "gn:population":0,
    "gn:timezone":"America/Managua",
    "iso:country":"NI",
    "wof:name":"Piedra Larga",
    "wof:placetype":"locality"
},
  "geometry": {"coordinates":[-85.83225999999998,12.69324],"type":"Point"}
}