{
  "type": "Feature",
  "properties": {
    "gn:admin1_code":"10.0",
    "gn:asciiname":"San Francisco del Penon",
    "gn:country_code":"NI",
    "gn:dem":96,
    "gn:feature_class":"P",
    "gn:feature_code":"PPL",
    "gn:name":"San Francisco del Pe\u00f1\u00f3n",
    "gn:population":0,
    "gn:timezone":"America/Managua",
    "iso:country":"NI",
    "wof:name":"San Francisco del Penon",
    "wof:placetype":"locality"
},
  "geometry": {"coordinates":[-86.04144000000002,12.4113],"type":"Point"}
}