{
  "type": "Feature",
  "properties": {
    "gn:admin1_code":"6.0",
    "gn:asciiname":"Charco Muerto",
    "gn:country_code":"NI",
    "gn:dem":45,
    "gn:feature_class":"P",
    "gn:feature_code":"PPL",
    "gn:name":"Charco Muerto",
    "gn:population":0,
    "gn:timezone":"America/Managua",
    "iso:country":"NI",
    "wof:name":"Charco Muerto",
    "wof:placetype":"locality"
},
  "geometry": {"coordinates":[-85.89319999999999,11.79451],"type":"Point"}
}