{
  "type": "Feature",
  "properties": {
    "gn:admin1_code":"17.0",
    "gn:asciiname":"Lisawe",
    "gn:country_code":"NI",
    "gn:dem":119,
    "gn:feature_class":"P",
    "gn:feature_code":"PPL",
    "gn:name":"Lisaw\u00e9",
    "gn:population":0,
    "gn:timezone":"America/Managua",
    "iso:country":"NI",
    "wof:name":"Lisawe",
    "wof:placetype":"locality"
},
  "geometry": {"coordinates":[-84.96895000000001,13.36929],"type":"Point"}
}