{
  "type": "Feature",
  "properties": {
    "gn:admin1_code":"8.0",
    "gn:asciiname":"Los Torunos",
    "gn:country_code":"NI",
    "gn:dem":124,
    "gn:feature_class":"P",
    "gn:feature_code":"PPL",
    "gn:name":"Los Toru\u00f1os",
    "gn:population":0,
    "gn:timezone":"America/Managua",
    "iso:country":"NI",
    "wof:name":"Los Torunos",
    "wof:placetype":"locality"
},
  "geometry": {"coordinates":[-86.53333000000001,12.51667],"type":"Point"}
}