{
  "type": "Feature",
  "properties": {
    "gn:admin1_code":"12.0",
    "gn:asciiname":"El Guiscanal",
    "gn:country_code":"NI",
    "gn:dem":239,
    "gn:feature_class":"P",
    "gn:feature_code":"PPL",
    "gn:name":"El Guisc\u00e1nal",
    "gn:population":0,
    "gn:timezone":"America/Managua",
    "iso:country":"NI",
    "name:und_x_variant":[
        "Guiscanal",
        "Caser\u00edo El Guisconal",
        "G\u00fciscar\u00e1n",
        "El Guisc\u00e1nal"
    ],
    "wof:name":"El Guiscanal",
    "wof:placetype":"locality"
},
  "geometry": {"coordinates":[-86.25178000000002,12.6426],"type":"Point"}
}