{
  "type": "Feature",
  "properties": {
    "gn:admin1_code":"8.0",
    "gn:asciiname":"San Ramon de la Uva",
    "gn:country_code":"NI",
    "gn:dem":878,
    "gn:feature_class":"P",
    "gn:feature_code":"PPL",
    "gn:name":"San Ram\u00f3n de la Uva",
    "gn:population":0,
    "gn:timezone":"America/Managua",
    "iso:country":"NI",
    "wof:name":"San Ramon de la Uva",
    "wof:placetype":"locality"
},
  "geometry": {"coordinates":[-86.28270999999999,12.82599],"type":"Point"}
}