{
  "type": "Feature",
  "properties": {
    "gn:admin1_code":"12.0",
    "gn:asciiname":"Las Maderas",
    "gn:country_code":"NI",
    "gn:dem":258,
    "gn:feature_class":"P",
    "gn:feature_code":"PPL",
    "gn:name":"Las Maderas",
    "gn:population":0,
    "gn:timezone":"America/Managua",
    "iso:country":"NI",
    "wof:name":"Las Maderas",
    "wof:placetype":"locality"
},
  "geometry": {"coordinates":[-85.51666999999998,12.81667],"type":"Point"}
}