{
  "type": "Feature",
  "properties": {
    "gn:admin1_code":"10.0",
    "gn:asciiname":"La Uva",
    "gn:country_code":"NI",
    "gn:dem":151,
    "gn:feature_class":"P",
    "gn:feature_code":"PPL",
    "gn:name":"La Uva",
    "gn:population":0,
    "gn:timezone":"America/Managua",
    "iso:country":"NI",
    "name:und_x_variant":[
        "Caser\u00edo La Uva",
        "La Uva"
    ],
    "wof:name":"La Uva",
    "wof:placetype":"locality"
},
  "geometry": {"coordinates":[-86.03121,12.47291],"type":"Point"}
}