{
  "type": "Feature",
  "properties": {
    "gn:admin1_code":"3.0",
    "gn:asciiname":"Las Costillas",
    "gn:country_code":"NI",
    "gn:dem":37,
    "gn:feature_class":"P",
    "gn:feature_code":"PPL",
    "gn:name":"Las Costillas",
    "gn:population":0,
    "gn:timezone":"America/Managua",
    "iso:country":"NI",
    "wof:name":"Las Costillas",
    "wof:placetype":"locality"
},
  "geometry": {"coordinates":[-87.27804999999999,12.66419],"type":"Point"}
}