{
  "type": "Feature",
  "properties": {
    "gn:admin1_code":"8.0",
    "gn:asciiname":"Mina El Limon",
    "gn:country_code":"NI",
    "gn:dem":76,
    "gn:feature_class":"P",
    "gn:feature_code":"PPL",
    "gn:name":"Mina El Lim\u00f3n",
    "gn:population":0,
    "gn:timezone":"America/Managua",
    "iso:country":"NI",
    "name:und_x_variant":[
        "El Lim\u00f3n",
        "Limon",
        "Mina Lim\u00f3n",
        "Mina El Lim\u00f3n"
    ],
    "wof:name":"Mina El Limon",
    "wof:placetype":"locality"
},
  "geometry": {"coordinates":[-86.73795,12.75067],"type":"Point"}
}