{
  "type": "Feature",
  "properties": {
    "gn:admin1_code":"15.0",
    "gn:asciiname":"Merida",
    "gn:country_code":"NI",
    "gn:dem":37,
    "gn:feature_class":"P",
    "gn:feature_code":"PPL",
    "gn:name":"M\u00e9rida",
    "gn:population":0,
    "gn:timezone":"America/Managua",
    "iso:country":"NI",
    "name:ceb_x_preferred":[
        "Merida"
    ],
    "name:dan_x_preferred":[
        "Merida"
    ],
    "name:est_x_preferred":[
        "Merida"
    ],
    "name:lav_x_preferred":[
        "Merida"
    ],
    "name:lit_x_preferred":[
        "Merida"
    ],
    "name:mkd_x_preferred":[
        "\u041c\u0435\u0440\u0438\u0434\u0430"
    ],
    "name:nno_x_preferred":[
        "M\u00e9rida"
    ],
    "name:sco_x_preferred":[
        "Merida"
    ],
    "name:tgl_x_preferred":[
        "Merida"
    ],
    "name:war_x_preferred":[
        "Merida"
    ],
    "wof:name":"Merida",
    "wof:placetype":"locality"
},
  "geometry": {"coordinates":[-85.56019000000001,11.44199],"type":"Point"}
}