{
  "type": "Feature",
  "properties": {
    "gn:admin1_code":"2.0",
    "gn:asciiname":"Las Esquinas",
    "gn:country_code":"NI",
    "gn:dem":187,
    "gn:feature_class":"P",
    "gn:feature_code":"PPL",
    "gn:name":"Las Esquinas",
    "gn:population":0,
    "gn:timezone":"America/Managua",
    "iso:country":"NI",
    "name:spa_x_preferred":[
        "Las Esquinas"
    ],
    "wof:name":"Las Esquinas",
    "wof:placetype":"locality"
},
  "geometry": {"coordinates":[-86.15488000000001,11.69197],"type":"Point"}
}