{
  "type": "Feature",
  "properties": {
    "gn:admin1_code":"10.0",
    "gn:asciiname":"Agua Dulce",
    "gn:country_code":"NI",
    "gn:dem":72,
    "gn:feature_class":"P",
    "gn:feature_code":"PPL",
    "gn:name":"Agua Dulce",
    "gn:population":0,
    "gn:timezone":"America/Managua",
    "iso:country":"NI",
    "wof:name":"Agua Dulce",
    "wof:placetype":"locality"
},
  "geometry": {"coordinates":[-86.16667,12.35],"type":"Point"}
}