{
  "type": "Feature",
  "properties": {
    "gn:admin1_code":"12.0",
    "gn:asciiname":"Washington",
    "gn:country_code":"NI",
    "gn:dem":473,
    "gn:feature_class":"P",
    "gn:feature_code":"PPL",
    "gn:name":"Washington",
    "gn:population":0,
    "gn:timezone":"America/Managua",
    "iso:country":"NI",
    "wof:name":"Washington",
    "wof:placetype":"locality"
},
  "geometry": {"coordinates":[-85.56616,12.96086],"type":"Point"}
}