{
  "type": "Feature",
  "properties": {
    "gn:admin1_code":"12.0",
    "gn:asciiname":"Kangrina",
    "gn:country_code":"NI",
    "gn:dem":83,
    "gn:feature_class":"P",
    "gn:feature_code":"PPL",
    "gn:name":"Kangrina",
    "gn:population":0,
    "gn:timezone":"America/Managua",
    "iso:country":"NI",
    "wof:name":"Kangrina",
    "wof:placetype":"locality"
},
  "geometry": {"coordinates":[-84.93465999999999,13.18298],"type":"Point"}
}