{
  "type": "Feature",
  "properties": {
    "gn:admin1_code":"8.0",
    "gn:asciiname":"San Jacinto",
    "gn:country_code":"NI",
    "gn:dem":198,
    "gn:feature_class":"P",
    "gn:feature_code":"PPL",
    "gn:name":"San Jacinto",
    "gn:population":0,
    "gn:timezone":"America/Managua",
    "iso:country":"NI",
    "wof:name":"San Jacinto",
    "wof:placetype":"locality"
},
  "geometry": {"coordinates":[-86.77684000000001,12.58248],"type":"Point"}
}