{
  "type": "Feature",
  "properties": {
    "gn:admin1_code":"1.0",
    "gn:asciiname":"El Roblar",
    "gn:country_code":"NI",
    "gn:dem":443,
    "gn:feature_class":"P",
    "gn:feature_code":"PPL",
    "gn:name":"El Roblar",
    "gn:population":0,
    "gn:timezone":"America/Managua",
    "iso:country":"NI",
    "wof:name":"El Roblar",
    "wof:placetype":"locality"
},
  "geometry": {"coordinates":[-85.50932,12.33094],"type":"Point"}
}