{
  "type": "Feature",
  "properties": {
    "gn:admin1_code":"6.0",
    "gn:asciiname":"Cutirre",
    "gn:country_code":"NI",
    "gn:dem":478,
    "gn:feature_class":"P",
    "gn:feature_code":"PPL",
    "gn:name":"Cutirre",
    "gn:population":0,
    "gn:timezone":"America/Managua",
    "iso:country":"NI",
    "wof:name":"Cutirre",
    "wof:placetype":"locality"
},
  "geometry": {"coordinates":[-85.93329,11.83154],"type":"Point"}
}