{
  "type": "Feature",
  "properties": {
    "gn:admin1_code":"3.0",
    "gn:asciiname":"Maderas Negras",
    "gn:cc2":"NI",
    "gn:country_code":"NI",
    "gn:dem":6,
    "gn:feature_class":"P",
    "gn:feature_code":"PPL",
    "gn:name":"Maderas Negras",
    "gn:population":0,
    "gn:timezone":"America/Managua",
    "iso:country":"NI",
    "name:und_x_variant":[
        "Caser\u00edo Maderas Negras",
        "Maderas Negras"
    ],
    "wof:name":"Maderas Negras",
    "wof:placetype":"locality"
},
  "geometry": {"coordinates":[-87.28333000000001,12.58333],"type":"Point"}
}