{
  "type": "Feature",
  "properties": {
    "gn:admin1_code":"17.0",
    "gn:asciiname":"Liwa Sirpe",
    "gn:country_code":"NI",
    "gn:dem":12,
    "gn:feature_class":"P",
    "gn:feature_code":"PPL",
    "gn:name":"Liwa Sirpe",
    "gn:population":0,
    "gn:timezone":"America/Managua",
    "iso:country":"NI",
    "wof:name":"Liwa Sirpe",
    "wof:placetype":"locality"
},
  "geometry": {"coordinates":[-83.39806,15.00669],"type":"Point"}
}