{
  "type": "Feature",
  "properties": {
    "gn:admin1_code":"3.0",
    "gn:asciiname":"Joaquin Zavala",
    "gn:country_code":"NI",
    "gn:dem":64,
    "gn:feature_class":"P",
    "gn:feature_code":"PPL",
    "gn:name":"Joaqu\u00edn Zavala",
    "gn:population":0,
    "gn:timezone":"America/Managua",
    "iso:country":"NI",
    "wof:name":"Joaquin Zavala",
    "wof:placetype":"locality"
},
  "geometry": {"coordinates":[-87.15000000000001,12.65],"type":"Point"}
}