{
  "type": "Feature",
  "properties": {
    "gn:admin1_code":"7.0",
    "gn:asciiname":"Tomatoya",
    "gn:country_code":"NI",
    "gn:dem":1051,
    "gn:feature_class":"P",
    "gn:feature_code":"PPL",
    "gn:name":"Tomatoya",
    "gn:population":0,
    "gn:timezone":"America/Managua",
    "iso:country":"NI",
    "wof:name":"Tomatoya",
    "wof:placetype":"locality"
},
  "geometry": {"coordinates":[-86.06416999999998,13.15012],"type":"Point"}
}