{
  "type": "Feature",
  "properties": {
    "gn:admin1_code":"2.0",
    "gn:asciiname":"San Presopio",
    "gn:country_code":"NI",
    "gn:dem":79,
    "gn:feature_class":"P",
    "gn:feature_code":"PPL",
    "gn:name":"San Presopio",
    "gn:population":0,
    "gn:timezone":"America/Managua",
    "iso:country":"NI",
    "name:spa_x_preferred":[
        "San Presopio"
    ],
    "wof:name":"San Presopio",
    "wof:placetype":"locality"
},
  "geometry": {"coordinates":[-86.00884000000001,11.71031],"type":"Point"}
}