{
  "type": "Feature",
  "properties": {
    "gn:admin1_code":"17.0",
    "gn:asciiname":"Uhri",
    "gn:country_code":"NI",
    "gn:dem":33,
    "gn:feature_class":"P",
    "gn:feature_code":"PPL",
    "gn:name":"Uhri",
    "gn:population":0,
    "gn:timezone":"America/Managua",
    "iso:country":"NI",
    "wof:name":"Uhri",
    "wof:placetype":"locality"
},
  "geometry": {"coordinates":[-83.83686,14.77044],"type":"Point"}
}