{
  "type": "Feature",
  "properties": {
    "gn:admin1_code":"18.0",
    "gn:asciiname":"Las Nubes",
    "gn:country_code":"NI",
    "gn:dem":86,
    "gn:feature_class":"P",
    "gn:feature_code":"PPL",
    "gn:name":"Las Nubes",
    "gn:population":0,
    "gn:timezone":"America/Managua",
    "iso:country":"NI",
    "wof:name":"Las Nubes",
    "wof:placetype":"locality"
},
  "geometry": {"coordinates":[-84.43977,12.12668],"type":"Point"}
}