{
  "type": "Feature",
  "properties": {
    "gn:admin1_code":"4.0",
    "gn:asciiname":"Bulun",
    "gn:country_code":"NI",
    "gn:dem":257,
    "gn:feature_class":"P",
    "gn:feature_code":"PPL",
    "gn:name":"Bul\u00fan",
    "gn:population":0,
    "gn:timezone":"America/Managua",
    "iso:country":"NI",
    "wof:name":"Bulun",
    "wof:placetype":"locality"
},
  "geometry": {"coordinates":[-84.90886999999999,12.21412],"type":"Point"}
}