{
  "type": "Feature",
  "properties": {
    "gn:admin1_code":"18.0",
    "gn:asciiname":"Santa Julia",
    "gn:country_code":"NI",
    "gn:dem":187,
    "gn:feature_class":"P",
    "gn:feature_code":"PPL",
    "gn:name":"Santa Julia",
    "gn:population":0,
    "gn:timezone":"America/Managua",
    "iso:country":"NI",
    "wof:name":"Santa Julia",
    "wof:placetype":"locality"
},
  "geometry": {"coordinates":[-84.81808000000002,12.38966],"type":"Point"}
}