{
  "type": "Feature",
  "properties": {
    "gn:admin1_code":"12.0",
    "gn:asciiname":"Llano El Boqueron",
    "gn:country_code":"NI",
    "gn:dem":918,
    "gn:feature_class":"P",
    "gn:feature_code":"PPL",
    "gn:name":"Llano El Boquer\u00f3n",
    "gn:population":0,
    "gn:timezone":"America/Managua",
    "iso:country":"NI",
    "wof:name":"Llano El Boqueron",
    "wof:placetype":"locality"
},
  "geometry": {"coordinates":[-86.27079000000001,12.84409],"type":"Point"}
}