{
  "type": "Feature",
  "properties": {
    "gn:admin1_code":"17.0",
    "gn:asciiname":"Karata",
    "gn:country_code":"NI",
    "gn:dem":2,
    "gn:feature_class":"P",
    "gn:feature_code":"PPL",
    "gn:name":"Karat\u00e1",
    "gn:population":0,
    "gn:timezone":"America/Managua",
    "iso:country":"NI",
    "name:ceb_x_preferred":[
        "Karata"
    ],
    "name:swe_x_preferred":[
        "Karata"
    ],
    "name:und_x_variant":[
        "Carata",
        "Karat\u00e1"
    ],
    "wof:name":"Karata",
    "wof:placetype":"locality"
},
  "geometry": {"coordinates":[-83.48090999999999,13.92543],"type":"Point"}
}