{
  "type": "Feature",
  "properties": {
    "gn:admin1_code":"6.0",
    "gn:asciiname":"Barrio La Cruz",
    "gn:country_code":"NI",
    "gn:dem":54,
    "gn:feature_class":"P",
    "gn:feature_code":"PPL",
    "gn:name":"Barrio La Cruz",
    "gn:population":0,
    "gn:timezone":"America/Managua",
    "iso:country":"NI",
    "name:spa_x_preferred":[
        "Barrio La Cruz"
    ],
    "wof:name":"Barrio La Cruz",
    "wof:placetype":"locality"
},
  "geometry": {"coordinates":[-85.95428000000003,11.9475],"type":"Point"}
}