{
  "type": "Feature",
  "properties": {
    "gn:admin1_code":"6.0",
    "gn:asciiname":"Cana de Castilla",
    "gn:country_code":"NI",
    "gn:dem":343,
    "gn:feature_class":"P",
    "gn:feature_code":"PPL",
    "gn:name":"Ca\u00f1a de Castilla",
    "gn:population":0,
    "gn:timezone":"America/Managua",
    "iso:country":"NI",
    "wof:name":"Cana de Castilla",
    "wof:placetype":"locality"
},
  "geometry": {"coordinates":[-85.99101,11.85865],"type":"Point"}
}