{
  "type": "Feature",
  "properties": {
    "gn:admin1_code":"12.0",
    "gn:asciiname":"Maunica",
    "gn:country_code":"NI",
    "gn:dem":571,
    "gn:feature_class":"P",
    "gn:feature_code":"PPL",
    "gn:name":"Maunica",
    "gn:population":0,
    "gn:timezone":"America/Managua",
    "iso:country":"NI",
    "wof:name":"Maunica",
    "wof:placetype":"locality"
},
  "geometry": {"coordinates":[-86.04438,12.76961],"type":"Point"}
}