{
  "type": "Feature",
  "properties": {
    "gn:admin1_code":"8.0",
    "gn:asciiname":"El Coco",
    "gn:country_code":"NI",
    "gn:dem":182,
    "gn:feature_class":"P",
    "gn:feature_code":"PPL",
    "gn:name":"El Coco",
    "gn:population":0,
    "gn:timezone":"America/Managua",
    "iso:country":"NI",
    "wof:name":"El Coco",
    "wof:placetype":"locality"
},
  "geometry": {"coordinates":[-86.51434999999999,12.82876],"type":"Point"}
}