{
  "type": "Feature",
  "properties": {
    "gn:admin1_code":"12.0",
    "gn:asciiname":"Caratera",
    "gn:cc2":"NI",
    "gn:country_code":"NI",
    "gn:dem":769,
    "gn:feature_class":"P",
    "gn:feature_code":"PPL",
    "gn:name":"Caratera",
    "gn:population":0,
    "gn:timezone":"America/Managua",
    "iso:country":"NI",
    "name:und_x_variant":[
        "Carratera",
        "Caratera"
    ],
    "wof:name":"Caratera",
    "wof:placetype":"locality"
},
  "geometry": {"coordinates":[-85.71666999999999,13.16667],"type":"Point"}
}