{
  "type": "Feature",
  "properties": {
    "gn:country":"NI",
    "gn:fcode":"PPL",
    "gn:pop":7872,
    "iso:country":"NI",
    "name:eng_x_preferred":[
        "Bocana de Paiwas"
    ],
    "name:fra_x_preferred":[
        "Bocana de Paiwas"
    ],
    "name:ita_x_preferred":[
        "Paiwas"
    ],
    "name:nld_x_preferred":[
        "Bocana de Paiwas"
    ],
    "name:spa_x_preferred":[
        "Paiwas"
    ],
    "name:swe_x_preferred":[
        "Bocana de Paiwas"
    ],
    "name:unk_x_variant":[
        "Paiwas"
    ],
    "name:urd_x_preferred":[
        "\u0628\u0648\u06a9\u0627\u0646\u0627 \u062f\u06d2 \u067e\u0627\u06cc\u0648\u0627\u0633"
    ],
    "name:vie_x_preferred":[
        "Paiwas"
    ],
    "name:zho_x_preferred":[
        "\u6d3e\u74e6\u65af"
    ],
    "qs:name":"Bocana de Paiwas",
    "qs:photos_9r":0,
    "qs:photos_sr":0,
    "qs:pop_sr":"5",
    "wd:wordcount":37,
    "wof:name":"Bocana de Paiwas",
    "wof:placetype":"locality",
    "wof:population":7872
},
  "geometry": {"coordinates":[-85.12269000000001,12.78571],"type":"Point"}
}