{
  "type": "Feature",
  "properties": {
    "gn:admin1_code":"15.0",
    "gn:asciiname":"Tierra Blanca",
    "gn:country_code":"NI",
    "gn:dem":70,
    "gn:feature_class":"P",
    "gn:feature_code":"PPL",
    "gn:name":"Tierra Blanca",
    "gn:population":0,
    "gn:timezone":"America/Managua",
    "iso:country":"NI",
    "name:ceb_x_preferred":[
        "Tierra Blanca"
    ],
    "name:deu_x_preferred":[
        "Tierra Blanca"
    ],
    "name:ita_x_preferred":[
        "Tierra Blanca"
    ],
    "name:pol_x_preferred":[
        "Tierra Blanca"
    ],
    "name:por_x_preferred":[
        "Tierra Blanca"
    ],
    "name:sco_x_preferred":[
        "Tierra Blanca"
    ],
    "name:spa_x_preferred":[
        "Tierra Blanca"
    ],
    "name:swe_x_preferred":[
        "Tierra Blanca"
    ],
    "wof:name":"Tierra Blanca",
    "wof:placetype":"locality"
},
  "geometry": {"coordinates":[-85.89908,11.5588],"type":"Point"}
}