{
  "type": "Feature",
  "properties": {
    "gn:admin1_code":"1.0",
    "gn:asciiname":"Guirruca",
    "gn:country_code":"NI",
    "gn:dem":499,
    "gn:feature_class":"P",
    "gn:feature_code":"PPL",
    "gn:name":"Guirruca",
    "gn:population":0,
    "gn:timezone":"America/Managua",
    "iso:country":"NI",
    "wof:name":"Guirruca",
    "wof:placetype":"locality"
},
  "geometry": {"coordinates":[-85.59931,12.44995],"type":"Point"}
}