{
  "type": "Feature",
  "properties": {
    "gn:admin1_code":"2.0",
    "gn:asciiname":"El Perdenal",
    "gn:country_code":"NI",
    "gn:dem":231,
    "gn:feature_class":"P",
    "gn:feature_code":"PPL",
    "gn:name":"El Perdenal",
    "gn:population":0,
    "gn:timezone":"America/Managua",
    "iso:country":"NI",
    "name:spa_x_preferred":[
        "El Perdenal"
    ],
    "wof:name":"El Perdenal",
    "wof:placetype":"locality"
},
  "geometry": {"coordinates":[-86.14584000000001,11.72741],"type":"Point"}
}