{
  "type": "Feature",
  "properties": {
    "gn:admin1_code":"2.0",
    "gn:asciiname":"La Marchenena",
    "gn:country_code":"NI",
    "gn:dem":658,
    "gn:feature_class":"P",
    "gn:feature_code":"PPL",
    "gn:name":"La Marchene\u00f1a",
    "gn:population":0,
    "gn:timezone":"America/Managua",
    "iso:country":"NI",
    "wof:name":"La Marchenena",
    "wof:placetype":"locality"
},
  "geometry": {"coordinates":[-86.30938,11.92061],"type":"Point"}
}