{
  "type": "Feature",
  "properties": {
    "gn:admin1_code":"8.0",
    "gn:asciiname":"Paso Picado",
    "gn:country_code":"NI",
    "gn:dem":25,
    "gn:feature_class":"P",
    "gn:feature_code":"PPL",
    "gn:name":"Paso Picado",
    "gn:population":0,
    "gn:timezone":"America/Managua",
    "iso:country":"NI",
    "wof:name":"Paso Picado",
    "wof:placetype":"locality"
},
  "geometry": {"coordinates":[-86.82129999999999,12.70929],"type":"Point"}
}