{
  "type": "Feature",
  "properties": {
    "gn:admin1_code":"3.0",
    "gn:asciiname":"El Salvador",
    "gn:cc2":"NI",
    "gn:country_code":"NI",
    "gn:dem":18,
    "gn:feature_class":"P",
    "gn:feature_code":"PPL",
    "gn:name":"El Salvador",
    "gn:population":0,
    "gn:timezone":"America/Managua",
    "iso:country":"NI",
    "name:und_x_variant":[
        "Salvador",
        "El Salvador"
    ],
    "wof:name":"El Salvador",
    "wof:placetype":"locality"
},
  "geometry": {"coordinates":[-87.33333,12.71667],"type":"Point"}
}