{
  "type": "Feature",
  "properties": {
    "gn:admin1_code":"7.0",
    "gn:asciiname":"Colon",
    "gn:country_code":"NI",
    "gn:dem":702,
    "gn:feature_class":"P",
    "gn:feature_code":"PPL",
    "gn:name":"Col\u00f3n",
    "gn:population":0,
    "gn:timezone":"America/Managua",
    "iso:country":"NI",
    "name:und_x_variant":[
        "Yupal\u00ed",
        "Col\u00f3n"
    ],
    "wof:name":"Colon",
    "wof:placetype":"locality"
},
  "geometry": {"coordinates":[-86.15649000000001,13.10789],"type":"Point"}
}