{
  "type": "Feature",
  "properties": {
    "gn:admin1_code":"10.0",
    "gn:asciiname":"San Emilio",
    "gn:country_code":"NI",
    "gn:dem":83,
    "gn:feature_class":"P",
    "gn:feature_code":"PPL",
    "gn:name":"San Emilio",
    "gn:population":0,
    "gn:timezone":"America/Managua",
    "iso:country":"NI",
    "wof:name":"San Emilio",
    "wof:placetype":"locality"
},
  "geometry": {"coordinates":[-86.03285,12.31057],"type":"Point"}
}