{
  "type": "Feature",
  "properties": {
    "gn:admin1_code":"10.0",
    "gn:asciiname":"San Emilio",
    "gn:country_code":"NI",
    "gn:dem":83,
    "gn:feature_class":"P",
    "gn:feature_code":"PPL",
    "gn:name":"San Emilio",
    "gn:population":0,
    "gn:timezone":"America/Managua",
    "iso:country":"NI",
    "name:bcl_x_preferred":[
        "San Emilio"
    ],
    "name:ceb_x_preferred":[
        "San Emilio"
    ],
    "name:deu_x_preferred":[
        "San Emilio"
    ],
    "name:fra_x_preferred":[
        "San Emilio"
    ],
    "name:ilo_x_preferred":[
        "San Emilio"
    ],
    "name:ind_x_preferred":[
        "San Emilio"
    ],
    "name:ita_x_preferred":[
        "San Emilio"
    ],
    "name:nld_x_preferred":[
        "San Emilio"
    ],
    "name:pag_x_preferred":[
        "San Emilio"
    ],
    "name:pam_x_preferred":[
        "San Emilio"
    ],
    "name:spa_x_preferred":[
        "San Emilio"
    ],
    "name:swe_x_preferred":[
        "San Emilio"
    ],
    "name:tgl_x_preferred":[
        "San Emilio"
    ],
    "name:vie_x_preferred":[
        "San Emilio"
    ],
    "name:war_x_preferred":[
        "San Emilio"
    ],
    "wof:name":"San Emilio",
    "wof:placetype":"locality"
},
  "geometry": {"coordinates":[-86.03285,12.31057],"type":"Point"}
}