{
  "type": "Feature",
  "properties": {
    "gn:admin1_code":"12.0",
    "gn:asciiname":"Los Cardones",
    "gn:country_code":"NI",
    "gn:dem":591,
    "gn:feature_class":"P",
    "gn:feature_code":"PPL",
    "gn:name":"Los Cardones",
    "gn:population":0,
    "gn:timezone":"America/Managua",
    "iso:country":"NI",
    "wof:name":"Los Cardones",
    "wof:placetype":"locality"
},
  "geometry": {"coordinates":[-86.05619,12.88479],"type":"Point"}
}