{
  "type": "Feature",
  "properties": {
    "gn:admin1_code":"15.0",
    "gn:asciiname":"Salinas",
    "gn:country_code":"NI",
    "gn:dem":12,
    "gn:feature_class":"P",
    "gn:feature_code":"PPL",
    "gn:name":"Salinas",
    "gn:population":0,
    "gn:timezone":"America/Managua",
    "iso:country":"NI",
    "name:und_x_variant":[
        "Las Salinas",
        "Salinas"
    ],
    "wof:name":"Salinas",
    "wof:placetype":"locality"
},
  "geometry": {"coordinates":[-86.10429999999999,11.47568],"type":"Point"}
}