{
  "type": "Feature",
  "properties": {
    "gn:admin1_code":"12.0",
    "gn:asciiname":"Valle San Antonio",
    "gn:country_code":"NI",
    "gn:dem":431,
    "gn:feature_class":"P",
    "gn:feature_code":"PPL",
    "gn:name":"Valle San Antonio",
    "gn:population":0,
    "gn:timezone":"America/Managua",
    "iso:country":"NI",
    "wof:name":"Valle San Antonio",
    "wof:placetype":"locality"
},
  "geometry": {"coordinates":[-86.10309000000002,12.65875],"type":"Point"}
}