{
  "type": "Feature",
  "properties": {
    "gn:admin1_code":"10.0",
    "gn:asciiname":"Comarca Los Ladinos",
    "gn:country_code":"NI",
    "gn:dem":296,
    "gn:feature_class":"P",
    "gn:feature_code":"PPL",
    "gn:name":"Comarca Los Ladinos",
    "gn:population":0,
    "gn:timezone":"America/Managua",
    "iso:country":"NI",
    "wof:name":"Comarca Los Ladinos",
    "wof:placetype":"locality"
},
  "geometry": {"coordinates":[-86.29054000000002,12.09267],"type":"Point"}
}