{
  "type": "Feature",
  "properties": {
    "gn:admin1_code":"17.0",
    "gn:asciiname":"Wakaban",
    "gn:country_code":"NI",
    "gn:dem":17,
    "gn:feature_class":"P",
    "gn:feature_code":"PPL",
    "gn:name":"Wakaban",
    "gn:population":0,
    "gn:timezone":"America/Managua",
    "iso:country":"NI",
    "wof:name":"Wakaban",
    "wof:placetype":"locality"
},
  "geometry": {"coordinates":[-83.59048,14.07708],"type":"Point"}
}