{
  "type": "Feature",
  "properties": {
    "gn:admin1_code":"8.0",
    "gn:asciiname":"Los Riitos",
    "gn:country_code":"NI",
    "gn:dem":52,
    "gn:feature_class":"P",
    "gn:feature_code":"PPL",
    "gn:name":"Los Riitos",
    "gn:population":0,
    "gn:timezone":"America/Managua",
    "iso:country":"NI",
    "wof:name":"Los Riitos",
    "wof:placetype":"locality"
},
  "geometry": {"coordinates":[-86.45844,12.50497],"type":"Point"}
}