{
  "type": "Feature",
  "properties": {
    "gn:admin1_code":"8.0",
    "gn:asciiname":"Jinocuabo",
    "gn:country_code":"NI",
    "gn:dem":108,
    "gn:feature_class":"P",
    "gn:feature_code":"PPL",
    "gn:name":"Ji\u00f1ocuabo",
    "gn:population":0,
    "gn:timezone":"America/Managua",
    "iso:country":"NI",
    "wof:name":"Jinocuabo",
    "wof:placetype":"locality"
},
  "geometry": {"coordinates":[-86.5949,12.68184],"type":"Point"}
}