{
  "type": "Feature",
  "properties": {
    "gn:admin1_code":"18.0",
    "gn:asciiname":"Chalmeca",
    "gn:country_code":"NI",
    "gn:dem":7,
    "gn:feature_class":"P",
    "gn:feature_code":"PPL",
    "gn:name":"Chalmeca",
    "gn:population":0,
    "gn:timezone":"America/Managua",
    "iso:country":"NI",
    "wof:name":"Chalmeca",
    "wof:placetype":"locality"
},
  "geometry": {"coordinates":[-84.09713000000001,12.12956],"type":"Point"}
}