{
  "type": "Feature",
  "properties": {
    "gn:admin1_code":"14.0",
    "gn:asciiname":"Cabanga",
    "gn:country_code":"NI",
    "gn:dem":32,
    "gn:feature_class":"P",
    "gn:feature_code":"PPL",
    "gn:name":"Cabanga",
    "gn:population":0,
    "gn:timezone":"America/Managua",
    "iso:country":"NI",
    "wof:name":"Cabanga",
    "wof:placetype":"locality"
},
  "geometry": {"coordinates":[-84.93185,10.95772],"type":"Point"}
}