{
  "type": "Feature",
  "properties": {
    "gn:admin1_code":"6.0",
    "gn:asciiname":"El Eslabon",
    "gn:country_code":"NI",
    "gn:dem":139,
    "gn:feature_class":"P",
    "gn:feature_code":"PPL",
    "gn:name":"El Eslab\u00f3n",
    "gn:population":0,
    "gn:timezone":"America/Managua",
    "iso:country":"NI",
    "wof:name":"El Eslabon",
    "wof:placetype":"locality"
},
  "geometry": {"coordinates":[-86.1259,11.63905],"type":"Point"}
}