{
  "type": "Feature",
  "properties": {
    "gn:admin1_code":"6.0",
    "gn:asciiname":"La Auroia",
    "gn:country_code":"NI",
    "gn:dem":110,
    "gn:feature_class":"P",
    "gn:feature_code":"PPL",
    "gn:name":"La Auroia",
    "gn:population":0,
    "gn:timezone":"America/Managua",
    "iso:country":"NI",
    "name:spa_x_preferred":[
        "La Auroia"
    ],
    "wof:name":"La Auroia",
    "wof:placetype":"locality"
},
  "geometry": {"coordinates":[-85.97483000000003,11.91274],"type":"Point"}
}