{
  "type": "Feature",
  "properties": {
    "gn:admin1_code":"4.0",
    "gn:asciiname":"Los Bueyes",
    "gn:country_code":"NI",
    "gn:dem":102,
    "gn:feature_class":"P",
    "gn:feature_code":"PPL",
    "gn:name":"Los Bueyes",
    "gn:population":0,
    "gn:timezone":"America/Managua",
    "iso:country":"NI",
    "wof:name":"Los Bueyes",
    "wof:placetype":"locality"
},
  "geometry": {"coordinates":[-85.14039,11.85334],"type":"Point"}
}