{
  "type": "Feature",
  "properties": {
    "gn:admin1_code":"18.0",
    "gn:asciiname":"Tasbapauni",
    "gn:country_code":"NI",
    "gn:dem":6,
    "gn:feature_class":"P",
    "gn:feature_code":"PPL",
    "gn:name":"Tasbapauni",
    "gn:population":0,
    "gn:timezone":"America/Managua",
    "iso:country":"NI",
    "name:und_x_variant":[
        "Tasbapone",
        "Tasbapawnie",
        "Tierra Colorada",
        "Tasbapauni"
    ],
    "wof:name":"Tasbapauni",
    "wof:placetype":"locality"
},
  "geometry": {"coordinates":[-83.54489000000002,12.67301],"type":"Point"}
}