{
  "type": "Feature",
  "properties": {
    "gn:admin1_code":"12.0",
    "gn:asciiname":"Valle El Nisperal",
    "gn:country_code":"NI",
    "gn:dem":498,
    "gn:feature_class":"P",
    "gn:feature_code":"PPL",
    "gn:name":"Valle El Nisperal",
    "gn:population":0,
    "gn:timezone":"America/Managua",
    "iso:country":"NI",
    "wof:name":"Valle El Nisperal",
    "wof:placetype":"locality"
},
  "geometry": {"coordinates":[-86.02016999999999,12.5804],"type":"Point"}
}