{
  "type": "Feature",
  "properties": {
    "gn:admin1_code":"12.0",
    "gn:asciiname":"Paiwas",
    "gn:country_code":"NI",
    "gn:dem":208,
    "gn:feature_class":"P",
    "gn:feature_code":"PPL",
    "gn:name":"Paiw\u00e1s",
    "gn:population":0,
    "gn:timezone":"America/Managua",
    "iso:country":"NI",
    "wof:name":"Paiwas",
    "wof:placetype":"locality"
},
  "geometry": {"coordinates":[-85.23751,12.84803],"type":"Point"}
}