{
  "type": "Feature",
  "properties": {
    "iso:country":"NI",
    "name:deu_x_preferred":[
        "El Castillo"
    ],
    "name:eng_x_preferred":[
        "El Castillo"
    ],
    "name:fra_x_preferred":[
        "El Castillo"
    ],
    "name:ita_x_preferred":[
        "El Castillo"
    ],
    "name:jpn_x_preferred":[
        "\u30a8\u30eb\u30ab\u30b9\u30c6\u30a3\u30fc\u30e8"
    ],
    "name:nld_x_preferred":[
        "El Castillo"
    ],
    "name:spa_x_preferred":[
        "El Castillo"
    ],
    "name:swe_x_preferred":[
        "El Castillo"
    ],
    "name:und_x_variant":[
        "Castillo"
    ],
    "name:urd_x_preferred":[
        "\u0627\u06cc\u0644 \u06a9\u0627\u0633\u062a\u06cc\u0644\u0648"
    ],
    "name:vie_x_preferred":[
        "El Castillo"
    ],
    "name:zho_x_preferred":[
        "\u57c3\u723e\u5361\u65af\u8482\u7565"
    ],
    "qs:gn_country":"NI",
    "qs:gn_fcode":"PPL",
    "qs:gn_pop":735,
    "qs:name":"El Castillo de La Concepci\u00f3n",
    "qs:name_adm0":"Nicaragua",
    "qs:name_adm1":"R\u00edo San Juan",
    "qs:photos":455,
    "qs:photos_1k":92,
    "qs:photos_9k":2,
    "qs:photos_9r":5,
    "qs:photos_all":455,
    "qs:photos_sr":7,
    "qs:placetype":"Town",
    "qs:pop_sr":"2",
    "qs:woe_adm0":23424915,
    "wof:name":"El Castillo de La Concepci\u00f3n",
    "wof:placetype":"locality",
    "wof:population":735
},
  "geometry": {"coordinates":[-84.39811,11.01844],"type":"Point"}
}