{
  "type": "Feature",
  "properties": {
    "gn:admin1_code":"17.0",
    "gn:asciiname":"Iskri",
    "gn:country_code":"NI",
    "gn:dem":4,
    "gn:feature_class":"P",
    "gn:feature_code":"PPL",
    "gn:name":"Iskri",
    "gn:population":0,
    "gn:timezone":"America/Managua",
    "iso:country":"NI",
    "wof:name":"Iskri",
    "wof:placetype":"locality"
},
  "geometry": {"coordinates":[-83.58035,13.86556],"type":"Point"}
}