{
  "type": "Feature",
  "properties": {
    "gn:admin1_code":"17.0",
    "gn:asciiname":"Wirapahani",
    "gn:country_code":"NI",
    "gn:dem":57,
    "gn:feature_class":"P",
    "gn:feature_code":"PPL",
    "gn:name":"Wirapahani",
    "gn:population":0,
    "gn:timezone":"America/Managua",
    "iso:country":"NI",
    "wof:name":"Wirapahani",
    "wof:placetype":"locality"
},
  "geometry": {"coordinates":[-84.25,14.68333],"type":"Point"}
}