{
  "type": "Feature",
  "properties": {
    "gn:admin1_code":"6.0",
    "gn:asciiname":"La Guinea",
    "gn:country_code":"NI",
    "gn:dem":48,
    "gn:feature_class":"P",
    "gn:feature_code":"PPL",
    "gn:name":"La Guinea",
    "gn:population":0,
    "gn:timezone":"America/Managua",
    "iso:country":"NI",
    "name:ita_x_preferred":[
        "La Guinea"
    ],
    "name:spa_x_preferred":[
        "La Guinea"
    ],
    "name:zho_x_preferred":[
        "\u62c9\u5e7e\u5167\u4e9e"
    ],
    "wof:name":"La Guinea",
    "wof:placetype":"locality"
},
  "geometry": {"coordinates":[-85.82516,11.71483],"type":"Point"}
}