{
  "type": "Feature",
  "properties": {
    "iso:country":"NI",
    "name:ceb_x_preferred":[
        "Nandaime"
    ],
    "name:chi_x_preferred":[
        "\u5357\u4ee3\u6885"
    ],
    "name:deu_x_preferred":[
        "Nandaime"
    ],
    "name:dut_x_preferred":[
        "Nandaime"
    ],
    "name:ell_x_preferred":[
        "\u039d\u03b1\u03bd\u03c4\u03ac\u03b9\u03bc\u03b5"
    ],
    "name:eng_x_preferred":[
        "Nandaime"
    ],
    "name:fra_x_preferred":[
        "Nandaime"
    ],
    "name:fre_x_preferred":[
        "Nandaime"
    ],
    "name:ger_x_preferred":[
        "Nandaime"
    ],
    "name:gre_x_preferred":[
        "\u039d\u03b1\u03bd\u03c4\u03ac\u03b9\u03bc\u03b5"
    ],
    "name:ita_x_preferred":[
        "Nandaime"
    ],
    "name:nld_x_preferred":[
        "Nandaime"
    ],
    "name:pol_x_preferred":[
        "Nandaime"
    ],
    "name:spa_x_preferred":[
        "Nandaime"
    ],
    "name:swe_x_preferred":[
        "Nandaime"
    ],
    "name:urd_x_preferred":[
        "\u0646\u0627\u0646\u062f\u0627\u06cc\u0645\u06d2"
    ],
    "name:vie_x_preferred":[
        "Nandaime"
    ],
    "name:zho_x_preferred":[
        "\u5357\u4ee3\u6885"
    ],
    "qs:gn_country":"NI",
    "qs:gn_fcode":"PPL",
    "qs:gn_pop":20810,
    "qs:name":"Nandaime",
    "qs:name_adm0":"Nicaragua",
    "qs:name_adm1":"Granada",
    "qs:photos":53,
    "qs:photos_1k":11,
    "qs:photos_9k":1,
    "qs:photos_9r":2,
    "qs:photos_all":53,
    "qs:photos_sr":2,
    "qs:placetype":"Town",
    "qs:pop_sr":"7",
    "qs:woe_adm0":23424915,
    "wof:name":"Nandaime",
    "wof:placetype":"locality",
    "wof:population":20810
},
  "geometry": {"coordinates":[-86.05286,11.75696],"type":"Point"}
}