{
  "type": "Feature",
  "properties": {
    "gn:admin1_code":"8.0",
    "gn:asciiname":"Las Colinas",
    "gn:country_code":"NI",
    "gn:dem":186,
    "gn:feature_class":"P",
    "gn:feature_code":"PPL",
    "gn:name":"Las Colinas",
    "gn:population":0,
    "gn:timezone":"America/Managua",
    "iso:country":"NI",
    "name:spa_x_preferred":[
        "Las Colinas"
    ],
    "wof:name":"Las Colinas",
    "wof:placetype":"locality"
},
  "geometry": {"coordinates":[-86.90000000000001,12.56821],"type":"Point"}
}