{
  "type": "Feature",
  "properties": {
    "gn:admin1_code":"17.0",
    "gn:asciiname":"Sainica",
    "gn:country_code":"NI",
    "gn:dem":8,
    "gn:feature_class":"P",
    "gn:feature_code":"PPL",
    "gn:name":"Sainica",
    "gn:population":0,
    "gn:timezone":"America/Managua",
    "iso:country":"NI",
    "name:und_x_variant":[
        "Saynika",
        "Sainica"
    ],
    "wof:name":"Sainica",
    "wof:placetype":"locality"
},
  "geometry": {"coordinates":[-83.61416,14.87945],"type":"Point"}
}