{
  "type": "Feature",
  "properties": {
    "gn:admin1_code":"12.0",
    "gn:asciiname":"San Juanillo",
    "gn:country_code":"NI",
    "gn:dem":406,
    "gn:feature_class":"P",
    "gn:feature_code":"PPL",
    "gn:name":"San Juanillo",
    "gn:population":0,
    "gn:timezone":"America/Managua",
    "iso:country":"NI",
    "wof:name":"San Juanillo",
    "wof:placetype":"locality"
},
  "geometry": {"coordinates":[-86.05110000000001,12.69839],"type":"Point"}
}