{
  "type": "Feature",
  "properties": {
    "gn:admin1_code":"10.0",
    "gn:asciiname":"Colonia Molina",
    "gn:country_code":"NI",
    "gn:dem":162,
    "gn:feature_class":"P",
    "gn:feature_code":"PPL",
    "gn:name":"Colonia Molina",
    "gn:population":0,
    "gn:timezone":"America/Managua",
    "iso:country":"NI",
    "wof:name":"Colonia Molina",
    "wof:placetype":"locality"
},
  "geometry": {"coordinates":[-86.31667,12.11667],"type":"Point"}
}