{
  "type": "Feature",
  "properties": {
    "gn:admin1_code":"6.0",
    "gn:asciiname":"El Carrizal",
    "gn:country_code":"NI",
    "gn:dem":41,
    "gn:feature_class":"P",
    "gn:feature_code":"PPL",
    "gn:name":"El Carrizal",
    "gn:population":0,
    "gn:timezone":"America/Managua",
    "iso:country":"NI",
    "wof:name":"El Carrizal",
    "wof:placetype":"locality"
},
  "geometry": {"coordinates":[-85.83704,11.76356],"type":"Point"}
}