{
  "type": "Feature",
  "properties": {
    "gn:admin1_code":"18.0",
    "gn:asciiname":"Los Leiva",
    "gn:country_code":"NI",
    "gn:dem":63,
    "gn:feature_class":"P",
    "gn:feature_code":"PPL",
    "gn:name":"Los Leiva",
    "gn:population":0,
    "gn:timezone":"America/Managua",
    "iso:country":"NI",
    "wof:name":"Los Leiva",
    "wof:placetype":"locality"
},
  "geometry": {"coordinates":[-84.1254,12.21124],"type":"Point"}
}