{
  "type": "Feature",
  "properties": {
    "gn:admin1_code":"15.0",
    "gn:asciiname":"La Flor",
    "gn:country_code":"NI",
    "gn:dem":20,
    "gn:feature_class":"P",
    "gn:feature_code":"PPL",
    "gn:name":"La Flor",
    "gn:population":0,
    "gn:timezone":"America/Managua",
    "iso:country":"NI",
    "name:fra_x_preferred":[
        "La flor"
    ],
    "name:und_x_variant":[
        "Flor",
        "La Flor"
    ],
    "wof:name":"La Flor",
    "wof:placetype":"locality"
},
  "geometry": {"coordinates":[-85.93966999999998,11.38486],"type":"Point"}
}