{
  "type": "Feature",
  "properties": {
    "gn:admin1_code":"17.0",
    "gn:asciiname":"Torre Dos",
    "gn:country_code":"NI",
    "gn:dem":80,
    "gn:feature_class":"P",
    "gn:feature_code":"PPL",
    "gn:name":"Torre Dos",
    "gn:population":0,
    "gn:timezone":"America/Managua",
    "iso:country":"NI",
    "wof:name":"Torre Dos",
    "wof:placetype":"locality"
},
  "geometry": {"coordinates":[-83.77588,14.75333],"type":"Point"}
}