{
  "type": "Feature",
  "properties": {
    "gn:admin1_code":"5.0",
    "gn:asciiname":"El Espinal",
    "gn:cc2":"NI",
    "gn:country_code":"NI",
    "gn:dem":997,
    "gn:feature_class":"P",
    "gn:feature_code":"PPL",
    "gn:name":"El Espinal",
    "gn:population":0,
    "gn:timezone":"America/Managua",
    "iso:country":"NI",
    "name:und_x_variant":[
        "Espinol",
        "Espinal",
        "El Espinal"
    ],
    "wof:name":"El Espinal",
    "wof:placetype":"locality"
},
  "geometry": {"coordinates":[-86.28333000000001,13.05],"type":"Point"}
}