{
  "type": "Feature",
  "properties": {
    "gn:admin1_code":"15.0",
    "gn:asciiname":"Nancimi",
    "gn:country_code":"NI",
    "gn:dem":70,
    "gn:feature_class":"P",
    "gn:feature_code":"PPL",
    "gn:name":"Nancim\u00ed",
    "gn:population":0,
    "gn:timezone":"America/Managua",
    "iso:country":"NI",
    "name:und_x_variant":[
        "Nancemi",
        "Nancim\u00ed"
    ],
    "wof:name":"Nancimi",
    "wof:placetype":"locality"
},
  "geometry": {"coordinates":[-85.96011999999997,11.47269],"type":"Point"}
}