{
  "type": "Feature",
  "properties": {
    "gn:admin1_code":"10.0",
    "gn:asciiname":"Ingenio Santa Rita",
    "gn:country_code":"NI",
    "gn:dem":127,
    "gn:feature_class":"P",
    "gn:feature_code":"PPL",
    "gn:name":"Ingenio Santa Rita",
    "gn:population":0,
    "gn:timezone":"America/Managua",
    "iso:country":"NI",
    "name:und_x_variant":[
        "Monte Fresco",
        "Santa Rita",
        "Ingenio Santa Rita"
    ],
    "wof:name":"Ingenio Santa Rita",
    "wof:placetype":"locality"
},
  "geometry": {"coordinates":[-86.50144,12.0622],"type":"Point"}
}