{
  "type": "Feature",
  "properties": {
    "gn:admin1_code":"1.0",
    "gn:asciiname":"Las Lagunas",
    "gn:country_code":"NI",
    "gn:dem":536,
    "gn:feature_class":"P",
    "gn:feature_code":"PPL",
    "gn:name":"Las Lagunas",
    "gn:population":0,
    "gn:timezone":"America/Managua",
    "iso:country":"NI",
    "name:ceb_x_preferred":[
        "Las Lagunas"
    ],
    "name:spa_x_preferred":[
        "Las Lagunas"
    ],
    "name:srp_x_preferred":[
        "\u041b\u0430\u0441 \u041b\u0430\u0433\u0443\u043d\u0430\u0441"
    ],
    "name:swe_x_preferred":[
        "Las Lagunas"
    ],
    "wof:name":"Las Lagunas",
    "wof:placetype":"locality"
},
  "geometry": {"coordinates":[-85.61359,12.46805],"type":"Point"}
}