{
  "type": "Feature",
  "properties": {
    "gn:admin1_code":"3.0",
    "gn:asciiname":"La Pita",
    "gn:country_code":"NI",
    "gn:dem":105,
    "gn:feature_class":"P",
    "gn:feature_code":"PPL",
    "gn:name":"La Pita",
    "gn:population":0,
    "gn:timezone":"America/Managua",
    "iso:country":"NI",
    "wof:name":"La Pita",
    "wof:placetype":"locality"
},
  "geometry": {"coordinates":[-87.34012,12.77675],"type":"Point"}
}