{
  "type": "Feature",
  "properties": {
    "gn:admin1_code":"7.0",
    "gn:asciiname":"La Rica",
    "gn:country_code":"NI",
    "gn:dem":867,
    "gn:feature_class":"P",
    "gn:feature_code":"PPL",
    "gn:name":"La Rica",
    "gn:population":0,
    "gn:timezone":"America/Managua",
    "iso:country":"NI",
    "wof:name":"La Rica",
    "wof:placetype":"locality"
},
  "geometry": {"coordinates":[-86.05,13.41667],"type":"Point"}
}