{
  "type": "Feature",
  "properties": {
    "gn:admin1_code":"17.0",
    "gn:asciiname":"Murubila",
    "gn:country_code":"NI",
    "gn:dem":98,
    "gn:feature_class":"P",
    "gn:feature_code":"PPL",
    "gn:name":"Murubila",
    "gn:population":0,
    "gn:timezone":"America/Managua",
    "iso:country":"NI",
    "wof:name":"Murubila",
    "wof:placetype":"locality"
},
  "geometry": {"coordinates":[-84.48333000000002,14.43333],"type":"Point"}
}