{
  "type": "Feature",
  "properties": {
    "gn:admin1_code":"2.0",
    "gn:asciiname":"Pochomil",
    "gn:country_code":"NI",
    "gn:dem":2,
    "gn:feature_class":"P",
    "gn:feature_code":"PPL",
    "gn:name":"Pochomil",
    "gn:population":0,
    "gn:timezone":"America/Managua",
    "iso:country":"NI",
    "wof:name":"Pochomil",
    "wof:placetype":"locality"
},
  "geometry": {"coordinates":[-86.51053,11.77466],"type":"Point"}
}