{
  "type": "Feature",
  "properties": {
    "gn:admin1_code":"15.0",
    "gn:asciiname":"Sucuya",
    "gn:country_code":"NI",
    "gn:dem":44,
    "gn:feature_class":"P",
    "gn:feature_code":"PPL",
    "gn:name":"Sucuy\u00e1",
    "gn:population":0,
    "gn:timezone":"America/Managua",
    "iso:country":"NI",
    "wof:name":"Sucuya",
    "wof:placetype":"locality"
},
  "geometry": {"coordinates":[-85.82561,11.51352],"type":"Point"}
}