{
  "type": "Feature",
  "properties": {
    "gn:admin1_code":"9.0",
    "gn:asciiname":"Valle San Antonio",
    "gn:country_code":"NI",
    "gn:dem":716,
    "gn:feature_class":"P",
    "gn:feature_code":"PPL",
    "gn:name":"Valle San Antonio",
    "gn:population":0,
    "gn:timezone":"America/Managua",
    "iso:country":"NI",
    "name:und_x_variant":[
        "San Antonio",
        "Valle San Antonio"
    ],
    "wof:name":"Valle San Antonio",
    "wof:placetype":"locality"
},
  "geometry": {"coordinates":[-86.52656,13.47575],"type":"Point"}
}