{
  "type": "Feature",
  "properties": {
    "gn:admin1_code":"15.0",
    "gn:asciiname":"La Leona",
    "gn:country_code":"NI",
    "gn:dem":43,
    "gn:feature_class":"P",
    "gn:feature_code":"PPL",
    "gn:name":"La Leona",
    "gn:population":0,
    "gn:timezone":"America/Managua",
    "iso:country":"NI",
    "wof:name":"La Leona",
    "wof:placetype":"locality"
},
  "geometry": {"coordinates":[-85.76666999999998,11.15],"type":"Point"}
}