{
  "type": "Feature",
  "properties": {
    "gn:admin1_code":"15.0",
    "gn:asciiname":"La Leona",
    "gn:country_code":"NI",
    "gn:dem":43,
    "gn:feature_class":"P",
    "gn:feature_code":"PPL",
    "gn:name":"La Leona",
    "gn:population":0,
    "gn:timezone":"America/Managua",
    "iso:country":"NI",
    "name:ceb_x_preferred":[
        "La Leona"
    ],
    "name:spa_x_preferred":[
        "La leona"
    ],
    "name:srp_x_preferred":[
        "\u041b\u0430 \u041b\u0435\u043e\u043d\u0430"
    ],
    "name:swe_x_preferred":[
        "La Leona"
    ],
    "wof:name":"La Leona",
    "wof:placetype":"locality"
},
  "geometry": {"coordinates":[-85.76666999999998,11.15],"type":"Point"}
}