{
  "type": "Feature",
  "properties": {
    "gn:admin1_code":"3.0",
    "gn:asciiname":"San Nicolas",
    "gn:country_code":"NI",
    "gn:dem":79,
    "gn:feature_class":"P",
    "gn:feature_code":"PPL",
    "gn:name":"San Nicol\u00e1s",
    "gn:population":0,
    "gn:timezone":"America/Managua",
    "iso:country":"NI",
    "wof:name":"San Nicolas",
    "wof:placetype":"locality"
},
  "geometry": {"coordinates":[-86.76111999999998,12.96323],"type":"Point"}
}