{
  "type": "Feature",
  "properties": {
    "gn:admin1_code":"10.0",
    "gn:asciiname":"El Espadillo",
    "gn:country_code":"NI",
    "gn:dem":69,
    "gn:feature_class":"P",
    "gn:feature_code":"PPL",
    "gn:name":"El Espadillo",
    "gn:population":0,
    "gn:timezone":"America/Managua",
    "iso:country":"NI",
    "wof:name":"El Espadillo",
    "wof:placetype":"locality"
},
  "geometry": {"coordinates":[-86.4624,12.25837],"type":"Point"}
}