{
  "type": "Feature",
  "properties": {
    "gn:admin1_code":"11.0",
    "gn:asciiname":"Miravalle",
    "gn:country_code":"NI",
    "gn:dem":775,
    "gn:feature_class":"P",
    "gn:feature_code":"PPL",
    "gn:name":"Miravalle",
    "gn:population":0,
    "gn:timezone":"America/Managua",
    "iso:country":"NI",
    "wof:name":"Miravalle",
    "wof:placetype":"locality"
},
  "geometry": {"coordinates":[-86.26408000000001,11.99251],"type":"Point"}
}