{
  "type": "Feature",
  "properties": {
    "iso:country":"NI",
    "name:arm_x_preferred":[
        "\u053c\u0561 \u053c\u056b\u0562\u0565\u0580\u057f\u0561\u0564"
    ],
    "name:ces_x_preferred":[
        "La Libertad"
    ],
    "name:chi_x_preferred":[
        "\u62c9\u5229\u4f2f\u5854\u5fb7"
    ],
    "name:cze_x_preferred":[
        "La Libertad"
    ],
    "name:dut_x_preferred":[
        "La Libertad"
    ],
    "name:ell_x_preferred":[
        "\u039b\u03b1 \u039b\u03b9\u03bc\u03c0\u03b5\u03c1\u03c4\u03ac\u03b4"
    ],
    "name:eng_x_preferred":[
        "La Libertad"
    ],
    "name:fra_x_preferred":[
        "La Libertad"
    ],
    "name:fre_x_preferred":[
        "La Libertad"
    ],
    "name:gre_x_preferred":[
        "\u039b\u03b1 \u039b\u03b9\u03bc\u03c0\u03b5\u03c1\u03c4\u03ac\u03b4"
    ],
    "name:ita_x_preferred":[
        "La Libertad"
    ],
    "name:nld_x_preferred":[
        "La Libertad"
    ],
    "name:nob_x_preferred":[
        "La Libertad"
    ],
    "name:spa_x_preferred":[
        "La Libertad"
    ],
    "name:swe_x_preferred":[
        "La Libertad"
    ],
    "name:unk_x_variant":[
        "Libertad"
    ],
    "name:urd_x_preferred":[
        "\u0644\u0627 \u0644\u06cc\u0628\u06cc\u0631\u062a\u0627\u0688\u060c \u0634\u0648\u0646\u062a\u0627\u0644\u06cc\u0633"
    ],
    "name:zho_x_preferred":[
        "\u62c9\u5229\u4f2f\u5854\u5fb7"
    ],
    "qs:gn_country":"NI",
    "qs:gn_fcode":"PPL",
    "qs:gn_pop":3127,
    "qs:name":"La Libertad",
    "qs:name_adm0":"Nicaragua",
    "qs:name_adm1":"Chontales",
    "qs:photos":0,
    "qs:photos_1k":0,
    "qs:photos_9k":0,
    "qs:photos_9r":0,
    "qs:photos_all":0,
    "qs:photos_sr":0,
    "qs:placetype":"Town",
    "qs:pop_sr":"4",
    "qs:woe_adm0":23424915,
    "wd:wordcount":49,
    "wof:name":"La Libertad",
    "wof:placetype":"locality",
    "wof:population":3127
},
  "geometry": {"coordinates":[-85.16595,12.21635],"type":"Point"}
}