{
  "type": "Feature",
  "properties": {
    "iso:country":"NI",
    "name:aze_x_preferred":[
        "La Libertad"
    ],
    "name:bul_x_preferred":[
        "\u041b\u0430 \u041b\u0438\u0431\u0435\u0440\u0442\u0430\u0434"
    ],
    "name:cat_x_preferred":[
        "La Libertad"
    ],
    "name:ceb_x_preferred":[
        "La Libertad"
    ],
    "name:ces_x_preferred":[
        "La Libertad"
    ],
    "name:dan_x_preferred":[
        "La Libertad"
    ],
    "name:deu_x_preferred":[
        "La Libertad"
    ],
    "name:ell_x_preferred":[
        "\u039b\u03b1 \u039b\u03b9\u03bc\u03c0\u03b5\u03c1\u03c4\u03ac\u03b4"
    ],
    "name:eng_x_preferred":[
        "La Libertad"
    ],
    "name:eus_x_preferred":[
        "La Libertad"
    ],
    "name:fra_x_preferred":[
        "La Libertad"
    ],
    "name:heb_x_preferred":[
        "\u05dc\u05d4 \u05dc\u05d9\u05d1\u05e8\u05d8\u05d3"
    ],
    "name:hye_x_preferred":[
        "\u053c\u0561 \u053c\u056b\u0562\u0565\u0580\u057f\u0561\u0564"
    ],
    "name:ita_x_preferred":[
        "La Libertad"
    ],
    "name:nan_x_preferred":[
        "La Libertad"
    ],
    "name:nld_x_preferred":[
        "La Libertad"
    ],
    "name:nob_x_preferred":[
        "La Libertad"
    ],
    "name:oss_x_preferred":[
        "\u041b\u0430-\u041b\u0438\u0431\u0435\u0440\u0442\u0430\u0434"
    ],
    "name:pol_x_preferred":[
        "La Libertad"
    ],
    "name:por_x_preferred":[
        "La Libertad"
    ],
    "name:spa_x_preferred":[
        "La Libertad"
    ],
    "name:swe_x_preferred":[
        "La Libertad"
    ],
    "name:szl_x_preferred":[
        "La Libertad"
    ],
    "name:und_x_variant":[
        "Libertad"
    ],
    "name:urd_x_preferred":[
        "\u0644\u0627 \u0644\u0628\u0631\u062a\u0627\u062f"
    ],
    "name:urd_x_variant":[
        "\u0644\u0627 \u0644\u06cc\u0628\u06cc\u0631\u062a\u0627\u0688",
        "\u0644\u0627 \u0644\u06cc\u0628\u06cc\u0631\u062a\u0627\u0688\u060c \u0634\u0648\u0646\u062a\u0627\u0644\u06cc\u0633"
    ],
    "name:vie_x_preferred":[
        "La Libertad"
    ],
    "name:zho_x_preferred":[
        "\u62c9\u5229\u4f2f\u5854\u5fb7"
    ],
    "qs:gn_country":"NI",
    "qs:gn_fcode":"PPL",
    "qs:gn_pop":3127,
    "qs:name":"La Libertad",
    "qs:name_adm0":"Nicaragua",
    "qs:name_adm1":"Chontales",
    "qs:photos":0,
    "qs:photos_1k":0,
    "qs:photos_9k":0,
    "qs:photos_9r":0,
    "qs:photos_all":0,
    "qs:photos_sr":0,
    "qs:placetype":"Town",
    "qs:pop_sr":"4",
    "qs:woe_adm0":23424915,
    "wd:wordcount":49,
    "wof:name":"La Libertad",
    "wof:placetype":"locality",
    "wof:population":3127
},
  "geometry": {"coordinates":[-85.16595,12.21635],"type":"Point"}
}