{
  "type": "Feature",
  "properties": {
    "gn:admin1_code":"1.0",
    "gn:asciiname":"Tagua",
    "gn:country_code":"NI",
    "gn:dem":785,
    "gn:feature_class":"P",
    "gn:feature_code":"PPL",
    "gn:name":"Tagua",
    "gn:population":0,
    "gn:timezone":"America/Managua",
    "iso:country":"NI",
    "wof:name":"Tagua",
    "wof:placetype":"locality"
},
  "geometry": {"coordinates":[-85.61123000000001,12.62779],"type":"Point"}
}