{
  "type": "Feature",
  "properties": {
    "gn:admin1_code":"14.0",
    "gn:asciiname":"Palo Verde",
    "gn:country_code":"NI",
    "gn:dem":45,
    "gn:feature_class":"P",
    "gn:feature_code":"PPL",
    "gn:name":"Palo Verde",
    "gn:population":0,
    "gn:timezone":"America/Managua",
    "iso:country":"NI",
    "name:ceb_x_preferred":[
        "Palo Verde"
    ],
    "name:deu_x_preferred":[
        "Palo Verde"
    ],
    "name:fra_x_preferred":[
        "Palo Verde"
    ],
    "name:spa_x_preferred":[
        "Palo Verde"
    ],
    "name:srp_x_preferred":[
        "\u041f\u0430\u043b\u043e \u0412\u0435\u0440\u0434\u0435"
    ],
    "name:swe_x_preferred":[
        "Palo Verde"
    ],
    "wof:name":"Palo Verde",
    "wof:placetype":"locality"
},
  "geometry": {"coordinates":[-84.84569999999999,11.5181],"type":"Point"}
}