{
  "type": "Feature",
  "properties": {
    "gn:admin1_code":"14.0",
    "gn:asciiname":"Palo Verde",
    "gn:country_code":"NI",
    "gn:dem":45,
    "gn:feature_class":"P",
    "gn:feature_code":"PPL",
    "gn:name":"Palo Verde",
    "gn:population":0,
    "gn:timezone":"America/Managua",
    "iso:country":"NI",
    "wof:name":"Palo Verde",
    "wof:placetype":"locality"
},
  "geometry": {"coordinates":[-84.84569999999999,11.5181],"type":"Point"}
}