{
  "type": "Feature",
  "properties": {
    "gn:admin1_code":"3.0",
    "gn:asciiname":"El Cacao",
    "gn:country_code":"NI",
    "gn:dem":29,
    "gn:feature_class":"P",
    "gn:feature_code":"PPL",
    "gn:name":"El Cacao",
    "gn:population":0,
    "gn:timezone":"America/Managua",
    "iso:country":"NI",
    "name:ceb_x_preferred":[
        "El Cacao"
    ],
    "name:ita_x_preferred":[
        "El Cacao"
    ],
    "name:swe_x_preferred":[
        "El Cacao"
    ],
    "wof:name":"El Cacao",
    "wof:placetype":"locality"
},
  "geometry": {"coordinates":[-87.25635,12.86006],"type":"Point"}
}