{
  "type": "Feature",
  "properties": {
    "gn:admin1_code":"18.0",
    "gn:asciiname":"Brown Bank",
    "gn:country_code":"NI",
    "gn:dem":12,
    "gn:feature_class":"P",
    "gn:feature_code":"PPL",
    "gn:name":"Brown Bank",
    "gn:population":0,
    "gn:timezone":"America/Managua",
    "iso:country":"NI",
    "name:und_x_variant":[
        "Brown\u2019s Bank",
        "Brown Bank"
    ],
    "wof:name":"Brown Bank",
    "wof:placetype":"locality"
},
  "geometry": {"coordinates":[-83.73066,12.45451],"type":"Point"}
}