{
  "type": "Feature",
  "properties": {
    "gn:admin1_code":"11.0",
    "gn:asciiname":"San Alejandro",
    "gn:country_code":"NI",
    "gn:dem":68,
    "gn:feature_class":"P",
    "gn:feature_code":"PPL",
    "gn:name":"San Alejandro",
    "gn:population":0,
    "gn:timezone":"America/Managua",
    "iso:country":"NI",
    "name:und_x_variant":[
        "San Jer\u00f3nimo",
        "San Alejandro"
    ],
    "wof:name":"San Alejandro",
    "wof:placetype":"locality"
},
  "geometry": {"coordinates":[-86.06299,12.1281],"type":"Point"}
}