{
  "type": "Feature",
  "properties": {
    "gn:country":"NI",
    "gn:fcode":"PPL",
    "gn:population":14809,
    "iso:country":"NI",
    "name:ast_x_preferred":[
        "Santo Tom\u00e1s"
    ],
    "name:ben_x_preferred":[
        "\u09b8\u09be\u09a8\u09cd\u09a4\u09cb \u09a4\u09cb\u09ae\u09be\u09b8"
    ],
    "name:cat_x_preferred":[
        "Santo Tom\u00e1s"
    ],
    "name:ceb_x_preferred":[
        "Santo Tom\u00e1s"
    ],
    "name:deu_x_preferred":[
        "Santo Tom\u00e1s"
    ],
    "name:ell_x_preferred":[
        "\u03a3\u03ac\u03bd\u03c4\u03bf \u03a4\u03bf\u03bc\u03ac\u03c2"
    ],
    "name:eng_x_preferred":[
        "Santo Tom\u00e1s"
    ],
    "name:eus_x_preferred":[
        "Santo Tom\u00e1s"
    ],
    "name:fra_x_preferred":[
        "Santo Tom\u00e1s"
    ],
    "name:glg_x_preferred":[
        "Santo Tom\u00e1s"
    ],
    "name:ita_x_preferred":[
        "Santo Tom\u00e1s"
    ],
    "name:nan_x_preferred":[
        "Santo Tom\u00e1s"
    ],
    "name:nld_x_preferred":[
        "Santo Tom\u00e1s"
    ],
    "name:pol_x_preferred":[
        "Santo Tom\u00e1s"
    ],
    "name:por_x_preferred":[
        "Santo Tom\u00e1s"
    ],
    "name:spa_x_preferred":[
        "Santo Tom\u00e1s"
    ],
    "name:swe_x_preferred":[
        "Santo Tom\u00e1s"
    ],
    "name:und_x_variant":[
        "Santa Tomas"
    ],
    "name:urd_x_preferred":[
        "\u0633\u0627\u0646\u062a\u0648 \u062a\u0648\u0645\u0627\u0633\u060c \u0686\u0648\u0646\u062a\u0627\u0644\u06cc\u0633"
    ],
    "name:urd_x_variant":[
        "\u0633\u0627\u0646\u062a\u0648 \u062a\u0648\u0645\u0627\u0633"
    ],
    "name:zho_x_preferred":[
        "\u8056\u6258\u99ac\u65af"
    ],
    "name:zho_x_variant":[
        "\u74e6\u65af\u6f58"
    ],
    "qs:name":"Santo Tom\u00e1s",
    "qs:photos_9r":0,
    "qs:photos_sr":0,
    "qs:pop_sr":"6",
    "wd:wordcount":202,
    "wof:name":"Santo Tom\u00e1s",
    "wof:placetype":"locality",
    "wof:population":14809
},
  "geometry": {"coordinates":[-85.09059000000001,12.06938],"type":"Point"}
}