{
  "type": "Feature",
  "properties": {
    "gn:admin1_code":"18.0",
    "gn:asciiname":"El Chamarro",
    "gn:country_code":"NI",
    "gn:dem":137,
    "gn:feature_class":"P",
    "gn:feature_code":"PPL",
    "gn:name":"El Chamarro",
    "gn:population":0,
    "gn:timezone":"America/Managua",
    "iso:country":"NI",
    "wof:name":"El Chamarro",
    "wof:placetype":"locality"
},
  "geometry": {"coordinates":[-84.93333,12.86667],"type":"Point"}
}