{
  "type": "Feature",
  "properties": {
    "gn:admin1_code":"15.0",
    "gn:asciiname":"Santa Emilia",
    "gn:country_code":"NI",
    "gn:dem":25,
    "gn:feature_class":"P",
    "gn:feature_code":"PPL",
    "gn:name":"Santa Emilia",
    "gn:population":0,
    "gn:timezone":"America/Managua",
    "iso:country":"NI",
    "wof:name":"Santa Emilia",
    "wof:placetype":"locality"
},
  "geometry": {"coordinates":[-86.06161999999998,11.44852],"type":"Point"}
}