{
  "type": "Feature",
  "properties": {
    "gn:admin1_code":"8.0",
    "gn:asciiname":"El Tinco",
    "gn:country_code":"NI",
    "gn:dem":39,
    "gn:feature_class":"P",
    "gn:feature_code":"PPL",
    "gn:name":"El Tinco",
    "gn:population":0,
    "gn:timezone":"America/Managua",
    "iso:country":"NI",
    "wof:name":"El Tinco",
    "wof:placetype":"locality"
},
  "geometry": {"coordinates":[-86.67874,12.02482],"type":"Point"}
}