{
  "type": "Feature",
  "properties": {
    "gn:admin1_code":"10.0",
    "gn:asciiname":"Talpetate",
    "gn:country_code":"NI",
    "gn:dem":551,
    "gn:feature_class":"P",
    "gn:feature_code":"PPL",
    "gn:name":"Talpetate",
    "gn:population":0,
    "gn:timezone":"America/Managua",
    "iso:country":"NI",
    "name:und_x_variant":[
        "Caser\u00edo Telpetate",
        "Talpetate"
    ],
    "wof:name":"Talpetate",
    "wof:placetype":"locality"
},
  "geometry": {"coordinates":[-86.14372,12.60963],"type":"Point"}
}