{
  "type": "Feature",
  "properties": {
    "gn:admin1_code":"8.0",
    "gn:asciiname":"La Coyotera",
    "gn:country_code":"NI",
    "gn:dem":30,
    "gn:feature_class":"P",
    "gn:feature_code":"PPL",
    "gn:name":"La Coyotera",
    "gn:population":0,
    "gn:timezone":"America/Managua",
    "iso:country":"NI",
    "wof:name":"La Coyotera",
    "wof:placetype":"locality"
},
  "geometry": {"coordinates":[-87.03936999999998,12.46219],"type":"Point"}
}