{
  "type": "Feature",
  "properties": {
    "gn:admin1_code":"3.0",
    "gn:asciiname":"El Balsamo",
    "gn:country_code":"NI",
    "gn:dem":20,
    "gn:feature_class":"P",
    "gn:feature_code":"PPL",
    "gn:name":"El B\u00e1lsamo",
    "gn:population":0,
    "gn:timezone":"America/Managua",
    "iso:country":"NI",
    "name:und_x_variant":[
        "B\u00e1lsamo",
        "El B\u00e1lsamo"
    ],
    "wof:name":"El Balsamo",
    "wof:placetype":"locality"
},
  "geometry": {"coordinates":[-87.23050000000001,12.62465],"type":"Point"}
}