{
  "type": "Feature",
  "properties": {
    "gn:admin1_code":"15.0",
    "gn:asciiname":"Orosi",
    "gn:country_code":"NI",
    "gn:dem":35,
    "gn:feature_class":"P",
    "gn:feature_code":"PPL",
    "gn:name":"Oros\u00ed",
    "gn:population":0,
    "gn:timezone":"America/Managua",
    "iso:country":"NI",
    "name:und_x_variant":[
        "Hacienda Orosi",
        "Oros\u00ed"
    ],
    "wof:name":"Orosi",
    "wof:placetype":"locality"
},
  "geometry": {"coordinates":[-85.33946,11.1488],"type":"Point"}
}