{
  "type": "Feature",
  "properties": {
    "gn:admin1_code":"5.0",
    "gn:asciiname":"El Ocotillo",
    "gn:country_code":"NI",
    "gn:dem":1140,
    "gn:feature_class":"P",
    "gn:feature_code":"PPL",
    "gn:name":"El Ocotillo",
    "gn:population":0,
    "gn:timezone":"America/Managua",
    "iso:country":"NI",
    "wof:name":"El Ocotillo",
    "wof:placetype":"locality"
},
  "geometry": {"coordinates":[-86.33487,13.00919],"type":"Point"}
}