{
  "type": "Feature",
  "properties": {
    "gn:admin1_code":"17.0",
    "gn:asciiname":"Sisinata",
    "gn:country_code":"NI",
    "gn:dem":24,
    "gn:feature_class":"P",
    "gn:feature_code":"PPL",
    "gn:name":"Sisinata",
    "gn:population":0,
    "gn:timezone":"America/Managua",
    "iso:country":"NI",
    "wof:name":"Sisinata",
    "wof:placetype":"locality"
},
  "geometry": {"coordinates":[-83.49136999999997,14.29284],"type":"Point"}
}