{
  "type": "Feature",
  "properties": {
    "gn:admin1_code":"10.0",
    "gn:asciiname":"Las Lajitas",
    "gn:country_code":"NI",
    "gn:dem":384,
    "gn:feature_class":"P",
    "gn:feature_code":"PPL",
    "gn:name":"Las Lajitas",
    "gn:population":0,
    "gn:timezone":"America/Managua",
    "iso:country":"NI",
    "name:und_x_variant":[
        "Caser\u00edo Las Lajitas",
        "Las Lajitas"
    ],
    "wof:name":"Las Lajitas",
    "wof:placetype":"locality"
},
  "geometry": {"coordinates":[-86.14191,12.58746],"type":"Point"}
}