{
  "type": "Feature",
  "properties": {
    "gn:admin1_code":"8.0",
    "gn:asciiname":"Los Arcos",
    "gn:country_code":"NI",
    "gn:dem":54,
    "gn:feature_class":"P",
    "gn:feature_code":"PPL",
    "gn:name":"Los Arcos",
    "gn:population":0,
    "gn:timezone":"America/Managua",
    "iso:country":"NI",
    "name:und_x_variant":[
        "El Areo",
        "El Arco",
        "Los Arcos"
    ],
    "wof:name":"Los Arcos",
    "wof:placetype":"locality"
},
  "geometry": {"coordinates":[-86.77424999999999,12.33041],"type":"Point"}
}