{
  "type": "Feature",
  "properties": {
    "gn:admin1_code":"3.0",
    "gn:asciiname":"El Zanate",
    "gn:country_code":"NI",
    "gn:dem":8,
    "gn:feature_class":"P",
    "gn:feature_code":"PPL",
    "gn:name":"El Zanate",
    "gn:population":0,
    "gn:timezone":"America/Managua",
    "iso:country":"NI",
    "wof:name":"El Zanate",
    "wof:placetype":"locality"
},
  "geometry": {"coordinates":[-87.22573,12.54144],"type":"Point"}
}