{
  "type": "Feature",
  "properties": {
    "gn:admin1_code":"8.0",
    "gn:asciiname":"Los Ranchos de Sinecapa",
    "gn:country_code":"NI",
    "gn:dem":44,
    "gn:feature_class":"P",
    "gn:feature_code":"PPL",
    "gn:name":"Los Ranchos de Sinecapa",
    "gn:population":0,
    "gn:timezone":"America/Managua",
    "iso:country":"NI",
    "wof:name":"Los Ranchos de Sinecapa",
    "wof:placetype":"locality"
},
  "geometry": {"coordinates":[-86.40384,12.47467],"type":"Point"}
}