{
  "type": "Feature",
  "properties": {
    "gn:admin1_code":"10.0",
    "gn:asciiname":"El Corozo",
    "gn:cc2":"NI",
    "gn:country_code":"NI",
    "gn:dem":771,
    "gn:feature_class":"P",
    "gn:feature_code":"PPL",
    "gn:name":"El Corozo",
    "gn:population":0,
    "gn:timezone":"America/Managua",
    "iso:country":"NI",
    "name:und_x_variant":[
        "Corozo",
        "El Corozo"
    ],
    "wof:name":"El Corozo",
    "wof:placetype":"locality"
},
  "geometry": {"coordinates":[-86.31667,11.96667],"type":"Point"}
}