{
  "type": "Feature",
  "properties": {
    "gn:admin1_code":"17.0",
    "gn:asciiname":"Dakban",
    "gn:country_code":"NI",
    "gn:dem":6,
    "gn:feature_class":"P",
    "gn:feature_code":"PPL",
    "gn:name":"Dakban",
    "gn:population":0,
    "gn:timezone":"America/Managua",
    "iso:country":"NI",
    "wof:name":"Dakban",
    "wof:placetype":"locality"
},
  "geometry": {"coordinates":[-83.51725,14.0596],"type":"Point"}
}