{
  "type": "Feature",
  "properties": {
    "gn:admin1_code":"4.0",
    "gn:asciiname":"Las Pozas",
    "gn:country_code":"NI",
    "gn:dem":70,
    "gn:feature_class":"P",
    "gn:feature_code":"PPL",
    "gn:name":"Las Pozas",
    "gn:population":0,
    "gn:timezone":"America/Managua",
    "iso:country":"NI",
    "name:ces_x_preferred":[
        "Las Pozas"
    ],
    "name:fra_x_preferred":[
        "Las Pozas"
    ],
    "name:hun_x_preferred":[
        "Las Pozas"
    ],
    "name:rus_x_preferred":[
        "\u041b\u0430\u0441-\u041f\u043e\u0441\u0430\u0441"
    ],
    "name:spa_x_preferred":[
        "Las Pozas"
    ],
    "name:ukr_x_preferred":[
        "\u041b\u0430\u0441-\u041f\u043e\u0441\u0430\u0441"
    ],
    "wof:name":"Las Pozas",
    "wof:placetype":"locality"
},
  "geometry": {"coordinates":[-85.30764000000001,11.98343],"type":"Point"}
}