{
  "type": "Feature",
  "properties": {
    "gn:admin1_code":"4.0",
    "gn:asciiname":"Las Pozas",
    "gn:country_code":"NI",
    "gn:dem":70,
    "gn:feature_class":"P",
    "gn:feature_code":"PPL",
    "gn:name":"Las Pozas",
    "gn:population":0,
    "gn:timezone":"America/Managua",
    "iso:country":"NI",
    "wof:name":"Las Pozas",
    "wof:placetype":"locality"
},
  "geometry": {"coordinates":[-85.30764000000001,11.98343],"type":"Point"}
}