{
  "type": "Feature",
  "properties": {
    "gn:admin1_code":"18.0",
    "gn:asciiname":"Facundo",
    "gn:country_code":"NI",
    "gn:dem":103,
    "gn:feature_class":"P",
    "gn:feature_code":"PPL",
    "gn:name":"Facundo",
    "gn:population":0,
    "gn:timezone":"America/Managua",
    "iso:country":"NI",
    "name:ara_x_preferred":[
        "\u0641\u0627\u0643\u0648\u0646\u062f\u0648"
    ],
    "name:fra_x_preferred":[
        "Facundo"
    ],
    "wof:name":"Facundo",
    "wof:placetype":"locality"
},
  "geometry": {"coordinates":[-84.2367,12.31141],"type":"Point"}
}