{
  "type": "Feature",
  "properties": {
    "gn:admin1_code":"10.0",
    "gn:asciiname":"Casa Sola",
    "gn:country_code":"NI",
    "gn:dem":451,
    "gn:feature_class":"P",
    "gn:feature_code":"PPL",
    "gn:name":"Casa Sola",
    "gn:population":0,
    "gn:timezone":"America/Managua",
    "iso:country":"NI",
    "wof:name":"Casa Sola",
    "wof:placetype":"locality"
},
  "geometry": {"coordinates":[-86.05103000000003,12.52357],"type":"Point"}
}