{
  "type": "Feature",
  "properties": {
    "gn:admin1_code":"18.0",
    "gn:asciiname":"Colonia Verdun",
    "gn:country_code":"NI",
    "gn:dem":212,
    "gn:feature_class":"P",
    "gn:feature_code":"PPL",
    "gn:name":"Colonia Verd\u00fan",
    "gn:population":0,
    "gn:timezone":"America/Managua",
    "iso:country":"NI",
    "name:und_x_variant":[
        "Colonia Agr\u00edcola Verd\u00fan",
        "Colonia Verd\u00fan"
    ],
    "wof:name":"Colonia Verdun",
    "wof:placetype":"locality"
},
  "geometry": {"coordinates":[-84.43559999999999,11.6449],"type":"Point"}
}