{
  "type": "Feature",
  "properties": {
    "gn:admin1_code":"1.0",
    "gn:asciiname":"San Gregorio",
    "gn:country_code":"NI",
    "gn:dem":465,
    "gn:feature_class":"P",
    "gn:feature_code":"PPL",
    "gn:name":"San Gregorio",
    "gn:population":0,
    "gn:timezone":"America/Managua",
    "iso:country":"NI",
    "wof:name":"San Gregorio",
    "wof:placetype":"locality"
},
  "geometry": {"coordinates":[-85.51666999999998,12.33333],"type":"Point"}
}