{
  "type": "Feature",
  "properties": {
    "gn:admin1_code":"17.0",
    "gn:asciiname":"Amparo",
    "gn:cc2":"NI",
    "gn:country_code":"NI",
    "gn:dem":93,
    "gn:feature_class":"P",
    "gn:feature_code":"PPL",
    "gn:name":"Amparo",
    "gn:population":0,
    "gn:timezone":"America/Managua",
    "iso:country":"NI",
    "name:und_x_variant":[
        "Huailahuas",
        "Wailawas",
        "Vailavas",
        "Amparo"
    ],
    "wof:name":"Amparo",
    "wof:placetype":"locality"
},
  "geometry": {"coordinates":[-84.83333,13.65],"type":"Point"}
}