{
  "type": "Feature",
  "properties": {
    "gn:admin1_code":"17.0",
    "gn:asciiname":"Amparo",
    "gn:cc2":"NI",
    "gn:country_code":"NI",
    "gn:dem":93,
    "gn:feature_class":"P",
    "gn:feature_code":"PPL",
    "gn:name":"Amparo",
    "gn:population":0,
    "gn:timezone":"America/Managua",
    "iso:country":"NI",
    "name:bre_x_preferred":[
        "Amparo"
    ],
    "name:ceb_x_preferred":[
        "Amparo"
    ],
    "name:deu_x_preferred":[
        "Amparo"
    ],
    "name:fra_x_preferred":[
        "Amparo"
    ],
    "name:glg_x_preferred":[
        "Amparo"
    ],
    "name:ita_x_preferred":[
        "Amparo"
    ],
    "name:kor_x_preferred":[
        "\uc554\ud30c\ub85c"
    ],
    "name:mlg_x_preferred":[
        "Amparo"
    ],
    "name:nld_x_preferred":[
        "Amparo"
    ],
    "name:nor_x_preferred":[
        "Amparo"
    ],
    "name:por_x_preferred":[
        "Amparo"
    ],
    "name:rus_x_preferred":[
        "\u0410\u043c\u043f\u0430\u0440\u0443"
    ],
    "name:spa_x_preferred":[
        "Amparo"
    ],
    "name:swe_x_preferred":[
        "Amparo"
    ],
    "name:und_x_variant":[
        "Huailahuas",
        "Wailawas",
        "Vailavas"
    ],
    "name:vie_x_preferred":[
        "Amparo"
    ],
    "name:vol_x_preferred":[
        "Amparo"
    ],
    "name:war_x_preferred":[
        "Amparo"
    ],
    "wof:name":"Amparo",
    "wof:placetype":"locality"
},
  "geometry": {"coordinates":[-84.83333,13.65],"type":"Point"}
}