{
  "type": "Feature",
  "properties": {
    "gn:admin1_code":"1.0",
    "gn:asciiname":"Yucapuca",
    "gn:country_code":"NI",
    "gn:dem":388,
    "gn:feature_class":"P",
    "gn:feature_code":"PPL",
    "gn:name":"Yucapuca",
    "gn:population":0,
    "gn:timezone":"America/Managua",
    "iso:country":"NI",
    "wof:name":"Yucapuca",
    "wof:placetype":"locality"
},
  "geometry": {"coordinates":[-85.50962,12.55548],"type":"Point"}
}