{
  "type": "Feature",
  "properties": {
    "gn:admin1_code":"6.0",
    "gn:asciiname":"Dulce Nombre",
    "gn:country_code":"NI",
    "gn:dem":110,
    "gn:feature_class":"P",
    "gn:feature_code":"PPL",
    "gn:name":"Dulce Nombre",
    "gn:population":0,
    "gn:timezone":"America/Managua",
    "iso:country":"NI",
    "name:spa_x_preferred":[
        "Dulce Nombre"
    ],
    "wof:name":"Dulce Nombre",
    "wof:placetype":"locality"
},
  "geometry": {"coordinates":[-85.98203000000002,11.94784],"type":"Point"}
}