{
  "type": "Feature",
  "properties": {
    "iso:country":"NI",
    "name:ceb_x_preferred":[
        "Tisma"
    ],
    "name:deu_x_preferred":[
        "Tisma"
    ],
    "name:eng_x_preferred":[
        "Tisma"
    ],
    "name:fra_x_preferred":[
        "Tisma"
    ],
    "name:ita_x_preferred":[
        "Tisma"
    ],
    "name:nld_x_preferred":[
        "Tisma"
    ],
    "name:spa_x_preferred":[
        "Tisma"
    ],
    "name:swe_x_preferred":[
        "Tisma"
    ],
    "name:urd_x_preferred":[
        "\u062a\u06cc\u0633\u0645\u0627"
    ],
    "name:vie_x_preferred":[
        "Tisma"
    ],
    "name:zho_x_preferred":[
        "\u8482\u65af\u99ac"
    ],
    "qs:gn_country":"NI",
    "qs:gn_fcode":"PPL",
    "qs:gn_pop":5182,
    "qs:name":"Tisma",
    "qs:name_adm0":"Nicaragua",
    "qs:name_adm1":"Masaya",
    "qs:photos":0,
    "qs:photos_1k":0,
    "qs:photos_9k":1,
    "qs:photos_9r":1,
    "qs:photos_all":2,
    "qs:photos_sr":0,
    "qs:placetype":"Town",
    "qs:pop_sr":"5",
    "qs:woe_adm0":23424915,
    "wof:name":"Tisma",
    "wof:placetype":"locality",
    "wof:population":5182
},
  "geometry": {"coordinates":[-86.01739000000001,12.08194],"type":"Point"}
}