{
  "type": "Feature",
  "properties": {
    "gn:admin1_code":"1.0",
    "gn:asciiname":"Maderas",
    "gn:cc2":"NI",
    "gn:country_code":"NI",
    "gn:dem":314,
    "gn:feature_class":"P",
    "gn:feature_code":"PPL",
    "gn:name":"Maderas",
    "gn:population":0,
    "gn:timezone":"America/Managua",
    "iso:country":"NI",
    "name:ceb_x_preferred":[
        "Volc\u00e1n Maderas"
    ],
    "name:ces_x_preferred":[
        "Maderas"
    ],
    "name:deu_x_preferred":[
        "Maderas"
    ],
    "name:fas_x_preferred":[
        "\u0645\u0627\u062f\u0631\u0627\u0633"
    ],
    "name:fra_x_preferred":[
        "Maderas"
    ],
    "name:hrv_x_preferred":[
        "Maderas"
    ],
    "name:hun_x_preferred":[
        "Maderas"
    ],
    "name:jpn_x_preferred":[
        "\u30de\u30c7\u30e9\u30b9\u5c71"
    ],
    "name:kat_x_preferred":[
        "\u10db\u10d0\u10d3\u10d4\u10e0\u10d0\u10e1\u10d8"
    ],
    "name:kor_x_preferred":[
        "\ub9c8\ub370\ub77c\uc2a4\uc0b0"
    ],
    "name:lit_x_preferred":[
        "Maderasas"
    ],
    "name:nld_x_preferred":[
        "Maderas"
    ],
    "name:pol_x_preferred":[
        "Maderas"
    ],
    "name:rus_x_preferred":[
        "\u041c\u0430\u0434\u0435\u0440\u0430\u0441"
    ],
    "name:slk_x_preferred":[
        "Maderas"
    ],
    "name:spa_x_preferred":[
        "Volc\u00e1n Maderas"
    ],
    "name:swe_x_preferred":[
        "Volc\u00e1n Maderas"
    ],
    "name:ukr_x_preferred":[
        "\u041c\u0430\u0434\u0435\u0440\u0430\u0441"
    ],
    "name:und_x_variant":[
        "Las Maderas"
    ],
    "name:zho_x_preferred":[
        "\u99ac\u5fb7\u62c9\u65af\u706b\u5c71"
    ],
    "wof:name":"Maderas",
    "wof:placetype":"locality"
},
  "geometry": {"coordinates":[-85.53333000000001,12.68333],"type":"Point"}
}