{
  "type": "Feature",
  "properties": {
    "gn:admin1_code":"1.0",
    "gn:asciiname":"Maderas",
    "gn:cc2":"NI",
    "gn:country_code":"NI",
    "gn:dem":314,
    "gn:feature_class":"P",
    "gn:feature_code":"PPL",
    "gn:name":"Maderas",
    "gn:population":0,
    "gn:timezone":"America/Managua",
    "iso:country":"NI",
    "name:und_x_variant":[
        "Las Maderas",
        "Maderas"
    ],
    "wof:name":"Maderas",
    "wof:placetype":"locality"
},
  "geometry": {"coordinates":[-85.53333000000001,12.68333],"type":"Point"}
}