{
  "type": "Feature",
  "properties": {
    "gn:admin1_code":"10.0",
    "gn:asciiname":"Santa Rita de Plata",
    "gn:country_code":"NI",
    "gn:dem":76,
    "gn:feature_class":"P",
    "gn:feature_code":"PPL",
    "gn:name":"Santa Rita de Plata",
    "gn:population":0,
    "gn:timezone":"America/Managua",
    "iso:country":"NI",
    "wof:name":"Santa Rita de Plata",
    "wof:placetype":"locality"
},
  "geometry": {"coordinates":[-86.48333000000002,12.26667],"type":"Point"}
}