{
  "type": "Feature",
  "properties": {
    "iso:country":"NI",
    "name:ast_x_preferred":[
        "Ticuantepe"
    ],
    "name:ceb_x_preferred":[
        "Ticuantepe"
    ],
    "name:ell_x_preferred":[
        "\u03a4\u03b9\u03ba\u03bf\u03c5\u03b1\u03bd\u03c4\u03ad\u03c0\u03b5"
    ],
    "name:eng_x_preferred":[
        "Ticuantepe"
    ],
    "name:eus_x_preferred":[
        "Ticuantepe"
    ],
    "name:fra_x_preferred":[
        "Ticuantepe"
    ],
    "name:ita_x_preferred":[
        "Ticuantepe"
    ],
    "name:nan_x_preferred":[
        "Ticuantepe"
    ],
    "name:nld_x_preferred":[
        "Ticuantepe"
    ],
    "name:pol_x_preferred":[
        "Ticuantepe"
    ],
    "name:por_x_preferred":[
        "Ticuantepe"
    ],
    "name:spa_x_preferred":[
        "Ticuantepe"
    ],
    "name:swe_x_preferred":[
        "Ticuantepe"
    ],
    "name:urd_x_preferred":[
        "\u062a\u06cc\u06a9\u0648\u0627\u0646\u062a\u06cc\u067e\u06d2"
    ],
    "name:vie_x_preferred":[
        "Ticuantepe"
    ],
    "name:zho_x_preferred":[
        "\u8482\u5eab\u5b89\u7279\u4f69"
    ],
    "qs:gn_country":"NI",
    "qs:gn_fcode":"PPL",
    "qs:gn_pop":13209,
    "qs:name":"Ticuantepe",
    "qs:name_adm0":"Nicaragua",
    "qs:name_adm1":"Managua",
    "qs:photos":1144,
    "qs:photos_1k":232,
    "qs:photos_9k":5,
    "qs:photos_9r":7,
    "qs:photos_all":1144,
    "qs:photos_sr":11,
    "qs:placetype":"Town",
    "qs:pop_sr":"6",
    "qs:woe_adm0":23424915,
    "wof:name":"Ticuantepe",
    "wof:placetype":"locality",
    "wof:population":13209
},
  "geometry": {"coordinates":[-86.20493,12.02263],"type":"Point"}
}