{
  "type": "Feature",
  "properties": {
    "gn:admin1_code":"6.0",
    "gn:asciiname":"El Rodeo",
    "gn:country_code":"NI",
    "gn:dem":310,
    "gn:feature_class":"P",
    "gn:feature_code":"PPL",
    "gn:name":"El Rodeo",
    "gn:population":0,
    "gn:timezone":"America/Managua",
    "iso:country":"NI",
    "name:ceb_x_preferred":[
        "El Rodeo"
    ],
    "name:deu_x_preferred":[
        "El Rodeo"
    ],
    "name:spa_x_preferred":[
        "El Rodeo"
    ],
    "name:srp_x_preferred":[
        "\u0415\u043b \u0420\u043e\u0434\u0435\u043e"
    ],
    "name:swe_x_preferred":[
        "El Rodeo"
    ],
    "wof:name":"El Rodeo",
    "wof:placetype":"locality"
},
  "geometry": {"coordinates":[-86.03333000000001,11.86667],"type":"Point"}
}