{
  "type": "Feature",
  "properties": {
    "gn:admin1_code":"12.0",
    "gn:asciiname":"Bilwaska",
    "gn:country_code":"NI",
    "gn:dem":658,
    "gn:feature_class":"P",
    "gn:feature_code":"PPL",
    "gn:name":"Bilwaska",
    "gn:population":0,
    "gn:timezone":"America/Managua",
    "iso:country":"NI",
    "wof:name":"Bilwaska",
    "wof:placetype":"locality"
},
  "geometry": {"coordinates":[-86.05306,12.82556],"type":"Point"}
}