{
  "type": "Feature",
  "properties": {
    "gn:admin1_code":"5.0",
    "gn:asciiname":"El Morado",
    "gn:country_code":"NI",
    "gn:dem":877,
    "gn:feature_class":"P",
    "gn:feature_code":"PPL",
    "gn:name":"El Morado",
    "gn:population":0,
    "gn:timezone":"America/Managua",
    "iso:country":"NI",
    "name:und_x_variant":[
        "Morado",
        "El Morado"
    ],
    "wof:name":"El Morado",
    "wof:placetype":"locality"
},
  "geometry": {"coordinates":[-86.45286,13.08291],"type":"Point"}
}