{
  "type": "Feature",
  "properties": {
    "gn:admin1_code":"8.0",
    "gn:asciiname":"Santa Rita",
    "gn:country_code":"NI",
    "gn:dem":44,
    "gn:feature_class":"P",
    "gn:feature_code":"PPL",
    "gn:name":"Santa Rita",
    "gn:population":0,
    "gn:timezone":"America/Managua",
    "iso:country":"NI",
    "wof:name":"Santa Rita",
    "wof:placetype":"locality"
},
  "geometry": {"coordinates":[-86.6771,12.29333],"type":"Point"}
}