{
  "type": "Feature",
  "properties": {
    "gn:admin1_code":"2.0",
    "gn:asciiname":"El Brasil",
    "gn:country_code":"NI",
    "gn:dem":196,
    "gn:feature_class":"P",
    "gn:feature_code":"PPL",
    "gn:name":"El Brasil",
    "gn:population":0,
    "gn:timezone":"America/Managua",
    "iso:country":"NI",
    "wof:name":"El Brasil",
    "wof:placetype":"locality"
},
  "geometry": {"coordinates":[-86.17282,11.7165],"type":"Point"}
}