{
  "type": "Feature",
  "properties": {
    "gn:admin1_code":"17.0",
    "gn:asciiname":"Danli",
    "gn:country_code":"NI",
    "gn:dem":179,
    "gn:feature_class":"P",
    "gn:feature_code":"PPL",
    "gn:name":"Danl\u00ed",
    "gn:population":0,
    "gn:timezone":"America/Managua",
    "iso:country":"NI",
    "name:und_x_variant":[
        "Danl\u00ed Arriba",
        "Danl\u00ed"
    ],
    "wof:name":"Danli",
    "wof:placetype":"locality"
},
  "geometry": {"coordinates":[-84.95295,13.68694],"type":"Point"}
}