{
  "type": "Feature",
  "properties": {
    "gn:admin1_code":"10.0",
    "gn:asciiname":"San Blas",
    "gn:country_code":"NI",
    "gn:dem":153,
    "gn:feature_class":"P",
    "gn:feature_code":"PPL",
    "gn:name":"San Blas",
    "gn:population":0,
    "gn:timezone":"America/Managua",
    "iso:country":"NI",
    "wof:name":"San Blas",
    "wof:placetype":"locality"
},
  "geometry": {"coordinates":[-86.04764,12.48112],"type":"Point"}
}