{
  "type": "Feature",
  "properties": {
    "gn:admin1_code":"8.0",
    "gn:asciiname":"Rincon Escondido",
    "gn:country_code":"NI",
    "gn:dem":137,
    "gn:feature_class":"P",
    "gn:feature_code":"PPL",
    "gn:name":"Rinc\u00f3n Escondido",
    "gn:population":0,
    "gn:timezone":"America/Managua",
    "iso:country":"NI",
    "wof:name":"Rincon Escondido",
    "wof:placetype":"locality"
},
  "geometry": {"coordinates":[-86.62801999999998,12.87684],"type":"Point"}
}