{
  "type": "Feature",
  "properties": {
    "gn:admin1_code":"3.0",
    "gn:asciiname":"Valle El Danto",
    "gn:country_code":"NI",
    "gn:dem":109,
    "gn:feature_class":"P",
    "gn:feature_code":"PPL",
    "gn:name":"Valle El Danto",
    "gn:population":0,
    "gn:timezone":"America/Managua",
    "iso:country":"NI",
    "name:und_x_variant":[
        "Danta",
        "Danto",
        "Valle El Danto"
    ],
    "wof:name":"Valle El Danto",
    "wof:placetype":"locality"
},
  "geometry": {"coordinates":[-86.77384000000001,13.07599],"type":"Point"}
}