{
  "type": "Feature",
  "properties": {
    "gn:admin1_code":"2.0",
    "gn:asciiname":"Banosa",
    "gn:country_code":"NI",
    "gn:dem":38,
    "gn:feature_class":"P",
    "gn:feature_code":"PPL",
    "gn:name":"Banosa",
    "gn:population":0,
    "gn:timezone":"America/Managua",
    "iso:country":"NI",
    "name:spa_x_preferred":[
        "Banosa"
    ],
    "wof:name":"Banosa",
    "wof:placetype":"locality"
},
  "geometry": {"coordinates":[-86.31728000000003,11.68202],"type":"Point"}
}