{
  "type": "Feature",
  "properties": {
    "gn:admin1_code":"17.0",
    "gn:asciiname":"Lapan",
    "gn:country_code":"NI",
    "gn:dem":26,
    "gn:feature_class":"P",
    "gn:feature_code":"PPL",
    "gn:name":"Lapan",
    "gn:population":0,
    "gn:timezone":"America/Managua",
    "iso:country":"NI",
    "wof:name":"Lapan",
    "wof:placetype":"locality"
},
  "geometry": {"coordinates":[-83.77651,13.87711],"type":"Point"}
}