{
  "type": "Feature",
  "properties": {
    "gn:admin1_code":"17.0",
    "gn:asciiname":"Lapan",
    "gn:country_code":"NI",
    "gn:dem":26,
    "gn:feature_class":"P",
    "gn:feature_code":"PPL",
    "gn:name":"Lapan",
    "gn:population":0,
    "gn:timezone":"America/Managua",
    "iso:country":"NI",
    "name:cat_x_preferred":[
        "Lapan"
    ],
    "name:ceb_x_preferred":[
        "Lapan"
    ],
    "name:deu_x_preferred":[
        "Lapan"
    ],
    "name:eus_x_preferred":[
        "Lapan"
    ],
    "name:fas_x_preferred":[
        "\u0644\u0627\u067e\u0627\u0646"
    ],
    "name:fra_x_preferred":[
        "Lapan"
    ],
    "name:hun_x_preferred":[
        "Lapan"
    ],
    "name:ita_x_preferred":[
        "Lapan"
    ],
    "name:lat_x_preferred":[
        "Lapan"
    ],
    "name:msa_x_preferred":[
        "Lapan"
    ],
    "name:nld_x_preferred":[
        "Lapan"
    ],
    "name:oci_x_preferred":[
        "Lapan"
    ],
    "name:pms_x_preferred":[
        "Lapan"
    ],
    "name:pol_x_preferred":[
        "Lapan"
    ],
    "name:por_x_preferred":[
        "Lapan"
    ],
    "name:ron_x_preferred":[
        "Lapan"
    ],
    "name:rus_x_preferred":[
        "\u041b\u0430\u043f\u0430\u043d"
    ],
    "name:slk_x_preferred":[
        "Lapan"
    ],
    "name:spa_x_preferred":[
        "Lapan"
    ],
    "name:swe_x_preferred":[
        "Lapan"
    ],
    "name:ukr_x_preferred":[
        "\u041b\u0430\u043f\u0430\u043d"
    ],
    "name:urd_x_preferred":[
        "\u0644\u0627\u067e\u0627\u0646"
    ],
    "name:uzb_x_preferred":[
        "Lapan"
    ],
    "name:vie_x_preferred":[
        "Lapan"
    ],
    "name:vol_x_preferred":[
        "Lapan"
    ],
    "name:war_x_preferred":[
        "Lapan"
    ],
    "name:zho_x_preferred":[
        "\u62c9\u5e9e"
    ],
    "wof:name":"Lapan",
    "wof:placetype":"locality"
},
  "geometry": {"coordinates":[-83.77651,13.87711],"type":"Point"}
}