{
  "type": "Feature",
  "properties": {
    "gn:admin1_code":"7.0",
    "gn:asciiname":"El Horno",
    "gn:country_code":"NI",
    "gn:dem":1022,
    "gn:feature_class":"P",
    "gn:feature_code":"PPL",
    "gn:name":"El Horno",
    "gn:population":0,
    "gn:timezone":"America/Managua",
    "iso:country":"NI",
    "name:und_x_variant":[
        "Horno",
        "El Horno"
    ],
    "wof:name":"El Horno",
    "wof:placetype":"locality"
},
  "geometry": {"coordinates":[-86.00274,13.03028],"type":"Point"}
}