{
  "type": "Feature",
  "properties": {
    "gn:admin1_code":"11.0",
    "gn:asciiname":"Campuzano",
    "gn:country_code":"NI",
    "gn:dem":166,
    "gn:feature_class":"P",
    "gn:feature_code":"PPL",
    "gn:name":"Campuzano",
    "gn:population":0,
    "gn:timezone":"America/Managua",
    "iso:country":"NI",
    "name:und_x_variant":[
        "Campazano",
        "Campuzano"
    ],
    "wof:name":"Campuzano",
    "wof:placetype":"locality"
},
  "geometry": {"coordinates":[-86.13651999999998,12.05367],"type":"Point"}
}