{
  "type": "Feature",
  "properties": {
    "gn:admin1_code":"9.0",
    "gn:asciiname":"Icalupe",
    "gn:country_code":"NI",
    "gn:dem":858,
    "gn:feature_class":"P",
    "gn:feature_code":"PPL",
    "gn:name":"Icalupe",
    "gn:population":0,
    "gn:timezone":"America/Managua",
    "iso:country":"NI",
    "wof:name":"Icalupe",
    "wof:placetype":"locality"
},
  "geometry": {"coordinates":[-86.68731,13.62998],"type":"Point"}
}