{
  "type": "Feature",
  "properties": {
    "gn:admin1_code":"3.0",
    "gn:asciiname":"San Pedro del Norte",
    "gn:country_code":"NI",
    "gn:dem":494,
    "gn:feature_class":"P",
    "gn:feature_code":"PPL",
    "gn:name":"San Pedro del Norte",
    "gn:population":0,
    "gn:timezone":"America/Managua",
    "iso:country":"NI",
    "name:ceb_x_preferred":[
        "San Pedro del Norte"
    ],
    "name:ell_x_preferred":[
        "\u03a3\u03b1\u03bd \u03a0\u03ad\u03b4\u03c1\u03bf \u03b4\u03b5\u03bb \u039d\u03cc\u03c1\u03c4\u03b5"
    ],
    "name:fra_x_preferred":[
        "San Pedro del Norte"
    ],
    "name:ita_x_preferred":[
        "San Pedro del Norte"
    ],
    "name:spa_x_preferred":[
        "San Pedro del Norte"
    ],
    "name:swe_x_preferred":[
        "San Pedro del Norte"
    ],
    "name:und_x_variant":[
        "San Pedro de Potrero Grande",
        "San Pedro",
        "San Pedro de Potrero"
    ],
    "name:urd_x_preferred":[
        "\u0633\u0627\u0646 \u067e\u06cc\u062f\u0631\u0648 \u0634\u0645\u0627\u0644\u06cc"
    ],
    "name:vie_x_preferred":[
        "San Pedro del Norte"
    ],
    "wof:name":"San Pedro del Norte",
    "wof:placetype":"locality"
},
  "geometry": {"coordinates":[-86.87844,13.27623],"type":"Point"}
}