{
  "type": "Feature",
  "properties": {
    "gn:admin1_code":"17.0",
    "gn:asciiname":"Yulu",
    "gn:country_code":"NI",
    "gn:dem":19,
    "gn:feature_class":"P",
    "gn:feature_code":"PPL",
    "gn:name":"Yul\u00fa",
    "gn:population":0,
    "gn:timezone":"America/Managua",
    "iso:country":"NI",
    "name:ceb_x_preferred":[
        "Yulu"
    ],
    "name:deu_x_preferred":[
        "Yulu"
    ],
    "name:swe_x_preferred":[
        "Yulu"
    ],
    "wof:name":"Yulu",
    "wof:placetype":"locality"
},
  "geometry": {"coordinates":[-83.59483,14.06659],"type":"Point"}
}