{
  "type": "Feature",
  "properties": {
    "gn:admin1_code":"4.0",
    "gn:asciiname":"Los Morenos",
    "gn:country_code":"NI",
    "gn:dem":423,
    "gn:feature_class":"P",
    "gn:feature_code":"PPL",
    "gn:name":"Los Morenos",
    "gn:population":0,
    "gn:timezone":"America/Managua",
    "iso:country":"NI",
    "wof:name":"Los Morenos",
    "wof:placetype":"locality"
},
  "geometry": {"coordinates":[-84.98057,12.16893],"type":"Point"}
}