{
  "type": "Feature",
  "properties": {
    "gn:admin1_code":"10.0",
    "gn:asciiname":"Desmotadora Las Brasiles",
    "gn:country_code":"NI",
    "gn:dem":74,
    "gn:feature_class":"P",
    "gn:feature_code":"PPL",
    "gn:name":"Desmotadora Las Brasiles",
    "gn:population":0,
    "gn:timezone":"America/Managua",
    "iso:country":"NI",
    "wof:name":"Desmotadora Las Brasiles",
    "wof:placetype":"locality"
},
  "geometry": {"coordinates":[-86.37031999999998,12.19244],"type":"Point"}
}