{
  "type": "Feature",
  "properties": {
    "gn:admin1_code":"2.0",
    "gn:asciiname":"Fatima",
    "gn:country_code":"NI",
    "gn:dem":488,
    "gn:feature_class":"P",
    "gn:feature_code":"PPL",
    "gn:name":"F\u00e1tima",
    "gn:population":0,
    "gn:timezone":"America/Managua",
    "iso:country":"NI",
    "wof:name":"Fatima",
    "wof:placetype":"locality"
},
  "geometry": {"coordinates":[-86.17851,11.89086],"type":"Point"}
}