{
  "type": "Feature",
  "properties": {
    "gn:admin1_code":"2.0",
    "gn:asciiname":"Fatima",
    "gn:country_code":"NI",
    "gn:dem":488,
    "gn:feature_class":"P",
    "gn:feature_code":"PPL",
    "gn:name":"F\u00e1tima",
    "gn:population":0,
    "gn:timezone":"America/Managua",
    "iso:country":"NI",
    "name:ara_x_preferred":[
        "\u0641\u0627\u0637\u0645\u0629"
    ],
    "name:bul_x_preferred":[
        "\u0424\u0430\u0442\u0438\u043c\u0430"
    ],
    "name:cat_x_preferred":[
        "F\u00e0tima"
    ],
    "name:ceb_x_preferred":[
        "Fatima"
    ],
    "name:deu_x_preferred":[
        "Fatima"
    ],
    "name:eus_x_preferred":[
        "Fatima"
    ],
    "name:fin_x_preferred":[
        "Fatima"
    ],
    "name:fra_x_preferred":[
        "Fatima"
    ],
    "name:glg_x_preferred":[
        "F\u00e1tima"
    ],
    "name:hun_x_preferred":[
        "Fatima"
    ],
    "name:hye_x_preferred":[
        "\u0556\u0561\u057f\u056b\u0574\u0561"
    ],
    "name:ita_x_preferred":[
        "Fatima"
    ],
    "name:jpn_x_preferred":[
        "\u30d5\u30a1\u30c6\u30a3\u30de"
    ],
    "name:kor_x_preferred":[
        "\ud30c\ud2f0\ub9c8"
    ],
    "name:nld_x_preferred":[
        "Fatima"
    ],
    "name:nor_x_preferred":[
        "Fatima"
    ],
    "name:pol_x_preferred":[
        "Fatima"
    ],
    "name:por_x_preferred":[
        "F\u00e1tima"
    ],
    "name:rus_x_preferred":[
        "\u0424\u0430\u0442\u0438\u043c\u0430"
    ],
    "name:slv_x_preferred":[
        "Fatima"
    ],
    "name:som_x_preferred":[
        "Fatima"
    ],
    "name:spa_x_preferred":[
        "F\u00e1tima"
    ],
    "name:srp_x_preferred":[
        "\u0424\u0430\u0442\u0438\u043c\u0430"
    ],
    "name:swe_x_preferred":[
        "Fatima"
    ],
    "name:ukr_x_preferred":[
        "\u0424\u0430\u0442\u0456\u043c\u0430"
    ],
    "name:urd_x_preferred":[
        "\u0641\u0627\u0637\u0645\u06c1"
    ],
    "name:zho_x_preferred":[
        "Fatima"
    ],
    "wof:name":"Fatima",
    "wof:placetype":"locality"
},
  "geometry": {"coordinates":[-86.17851,11.89086],"type":"Point"}
}