{
  "type": "Feature",
  "properties": {
    "gn:admin1_code":"3.0",
    "gn:asciiname":"Trujillo",
    "gn:country_code":"NI",
    "gn:dem":77,
    "gn:feature_class":"P",
    "gn:feature_code":"PPL",
    "gn:name":"Trujillo",
    "gn:population":0,
    "gn:timezone":"America/Managua",
    "iso:country":"NI",
    "name:ara_x_preferred":[
        "\u062a\u0631\u062c\u064a\u0644\u0629"
    ],
    "name:bre_x_preferred":[
        "Trujillo"
    ],
    "name:bul_x_preferred":[
        "\u0422\u0440\u0443\u0445\u0438\u043b\u044c\u043e"
    ],
    "name:cat_x_preferred":[
        "Trujillo"
    ],
    "name:ceb_x_preferred":[
        "Trujillo"
    ],
    "name:ces_x_preferred":[
        "Trujillo"
    ],
    "name:dan_x_preferred":[
        "Trujillo"
    ],
    "name:deu_x_preferred":[
        "Trujillo"
    ],
    "name:epo_x_preferred":[
        "Trujillo"
    ],
    "name:est_x_preferred":[
        "Trujillo"
    ],
    "name:eus_x_preferred":[
        "Trujillo"
    ],
    "name:ext_x_preferred":[
        "Trugillu"
    ],
    "name:fas_x_preferred":[
        "\u062a\u0631\u0648\u062e\u06cc\u0648"
    ],
    "name:fin_x_preferred":[
        "Trujillo"
    ],
    "name:fra_x_preferred":[
        "Trujillo"
    ],
    "name:glg_x_preferred":[
        "Trujillo"
    ],
    "name:heb_x_preferred":[
        "\u05d8\u05e8\u05d5\u05d7\u05d9\u05d5"
    ],
    "name:hun_x_preferred":[
        "Trujillo"
    ],
    "name:ita_x_preferred":[
        "Trujillo"
    ],
    "name:jpn_x_preferred":[
        "\u30c8\u30eb\u30d2\u30fc\u30ea\u30e7"
    ],
    "name:kat_x_preferred":[
        "\u10e2\u10e0\u10e3\u10ee\u10d8\u10da\u10d8\u10dd"
    ],
    "name:kor_x_preferred":[
        "\ud2b8\ub8e8\ud788\uc694"
    ],
    "name:lit_x_preferred":[
        "Truchiljas"
    ],
    "name:nds_x_preferred":[
        "Trujillo"
    ],
    "name:nld_x_preferred":[
        "Trujillo"
    ],
    "name:nor_x_preferred":[
        "Trujillo"
    ],
    "name:pol_x_preferred":[
        "Trujillo"
    ],
    "name:por_x_preferred":[
        "Trujillo"
    ],
    "name:que_x_preferred":[
        "Trujillo"
    ],
    "name:rus_x_preferred":[
        "\u0422\u0440\u0443\u0445\u0438\u043b\u044c\u043e"
    ],
    "name:sco_x_preferred":[
        "Trujillo"
    ],
    "name:spa_x_preferred":[
        "Trujillo"
    ],
    "name:srp_x_preferred":[
        "\u0422\u0440\u0443\u0445\u0438\u0459\u043e"
    ],
    "name:swe_x_preferred":[
        "Trujillo"
    ],
    "name:ukr_x_preferred":[
        "\u0422\u0440\u0443\u0445\u0456\u043b\u044c\u0439\u043e"
    ],
    "name:war_x_preferred":[
        "Trujillo"
    ],
    "name:zho_x_preferred":[
        "\u7279\u9c81\u5e0c\u7565"
    ],
    "wof:name":"Trujillo",
    "wof:placetype":"locality"
},
  "geometry": {"coordinates":[-87.13160000000001,12.72467],"type":"Point"}
}