{
  "type": "Feature",
  "properties": {
    "gn:admin1_code":"3.0",
    "gn:asciiname":"Trujillo",
    "gn:country_code":"NI",
    "gn:dem":77,
    "gn:feature_class":"P",
    "gn:feature_code":"PPL",
    "gn:name":"Trujillo",
    "gn:population":0,
    "gn:timezone":"America/Managua",
    "iso:country":"NI",
    "wof:name":"Trujillo",
    "wof:placetype":"locality"
},
  "geometry": {"coordinates":[-87.13160000000001,12.72467],"type":"Point"}
}