{
  "type": "Feature",
  "properties": {
    "gn:admin1_code":"18.0",
    "gn:asciiname":"Rama Cay",
    "gn:country_code":"NI",
    "gn:dem":11,
    "gn:feature_class":"P",
    "gn:feature_code":"PPL",
    "gn:name":"Rama Cay",
    "gn:population":0,
    "gn:timezone":"America/Managua",
    "iso:country":"NI",
    "name:cat_x_preferred":[
        "Cayo Rama"
    ],
    "name:ceb_x_preferred":[
        "Rama Cay"
    ],
    "name:fin_x_preferred":[
        "Rama Cay"
    ],
    "name:kat_x_preferred":[
        "\u10e0\u10d0\u10db\u10d8\u10e1 \u10e0\u10d8\u10e4\u10d8"
    ],
    "name:spa_x_preferred":[
        "Cayo Rama"
    ],
    "name:swe_x_preferred":[
        "Rama Cay"
    ],
    "wof:name":"Rama Cay",
    "wof:placetype":"locality"
},
  "geometry": {"coordinates":[-83.80874,11.88111],"type":"Point"}
}