{
  "type": "Feature",
  "properties": {
    "gn:admin1_code":"18.0",
    "gn:asciiname":"Rama Cay",
    "gn:country_code":"NI",
    "gn:dem":11,
    "gn:feature_class":"P",
    "gn:feature_code":"PPL",
    "gn:name":"Rama Cay",
    "gn:population":0,
    "gn:timezone":"America/Managua",
    "iso:country":"NI",
    "wof:name":"Rama Cay",
    "wof:placetype":"locality"
},
  "geometry": {"coordinates":[-83.80874,11.88111],"type":"Point"}
}