{
  "type": "Feature",
  "properties": {
    "iso:country":"NI",
    "name:ast_x_preferred":[
        "Puerto Moraz\u00e1n"
    ],
    "name:cat_x_preferred":[
        "Puerto Moraz\u00e1n"
    ],
    "name:ceb_x_preferred":[
        "Puerto Moraz\u00e1n"
    ],
    "name:ell_x_preferred":[
        "\u03a0\u03bf\u03c5\u03ad\u03c1\u03c4\u03bf \u039c\u03bf\u03c1\u03b1\u03c3\u03ac\u03bd"
    ],
    "name:eng_x_preferred":[
        "Puerto Moraz\u00e1n"
    ],
    "name:eus_x_preferred":[
        "Puerto Moraz\u00e1n"
    ],
    "name:fra_x_preferred":[
        "Puerto Moraz\u00e1n"
    ],
    "name:ita_x_preferred":[
        "Puerto Moraz\u00e1n"
    ],
    "name:nan_x_preferred":[
        "Puerto Moraz\u00e1n"
    ],
    "name:nld_x_preferred":[
        "Puerto Moraz\u00e1n"
    ],
    "name:pol_x_preferred":[
        "Puerto Moraz\u00e1n"
    ],
    "name:por_x_preferred":[
        "Puerto Moraz\u00e1n"
    ],
    "name:sco_x_preferred":[
        "Puerto Moraz\u00e1n"
    ],
    "name:spa_x_preferred":[
        "Puerto Moraz\u00e1n"
    ],
    "name:swe_x_preferred":[
        "Puerto Moraz\u00e1n"
    ],
    "name:und_x_variant":[
        "Moraz\u00e1n"
    ],
    "name:urd_x_preferred":[
        "\u067e\u0648\u06cc\u0631\u062a\u0648 \u0645\u0648\u0631\u0627\u0633\u0627\u0646"
    ],
    "name:vie_x_preferred":[
        "Puerto Moraz\u00e1n"
    ],
    "name:zho_x_preferred":[
        "\u83ab\u62c9\u6851\u6e2f"
    ],
    "qs:gn_country":"NI",
    "qs:gn_fcode":"PPL",
    "qs:gn_pop":7671,
    "qs:name":"Puerto Morazan",
    "qs:name_adm0":"Nicaragua",
    "qs:name_adm1":"Chinandega",
    "qs:photos":0,
    "qs:photos_1k":0,
    "qs:photos_9k":0,
    "qs:photos_9r":0,
    "qs:photos_all":0,
    "qs:photos_sr":0,
    "qs:placetype":"Town",
    "qs:pop_sr":"5",
    "qs:woe_adm0":23424915,
    "wd:wordcount":74,
    "wof:name":"Puerto Morazan",
    "wof:placetype":"locality",
    "wof:population":7671
},
  "geometry": {"coordinates":[-87.17167000000001,12.85042],"type":"Point"}
}