{
  "type": "Feature",
  "properties": {
    "gn:admin1_code":"5.0",
    "gn:asciiname":"Las Tablas",
    "gn:country_code":"NI",
    "gn:dem":563,
    "gn:feature_class":"P",
    "gn:feature_code":"PPL",
    "gn:name":"Las Tablas",
    "gn:population":0,
    "gn:timezone":"America/Managua",
    "iso:country":"NI",
    "name:ceb_x_preferred":[
        "Las Tablas"
    ],
    "name:ita_x_preferred":[
        "Las Tablas"
    ],
    "name:spa_x_preferred":[
        "Las Tablas"
    ],
    "name:srp_x_preferred":[
        "\u041b\u0430\u0441 \u0422\u0430\u0431\u043b\u0430\u0441"
    ],
    "name:swe_x_preferred":[
        "Las Tablas"
    ],
    "name:und_x_variant":[
        "Tablas",
        "Las Tablas"
    ],
    "wof:name":"Las Tablas",
    "wof:placetype":"locality"
},
  "geometry": {"coordinates":[-86.61473000000002,13.10498],"type":"Point"}
}