{
  "type": "Feature",
  "properties": {
    "gn:admin1_code":"11.0",
    "gn:asciiname":"Las Sabanas",
    "gn:country_code":"NI",
    "gn:dem":428,
    "gn:feature_class":"P",
    "gn:feature_code":"PPL",
    "gn:name":"Las Sabanas",
    "gn:population":0,
    "gn:timezone":"America/Managua",
    "iso:country":"NI",
    "name:ceb_x_preferred":[
        "Las Sabanas"
    ],
    "name:ell_x_preferred":[
        "\u039b\u03b1\u03c2 \u03a3\u03b1\u03bc\u03c0\u03ac\u03bd\u03b1\u03c2"
    ],
    "name:fra_x_preferred":[
        "Las Sabanas"
    ],
    "name:ita_x_preferred":[
        "Las Sabanas"
    ],
    "name:spa_x_preferred":[
        "Las Sabanas"
    ],
    "name:swe_x_preferred":[
        "Las Sabanas"
    ],
    "name:urd_x_preferred":[
        "\u0644\u0627\u0633 \u0633\u0627\u0628\u0627\u0646\u0627\u0633"
    ],
    "name:vie_x_preferred":[
        "Las Sabanas"
    ],
    "name:zho_x_preferred":[
        "\u62c9\u65af\u85a9\u74e6\u7d0d\u65af"
    ],
    "wof:name":"Las Sabanas",
    "wof:placetype":"locality"
},
  "geometry": {"coordinates":[-86.16667,11.95],"type":"Point"}
}