{
  "type": "Feature",
  "properties": {
    "gn:admin1_code":"11.0",
    "gn:asciiname":"Las Sabanas",
    "gn:country_code":"NI",
    "gn:dem":428,
    "gn:feature_class":"P",
    "gn:feature_code":"PPL",
    "gn:name":"Las Sabanas",
    "gn:population":0,
    "gn:timezone":"America/Managua",
    "iso:country":"NI",
    "wof:name":"Las Sabanas",
    "wof:placetype":"locality"
},
  "geometry": {"coordinates":[-86.16667,11.95],"type":"Point"}
}