{
  "type": "Feature",
  "properties": {
    "gn:admin1_code":"2.0",
    "gn:asciiname":"El Nagerotena",
    "gn:country_code":"NI",
    "gn:dem":221,
    "gn:feature_class":"P",
    "gn:feature_code":"PPL",
    "gn:name":"El Nagerotena",
    "gn:population":0,
    "gn:timezone":"America/Managua",
    "iso:country":"NI",
    "name:spa_x_preferred":[
        "El Nagerotena"
    ],
    "wof:name":"El Nagerotena",
    "wof:placetype":"locality"
},
  "geometry": {"coordinates":[-86.13964,11.74447],"type":"Point"}
}