{
  "type": "Feature",
  "properties": {
    "gn:admin1_code":"13.0",
    "gn:asciiname":"Susucayan",
    "gn:country_code":"NI",
    "gn:dem":587,
    "gn:feature_class":"P",
    "gn:feature_code":"PPL",
    "gn:name":"Susucay\u00e1n",
    "gn:population":0,
    "gn:timezone":"America/Managua",
    "iso:country":"NI",
    "name:und_x_variant":[
        "Suscallon",
        "Susucay\u00e1n"
    ],
    "wof:name":"Susucayan",
    "wof:placetype":"locality"
},
  "geometry": {"coordinates":[-86.17156,13.674],"type":"Point"}
}