{
  "type": "Feature",
  "properties": {
    "iso:country":"NI",
    "name:ceb_x_preferred":[
        "Santa Rosa del Pe\u00f1\u00f3n"
    ],
    "name:ell_x_preferred":[
        "\u03a3\u03ac\u03bd\u03c4\u03b1 \u03a1\u03cc\u03c3\u03b1 \u03b4\u03b5\u03bb \u03a0\u03b5\u03bd\u03b9\u03cc\u03bd"
    ],
    "name:eng_x_preferred":[
        "Santa Rosa del Pe\u00f1\u00f3n"
    ],
    "name:fra_x_preferred":[
        "Santa Rosa del Pe\u00f1\u00f3n"
    ],
    "name:ita_x_preferred":[
        "Santa Rosa del Pe\u00f1\u00f3n"
    ],
    "name:nld_x_preferred":[
        "Santa Rosa del Pe\u00f1\u00f3n"
    ],
    "name:spa_x_preferred":[
        "Santa Rosa del Pe\u00f1\u00f3n"
    ],
    "name:swe_x_preferred":[
        "Santa Rosa del Pe\u00f1\u00f3n"
    ],
    "name:und_x_variant":[
        "Santa Rosa"
    ],
    "name:urd_x_preferred":[
        "\u0633\u0627\u0646\u062a\u0627 \u0631\u0648\u0632\u0627 \u062f\u06cc\u0644 \u067e\u06cc\u0646\u0648\u0646"
    ],
    "name:vie_x_preferred":[
        "Santa Rosa del Pe\u00f1\u00f3n"
    ],
    "name:zho_x_preferred":[
        "\u8056\u7f85\u85a9\u5fb7\u723e\u4f69\u5c3c\u7fc1"
    ],
    "qs:gn_country":"NI",
    "qs:gn_fcode":"PPL",
    "qs:gn_pop":2913,
    "qs:name":"Santa Rosa del Pe\u00f1\u00f3n",
    "qs:name_adm0":"Nicaragua",
    "qs:name_adm1":"Le\u00f3n",
    "qs:photos":0,
    "qs:photos_1k":0,
    "qs:photos_9k":1,
    "qs:photos_9r":1,
    "qs:photos_all":2,
    "qs:photos_sr":0,
    "qs:placetype":"Town",
    "qs:pop_sr":"4",
    "qs:woe_adm0":23424915,
    "wd:wordcount":36,
    "wof:name":"Santa Rosa del Pe\u00f1\u00f3n",
    "wof:placetype":"locality",
    "wof:population":2913
},
  "geometry": {"coordinates":[-86.36994,12.80116],"type":"Point"}
}