{
  "type": "Feature",
  "properties": {
    "gn:admin1_code":"10.0",
    "gn:asciiname":"El Boqueron",
    "gn:country_code":"NI",
    "gn:dem":50,
    "gn:feature_class":"P",
    "gn:feature_code":"PPL",
    "gn:name":"El Boquer\u00f3n",
    "gn:population":0,
    "gn:timezone":"America/Managua",
    "iso:country":"NI",
    "name:und_x_variant":[
        "Boquer\u00f3n",
        "El Boquer\u00f3n"
    ],
    "wof:name":"El Boqueron",
    "wof:placetype":"locality"
},
  "geometry": {"coordinates":[-86.52421,12.28771],"type":"Point"}
}