{
  "type": "Feature",
  "properties": {
    "gn:admin1_code":"3.0",
    "gn:asciiname":"Campuzano",
    "gn:country_code":"NI",
    "gn:dem":23,
    "gn:feature_class":"P",
    "gn:feature_code":"PPL",
    "gn:name":"Campuzano",
    "gn:population":0,
    "gn:timezone":"America/Managua",
    "iso:country":"NI",
    "wof:name":"Campuzano",
    "wof:placetype":"locality"
},
  "geometry": {"coordinates":[-87.06141,12.79239],"type":"Point"}
}