{
  "type": "Feature",
  "properties": {
    "gn:admin1_code":"4.0",
    "gn:asciiname":"El Tule",
    "gn:country_code":"NI",
    "gn:dem":426,
    "gn:feature_class":"P",
    "gn:feature_code":"PPL",
    "gn:name":"El Tule",
    "gn:population":0,
    "gn:timezone":"America/Managua",
    "iso:country":"NI",
    "name:ceb_x_preferred":[
        "El Tule"
    ],
    "name:srp_x_preferred":[
        "\u0415\u043b \u0422\u0443\u043b\u0435"
    ],
    "name:swe_x_preferred":[
        "El Tule"
    ],
    "wof:name":"El Tule",
    "wof:placetype":"locality"
},
  "geometry": {"coordinates":[-85.44605,12.23831],"type":"Point"}
}