{
  "type": "Feature",
  "properties": {
    "iso:country":"NI",
    "name:afr_x_preferred":[
        "El Viejo"
    ],
    "name:deu_x_preferred":[
        "El Viejo"
    ],
    "name:ell_x_preferred":[
        "\u0395\u03bb \u0392\u03b9\u03ad\u03c7\u03bf"
    ],
    "name:eng_x_preferred":[
        "El Viejo"
    ],
    "name:fra_x_preferred":[
        "El Viejo"
    ],
    "name:ita_x_preferred":[
        "El Viejo"
    ],
    "name:lit_x_preferred":[
        "El Vjechas"
    ],
    "name:nld_x_preferred":[
        "El Viejo"
    ],
    "name:pol_x_preferred":[
        "El Viejo"
    ],
    "name:rus_x_preferred":[
        "\u042d\u043b\u044c-\u0412\u044c\u0435\u0445\u043e"
    ],
    "name:spa_x_preferred":[
        "El Viejo"
    ],
    "name:swe_x_preferred":[
        "El Viejo"
    ],
    "name:unk_x_variant":[
        "Viejo"
    ],
    "name:urd_x_preferred":[
        "\u0627\u06cc\u0644 \u0648\u06cc\u0626\u062e\u0648"
    ],
    "name:vie_x_preferred":[
        "El Viejo"
    ],
    "name:zho_x_preferred":[
        "\u57c3\u723e\u5225\u970d"
    ],
    "qs:gn_country":"NI",
    "qs:gn_fcode":"PPL",
    "qs:gn_pop":53504,
    "qs:name":"El Viejo",
    "qs:name_adm0":"Nicaragua",
    "qs:name_adm1":"Chinandega",
    "qs:photos":321,
    "qs:photos_1k":65,
    "qs:photos_9k":1,
    "qs:photos_9r":5,
    "qs:photos_all":321,
    "qs:photos_sr":5,
    "qs:placetype":"Town",
    "qs:pop_sr":"8",
    "qs:woe_adm0":23424915,
    "wof:name":"El Viejo",
    "wof:placetype":"locality",
    "wof:population":53504
},
  "geometry": {"coordinates":[-87.16722,12.6633],"type":"Point"}
}