{
  "type": "Feature",
  "properties": {
    "gn:admin1_code":"16.0",
    "gn:asciiname":"Huahua",
    "gn:country_code":"NI",
    "gn:dem":3,
    "gn:feature_class":"P",
    "gn:feature_code":"PPL",
    "gn:name":"Huahua",
    "gn:population":0,
    "gn:timezone":"America/Managua",
    "iso:country":"NI",
    "wof:name":"Huahua",
    "wof:placetype":"locality"
},
  "geometry": {"coordinates":[-83.46734000000002,13.87241],"type":"Point"}
}