{
  "type": "Feature",
  "properties": {
    "gn:admin1_code":"12.0",
    "gn:asciiname":"Waswali Abajo",
    "gn:country_code":"NI",
    "gn:dem":627,
    "gn:feature_class":"P",
    "gn:feature_code":"PPL",
    "gn:name":"Waswal\u00ed Abajo",
    "gn:population":0,
    "gn:timezone":"America/Managua",
    "iso:country":"NI",
    "name:und_x_variant":[
        "Waslala",
        "Waswali",
        "Waswal\u00ed Abajo"
    ],
    "wof:name":"Waswali Abajo",
    "wof:placetype":"locality"
},
  "geometry": {"coordinates":[-85.97617,12.91932],"type":"Point"}
}