{
  "type": "Feature",
  "properties": {
    "gn:admin1_code":"12.0",
    "gn:asciiname":"Nombre de Jesus",
    "gn:country_code":"NI",
    "gn:dem":627,
    "gn:feature_class":"P",
    "gn:feature_code":"PPL",
    "gn:name":"Nombre de Jes\u00fas",
    "gn:population":0,
    "gn:timezone":"America/Managua",
    "iso:country":"NI",
    "wof:name":"Nombre de Jesus",
    "wof:placetype":"locality"
},
  "geometry": {"coordinates":[-85.94386999999998,12.5839],"type":"Point"}
}