{
  "type": "Feature",
  "properties": {
    "gn:admin1_code":"2.0",
    "gn:asciiname":"Las Lomas",
    "gn:country_code":"NI",
    "gn:dem":38,
    "gn:feature_class":"P",
    "gn:feature_code":"PPL",
    "gn:name":"Las Lomas",
    "gn:population":0,
    "gn:timezone":"America/Managua",
    "iso:country":"NI",
    "name:spa_x_preferred":[
        "Las Lomas"
    ],
    "wof:name":"Las Lomas",
    "wof:placetype":"locality"
},
  "geometry": {"coordinates":[-86.32814,11.67391],"type":"Point"}
}