{
  "type": "Feature",
  "properties": {
    "gn:admin1_code":"2.0",
    "gn:asciiname":"Las Lomas",
    "gn:country_code":"NI",
    "gn:dem":38,
    "gn:feature_class":"P",
    "gn:feature_code":"PPL",
    "gn:name":"Las Lomas",
    "gn:population":0,
    "gn:timezone":"America/Managua",
    "iso:country":"NI",
    "name:ceb_x_preferred":[
        "Las Lomas"
    ],
    "name:deu_x_preferred":[
        "Las Lomas"
    ],
    "name:ita_x_preferred":[
        "Las Lomas"
    ],
    "name:nld_x_preferred":[
        "Las Lomas"
    ],
    "name:por_x_preferred":[
        "Las Lomas"
    ],
    "name:sco_x_preferred":[
        "Las Lomas"
    ],
    "name:spa_x_preferred":[
        "Las Lomas"
    ],
    "name:srp_x_preferred":[
        "\u041b\u0430\u0441 \u041b\u043e\u043c\u0430\u0441"
    ],
    "name:swe_x_preferred":[
        "Las Lomas"
    ],
    "name:vol_x_preferred":[
        "Las Lomas"
    ],
    "wof:name":"Las Lomas",
    "wof:placetype":"locality"
},
  "geometry": {"coordinates":[-86.32814,11.67391],"type":"Point"}
}