{
  "type": "Feature",
  "properties": {
    "gn:admin1_code":"11.0",
    "gn:asciiname":"Barrio Pio XII",
    "gn:country_code":"NI",
    "gn:dem":467,
    "gn:feature_class":"P",
    "gn:feature_code":"PPL",
    "gn:name":"Barrio P\u00edo XII",
    "gn:population":0,
    "gn:timezone":"America/Managua",
    "iso:country":"NI",
    "name:und_x_variant":[
        "P\u00edoxil",
        "P\u00edoxll",
        "P\u00edo XII",
        "Barrio P\u00edo XII"
    ],
    "wof:name":"Barrio Pio XII",
    "wof:placetype":"locality"
},
  "geometry": {"coordinates":[-86.12509,11.90162],"type":"Point"}
}