{
  "type": "Feature",
  "properties": {
    "gn:asciiname":"Little Corn Island",
    "gn:country_code":"NI",
    "gn:dem":13,
    "gn:feature_class":"P",
    "gn:feature_code":"PPL",
    "gn:name":"Little Corn Island",
    "gn:population":0,
    "gn:timezone":"America/Managua",
    "iso:country":"NI",
    "wof:name":"Little Corn Island",
    "wof:placetype":"locality"
},
  "geometry": {"coordinates":[-82.9812,12.28889],"type":"Point"}
}