{
  "type": "Feature",
  "properties": {
    "gn:admin1_code":"12.0",
    "gn:asciiname":"La Perla",
    "gn:country_code":"NI",
    "gn:dem":767,
    "gn:feature_class":"P",
    "gn:feature_code":"PPL",
    "gn:name":"La Perla",
    "gn:population":0,
    "gn:timezone":"America/Managua",
    "iso:country":"NI",
    "name:ceb_x_preferred":[
        "La Perla"
    ],
    "name:deu_x_preferred":[
        "La Perla"
    ],
    "name:epo_x_preferred":[
        "La Perla"
    ],
    "name:fra_x_preferred":[
        "La Perla"
    ],
    "name:ita_x_preferred":[
        "La perla"
    ],
    "name:nld_x_preferred":[
        "La Perla"
    ],
    "name:spa_x_preferred":[
        "La Perla"
    ],
    "name:srp_x_preferred":[
        "\u041b\u0430 \u041f\u0435\u0440\u043b\u0430"
    ],
    "name:swe_x_preferred":[
        "La Perla"
    ],
    "wof:name":"La Perla",
    "wof:placetype":"locality"
},
  "geometry": {"coordinates":[-85.63414,12.95785],"type":"Point"}
}