{
  "type": "Feature",
  "properties": {
    "gn:admin1_code":"18.0",
    "gn:asciiname":"El Perro",
    "gn:country_code":"NI",
    "gn:dem":111,
    "gn:feature_class":"P",
    "gn:feature_code":"PPL",
    "gn:name":"El Perro",
    "gn:population":0,
    "gn:timezone":"America/Managua",
    "iso:country":"NI",
    "wof:name":"El Perro",
    "wof:placetype":"locality"
},
  "geometry": {"coordinates":[-84.69001999999998,12.91481],"type":"Point"}
}