{
  "type": "Feature",
  "properties": {
    "gn:admin1_code":"1.0",
    "gn:asciiname":"Tomatollita",
    "gn:country_code":"NI",
    "gn:dem":632,
    "gn:feature_class":"P",
    "gn:feature_code":"PPL",
    "gn:name":"Tomatollita",
    "gn:population":0,
    "gn:timezone":"America/Managua",
    "iso:country":"NI",
    "wof:name":"Tomatollita",
    "wof:placetype":"locality"
},
  "geometry": {"coordinates":[-85.91972,12.5141],"type":"Point"}
}