{
  "type": "Feature",
  "properties": {
    "gn:admin1_code":"8.0",
    "gn:asciiname":"La Marimba",
    "gn:country_code":"NI",
    "gn:dem":9,
    "gn:feature_class":"P",
    "gn:feature_code":"PPL",
    "gn:name":"La Marimba",
    "gn:population":0,
    "gn:timezone":"America/Managua",
    "iso:country":"NI",
    "wof:name":"La Marimba",
    "wof:placetype":"locality"
},
  "geometry": {"coordinates":[-86.83333,12.26667],"type":"Point"}
}