{
  "type": "Feature",
  "properties": {
    "gn:admin1_code":"4.0",
    "gn:asciiname":"Las Lajitas",
    "gn:country_code":"NI",
    "gn:dem":112,
    "gn:feature_class":"P",
    "gn:feature_code":"PPL",
    "gn:name":"Las Lajitas",
    "gn:population":0,
    "gn:timezone":"America/Managua",
    "iso:country":"NI",
    "name:ceb_x_preferred":[
        "Las Lajitas"
    ],
    "name:por_x_preferred":[
        "Las Lajitas"
    ],
    "name:spa_x_preferred":[
        "Las Lajitas"
    ],
    "name:urd_x_preferred":[
        "\u0644\u0627\u0633 \u0644\u0627\u062c\u06cc\u0679\u0627\u0633"
    ],
    "wof:name":"Las Lajitas",
    "wof:placetype":"locality"
},
  "geometry": {"coordinates":[-85.40782,12.12871],"type":"Point"}
}