{
  "type": "Feature",
  "properties": {
    "gn:admin1_code":"17.0",
    "gn:asciiname":"Bilwaskarma",
    "gn:country_code":"NI",
    "gn:dem":39,
    "gn:feature_class":"P",
    "gn:feature_code":"PPL",
    "gn:name":"Bilwaskarma",
    "gn:population":0,
    "gn:timezone":"America/Managua",
    "iso:country":"NI",
    "name:und_x_variant":[
        "Karma",
        "Bilas",
        "Bilas Carmen",
        "Bilhuas",
        "Bilwascarma",
        "Bilwarkarma",
        "Bilwaskarma"
    ],
    "wof:name":"Bilwaskarma",
    "wof:placetype":"locality"
},
  "geometry": {"coordinates":[-83.88285999999999,14.7588],"type":"Point"}
}