{
  "type": "Feature",
  "properties": {
    "gn:admin1_code":"6.0",
    "gn:asciiname":"San Francisco de Cascabel",
    "gn:country_code":"NI",
    "gn:dem":41,
    "gn:feature_class":"P",
    "gn:feature_code":"PPL",
    "gn:name":"San Francisco de Cascabel",
    "gn:population":0,
    "gn:timezone":"America/Managua",
    "iso:country":"NI",
    "name:spa_x_preferred":[
        "San Francisco de Cascabel"
    ],
    "wof:name":"San Francisco de Cascabel",
    "wof:placetype":"locality"
},
  "geometry": {"coordinates":[-85.84729,11.71332],"type":"Point"}
}