{
  "type": "Feature",
  "properties": {
    "gn:admin1_code":"2.0",
    "gn:asciiname":"Vado",
    "gn:country_code":"NI",
    "gn:dem":98,
    "gn:feature_class":"P",
    "gn:feature_code":"PPL",
    "gn:name":"Vado",
    "gn:population":0,
    "gn:timezone":"America/Managua",
    "iso:country":"NI",
    "name:ceb_x_preferred":[
        "Vado"
    ],
    "name:ita_x_preferred":[
        "Vado"
    ],
    "name:jpn_x_preferred":[
        "\u30f4\u30a1\u30fc\u30c9"
    ],
    "name:spa_x_preferred":[
        "Vado"
    ],
    "name:srp_x_preferred":[
        "Vado"
    ],
    "name:swe_x_preferred":[
        "Vado"
    ],
    "wof:name":"Vado",
    "wof:placetype":"locality"
},
  "geometry": {"coordinates":[-86.05824,11.71493],"type":"Point"}
}