{
  "type": "Feature",
  "properties": {
    "gn:admin1_code":"18.0",
    "gn:asciiname":"Karawala",
    "gn:country_code":"NI",
    "gn:dem":11,
    "gn:feature_class":"P",
    "gn:feature_code":"PPL",
    "gn:name":"Karawala",
    "gn:population":0,
    "gn:timezone":"America/Managua",
    "iso:country":"NI",
    "name:spa_x_preferred":[
        "Karawala"
    ],
    "wof:name":"Karawala",
    "wof:placetype":"locality"
},
  "geometry": {"coordinates":[-83.57724,12.93072],"type":"Point"}
}