{
  "type": "Feature",
  "properties": {
    "gn:admin1_code":"15.0",
    "gn:asciiname":"Esquipulas",
    "gn:country_code":"NI",
    "gn:dem":50,
    "gn:feature_class":"P",
    "gn:feature_code":"PPL",
    "gn:name":"Esquipulas",
    "gn:population":0,
    "gn:timezone":"America/Managua",
    "iso:country":"NI",
    "name:ceb_x_preferred":[
        "Esquipulas"
    ],
    "name:deu_x_preferred":[
        "Esquipulas"
    ],
    "name:fra_x_preferred":[
        "Esquipulas"
    ],
    "name:ind_x_preferred":[
        "Esquipulas"
    ],
    "name:ita_x_preferred":[
        "Esquipulas"
    ],
    "name:lit_x_preferred":[
        "Eskipulasas"
    ],
    "name:pol_x_preferred":[
        "Esquipulas"
    ],
    "name:por_x_preferred":[
        "Esquipulas"
    ],
    "name:spa_x_preferred":[
        "Esquipulas"
    ],
    "name:und_x_variant":[
        "Esquipula",
        "Esquipulas"
    ],
    "name:urd_x_preferred":[
        "\u0627\u06cc\u0633\u06a9\u0648\u06cc\u067e\u0648\u0644\u0627\u0633"
    ],
    "name:vie_x_preferred":[
        "Esquipulas"
    ],
    "name:zho_x_preferred":[
        "\u57c3\u65af\u57fa\u666e\u62c9\u65af"
    ],
    "wof:name":"Esquipulas",
    "wof:placetype":"locality"
},
  "geometry": {"coordinates":[-85.70602,11.50672],"type":"Point"}
}