{
  "type": "Feature",
  "properties": {
    "gn:admin1_code":"15.0",
    "gn:asciiname":"Esquipulas",
    "gn:country_code":"NI",
    "gn:dem":50,
    "gn:feature_class":"P",
    "gn:feature_code":"PPL",
    "gn:name":"Esquipulas",
    "gn:population":0,
    "gn:timezone":"America/Managua",
    "iso:country":"NI",
    "name:und_x_variant":[
        "Esquipula",
        "Esquipulas"
    ],
    "wof:name":"Esquipulas",
    "wof:placetype":"locality"
},
  "geometry": {"coordinates":[-85.70602,11.50672],"type":"Point"}
}