{
  "type": "Feature",
  "properties": {
    "gn:admin1_code":"4.0",
    "gn:asciiname":"Canas Gordas",
    "gn:country_code":"NI",
    "gn:dem":36,
    "gn:feature_class":"P",
    "gn:feature_code":"PPL",
    "gn:name":"Ca\u00f1as Gordas",
    "gn:population":0,
    "gn:timezone":"America/Managua",
    "iso:country":"NI",
    "wof:name":"Canas Gordas",
    "wof:placetype":"locality"
},
  "geometry": {"coordinates":[-85.40419,11.88895],"type":"Point"}
}