{
  "type": "Feature",
  "properties": {
    "gn:admin1_code":"10.0",
    "gn:asciiname":"Comarca San Jose De Las Canadas",
    "gn:country_code":"NI",
    "gn:dem":329,
    "gn:feature_class":"P",
    "gn:feature_code":"PPL",
    "gn:name":"Comarca San Jos\u00e9 De Las Ca\u00f1adas",
    "gn:population":0,
    "gn:timezone":"America/Managua",
    "iso:country":"NI",
    "wof:name":"Comarca San Jose De Las Canadas",
    "wof:placetype":"locality"
},
  "geometry": {"coordinates":[-86.32741999999998,12.09793],"type":"Point"}
}