{
  "type": "Feature",
  "properties": {
    "gn:admin1_code":"15.0",
    "gn:asciiname":"Santa Justa",
    "gn:country_code":"NI",
    "gn:dem":59,
    "gn:feature_class":"P",
    "gn:feature_code":"PPL",
    "gn:name":"Santa Justa",
    "gn:population":0,
    "gn:timezone":"America/Managua",
    "iso:country":"NI",
    "name:cat_x_preferred":[
        "Santa Justa"
    ],
    "name:ceb_x_preferred":[
        "Santa Justa"
    ],
    "name:deu_x_preferred":[
        "Santa Justa"
    ],
    "name:fra_x_preferred":[
        "Santa Justa"
    ],
    "name:ita_x_preferred":[
        "Santa Justa"
    ],
    "name:nld_x_preferred":[
        "Santa Justa"
    ],
    "name:por_x_preferred":[
        "Santa Justa"
    ],
    "name:rus_x_preferred":[
        "\u0421\u0430\u043d\u0442\u0430-\u0416\u0443\u0448\u0442\u0430"
    ],
    "name:spa_x_preferred":[
        "Santa Justa"
    ],
    "name:swe_x_preferred":[
        "Santa Justa"
    ],
    "wof:name":"Santa Justa",
    "wof:placetype":"locality"
},
  "geometry": {"coordinates":[-85.90987,11.59528],"type":"Point"}
}