{
  "type": "Feature",
  "properties": {
    "gn:admin1_code":"15.0",
    "gn:asciiname":"Santa Justa",
    "gn:country_code":"NI",
    "gn:dem":59,
    "gn:feature_class":"P",
    "gn:feature_code":"PPL",
    "gn:name":"Santa Justa",
    "gn:population":0,
    "gn:timezone":"America/Managua",
    "iso:country":"NI",
    "wof:name":"Santa Justa",
    "wof:placetype":"locality"
},
  "geometry": {"coordinates":[-85.90987,11.59528],"type":"Point"}
}