{
  "type": "Feature",
  "properties": {
    "gn:admin1_code":"3.0",
    "gn:asciiname":"Valle Las Pilas",
    "gn:country_code":"NI",
    "gn:dem":71,
    "gn:feature_class":"P",
    "gn:feature_code":"PPL",
    "gn:name":"Valle Las Pilas",
    "gn:population":0,
    "gn:timezone":"America/Managua",
    "iso:country":"NI",
    "wof:name":"Valle Las Pilas",
    "wof:placetype":"locality"
},
  "geometry": {"coordinates":[-86.77200999999999,13.00297],"type":"Point"}
}