{
  "type": "Feature",
  "properties": {
    "gn:admin1_code":"3.0",
    "gn:asciiname":"La Vaca",
    "gn:country_code":"NI",
    "gn:dem":17,
    "gn:feature_class":"P",
    "gn:feature_code":"PPL",
    "gn:name":"La Vaca",
    "gn:population":0,
    "gn:timezone":"America/Managua",
    "iso:country":"NI",
    "name:spa_x_preferred":[
        "Humedal La Vaca"
    ],
    "wof:name":"La Vaca",
    "wof:placetype":"locality"
},
  "geometry": {"coordinates":[-87.5391,12.84995],"type":"Point"}
}