{
  "type": "Feature",
  "properties": {
    "gn:admin1_code":"5.0",
    "gn:asciiname":"Los Llanos",
    "gn:country_code":"NI",
    "gn:dem":1074,
    "gn:feature_class":"P",
    "gn:feature_code":"PPL",
    "gn:name":"Los Llanos",
    "gn:population":0,
    "gn:timezone":"America/Managua",
    "iso:country":"NI",
    "wof:name":"Los Llanos",
    "wof:placetype":"locality"
},
  "geometry": {"coordinates":[-86.56959999999999,13.3044],"type":"Point"}
}