{
  "type": "Feature",
  "properties": {
    "gn:admin1_code":"12.0",
    "gn:asciiname":"Canada Grande",
    "gn:country_code":"NI",
    "gn:dem":878,
    "gn:feature_class":"P",
    "gn:feature_code":"PPL",
    "gn:name":"Ca\u00f1ada Grande",
    "gn:population":0,
    "gn:timezone":"America/Managua",
    "iso:country":"NI",
    "wof:name":"Canada Grande",
    "wof:placetype":"locality"
},
  "geometry": {"coordinates":[-85.95118000000002,12.74856],"type":"Point"}
}