{
  "type": "Feature",
  "properties": {
    "gn:admin1_code":"18.0",
    "gn:asciiname":"Larga Vista",
    "gn:country_code":"NI",
    "gn:dem":15,
    "gn:feature_class":"P",
    "gn:feature_code":"PPL",
    "gn:name":"Larga Vista",
    "gn:population":0,
    "gn:timezone":"America/Managua",
    "iso:country":"NI",
    "wof:name":"Larga Vista",
    "wof:placetype":"locality"
},
  "geometry": {"coordinates":[-83.82425000000001,12.44881],"type":"Point"}
}