{
  "type": "Feature",
  "properties": {
    "gn:admin1_code":"8.0",
    "gn:asciiname":"Mina Santa Pancha",
    "gn:country_code":"NI",
    "gn:dem":71,
    "gn:feature_class":"P",
    "gn:feature_code":"PPL",
    "gn:name":"Mina Santa Pancha",
    "gn:population":0,
    "gn:timezone":"America/Managua",
    "iso:country":"NI",
    "wof:name":"Mina Santa Pancha",
    "wof:placetype":"locality"
},
  "geometry": {"coordinates":[-86.69851,12.7372],"type":"Point"}
}