{
  "type": "Feature",
  "properties": {
    "gn:admin1_code":"6.0",
    "gn:asciiname":"El Amparo",
    "gn:country_code":"NI",
    "gn:dem":90,
    "gn:feature_class":"P",
    "gn:feature_code":"PPL",
    "gn:name":"El Amparo",
    "gn:population":0,
    "gn:timezone":"America/Managua",
    "iso:country":"NI",
    "name:spa_x_preferred":[
        "El Amparo"
    ],
    "wof:name":"El Amparo",
    "wof:placetype":"locality"
},
  "geometry": {"coordinates":[-85.97566999999999,11.9545],"type":"Point"}
}