{
  "type": "Feature",
  "properties": {
    "gn:admin1_code":"2.0",
    "gn:asciiname":"Los Baltodanos",
    "gn:country_code":"NI",
    "gn:dem":133,
    "gn:feature_class":"P",
    "gn:feature_code":"PPL",
    "gn:name":"Los Baltodanos",
    "gn:population":0,
    "gn:timezone":"America/Managua",
    "iso:country":"NI",
    "name:und_x_variant":[
        "Los Baltodano",
        "Los Baltodanos"
    ],
    "wof:name":"Los Baltodanos",
    "wof:placetype":"locality"
},
  "geometry": {"coordinates":[-86.36575000000001,11.79341],"type":"Point"}
}