{
  "type": "Feature",
  "properties": {
    "gn:admin1_code":"4.0",
    "gn:asciiname":"Aguas Calientes",
    "gn:country_code":"NI",
    "gn:dem":107,
    "gn:feature_class":"P",
    "gn:feature_code":"PPL",
    "gn:name":"Aguas Calientes",
    "gn:population":0,
    "gn:timezone":"America/Managua",
    "iso:country":"NI",
    "wof:name":"Aguas Calientes",
    "wof:placetype":"locality"
},
  "geometry": {"coordinates":[-85.37371,12.15419],"type":"Point"}
}