{
  "type": "Feature",
  "properties": {
    "gn:admin1_code":"10.0",
    "gn:asciiname":"Comarca Silvia Ferrufino",
    "gn:country_code":"NI",
    "gn:dem":269,
    "gn:feature_class":"P",
    "gn:feature_code":"PPL",
    "gn:name":"Comarca Silvia Ferrufino",
    "gn:population":0,
    "gn:timezone":"America/Managua",
    "iso:country":"NI",
    "wof:name":"Comarca Silvia Ferrufino",
    "wof:placetype":"locality"
},
  "geometry": {"coordinates":[-86.27549999999999,12.09524],"type":"Point"}
}