{
  "type": "Feature",
  "properties": {
    "gn:admin1_code":"12.0",
    "gn:asciiname":"Valle El Brasil",
    "gn:country_code":"NI",
    "gn:dem":370,
    "gn:feature_class":"P",
    "gn:feature_code":"PPL",
    "gn:name":"Valle El Brasil",
    "gn:population":0,
    "gn:timezone":"America/Managua",
    "iso:country":"NI",
    "name:und_x_variant":[
        "Brazil",
        "Brasil",
        "Valle El Brasil"
    ],
    "wof:name":"Valle El Brasil",
    "wof:placetype":"locality"
},
  "geometry": {"coordinates":[-86.2379,12.64933],"type":"Point"}
}