{
  "type": "Feature",
  "properties": {
    "gn:admin1_code":"17.0",
    "gn:asciiname":"Kauru Tingni",
    "gn:country_code":"NI",
    "gn:dem":58,
    "gn:feature_class":"P",
    "gn:feature_code":"PPL",
    "gn:name":"Kauru Tingni",
    "gn:population":0,
    "gn:timezone":"America/Managua",
    "iso:country":"NI",
    "wof:name":"Kauru Tingni",
    "wof:placetype":"locality"
},
  "geometry": {"coordinates":[-84.55029,14.6549],"type":"Point"}
}