{
  "type": "Feature",
  "properties": {
    "gn:admin1_code":"18.0",
    "gn:asciiname":"Cano Mocho",
    "gn:country_code":"NI",
    "gn:dem":24,
    "gn:feature_class":"P",
    "gn:feature_code":"PPL",
    "gn:name":"Ca\u00f1o Mocho",
    "gn:population":0,
    "gn:timezone":"America/Managua",
    "iso:country":"NI",
    "name:und_x_variant":[
        "Moho Creek",
        "Ca\u00f1o Moho",
        "Ca\u00f1o Mocho"
    ],
    "wof:name":"Cano Mocho",
    "wof:placetype":"locality"
},
  "geometry": {"coordinates":[-83.80639000000002,12.11674],"type":"Point"}
}