{
  "type": "Feature",
  "properties": {
    "gn:admin1_code":"17.0",
    "gn:asciiname":"Kligna",
    "gn:country_code":"NI",
    "gn:dem":69,
    "gn:feature_class":"P",
    "gn:feature_code":"PPL",
    "gn:name":"Kligna",
    "gn:population":0,
    "gn:timezone":"America/Managua",
    "iso:country":"NI",
    "name:und_x_variant":[
        "Klinas",
        "Kligna"
    ],
    "wof:name":"Kligna",
    "wof:placetype":"locality"
},
  "geometry": {"coordinates":[-84.43881,14.57444],"type":"Point"}
}