{
  "type": "Feature",
  "properties": {
    "gn:admin1_code":"1.0",
    "gn:asciiname":"El Tabano",
    "gn:country_code":"NI",
    "gn:dem":216,
    "gn:feature_class":"P",
    "gn:feature_code":"PPL",
    "gn:name":"El T\u00e1bano",
    "gn:population":0,
    "gn:timezone":"America/Managua",
    "iso:country":"NI",
    "wof:name":"El Tabano",
    "wof:placetype":"locality"
},
  "geometry": {"coordinates":[-85.93351,12.41864],"type":"Point"}
}