{
  "type": "Feature",
  "properties": {
    "gn:admin1_code":"9.0",
    "gn:asciiname":"Verapaz",
    "gn:country_code":"NI",
    "gn:dem":643,
    "gn:feature_class":"P",
    "gn:feature_code":"PPL",
    "gn:name":"Verapaz",
    "gn:population":0,
    "gn:timezone":"America/Managua",
    "iso:country":"NI",
    "name:deu_x_preferred":[
        "Verapaz"
    ],
    "name:por_x_preferred":[
        "Verapaz"
    ],
    "name:sco_x_preferred":[
        "Verapaz"
    ],
    "name:spa_x_preferred":[
        "Verapaz"
    ],
    "name:srp_x_preferred":[
        "\u0412\u0435\u0440\u0430\u043f\u0430\u0437"
    ],
    "name:ukr_x_preferred":[
        "\u0412\u0435\u0440\u0430\u043f\u0430\u0441"
    ],
    "wof:name":"Verapaz",
    "wof:placetype":"locality"
},
  "geometry": {"coordinates":[-86.52761,13.56785],"type":"Point"}
}