{
  "type": "Feature",
  "properties": {
    "gn:admin1_code":"5.0",
    "gn:asciiname":"El Potrerillo",
    "gn:country_code":"NI",
    "gn:dem":836,
    "gn:feature_class":"P",
    "gn:feature_code":"PPL",
    "gn:name":"El Potrerillo",
    "gn:population":0,
    "gn:timezone":"America/Managua",
    "iso:country":"NI",
    "name:und_x_variant":[
        "Potrerillo",
        "Potrerios",
        "Potrerillos",
        "El Potrerillo"
    ],
    "wof:name":"El Potrerillo",
    "wof:placetype":"locality"
},
  "geometry": {"coordinates":[-86.46848,13.32428],"type":"Point"}
}