{
  "type": "Feature",
  "properties": {
    "gn:admin1_code":"3.0",
    "gn:asciiname":"Filadelfia",
    "gn:country_code":"NI",
    "gn:dem":44,
    "gn:feature_class":"P",
    "gn:feature_code":"PPL",
    "gn:name":"Filadelfia",
    "gn:population":0,
    "gn:timezone":"America/Managua",
    "iso:country":"NI",
    "wof:name":"Filadelfia",
    "wof:placetype":"locality"
},
  "geometry": {"coordinates":[-87.11667,12.58333],"type":"Point"}
}