{
  "type": "Feature",
  "properties": {
    "gn:admin1_code":"15.0",
    "gn:asciiname":"Canas",
    "gn:country_code":"NI",
    "gn:dem":37,
    "gn:feature_class":"P",
    "gn:feature_code":"PPL",
    "gn:name":"Ca\u00f1as",
    "gn:population":0,
    "gn:timezone":"America/Managua",
    "iso:country":"NI",
    "name:ceb_x_preferred":[
        "Canas"
    ],
    "name:deu_x_preferred":[
        "Canas"
    ],
    "name:nld_x_preferred":[
        "Canas"
    ],
    "name:por_x_preferred":[
        "Canas"
    ],
    "name:ron_x_preferred":[
        "Canas"
    ],
    "name:rus_x_preferred":[
        "\u041a\u0430\u043d\u0430\u0441"
    ],
    "name:swe_x_preferred":[
        "Canas"
    ],
    "wof:name":"Canas",
    "wof:placetype":"locality"
},
  "geometry": {"coordinates":[-85.27174000000002,11.11381],"type":"Point"}
}