{
  "type": "Feature",
  "properties": {
    "gn:admin1_code":"11.0",
    "gn:asciiname":"La Piedra",
    "gn:country_code":"NI",
    "gn:dem":77,
    "gn:feature_class":"P",
    "gn:feature_code":"PPL",
    "gn:name":"La Piedra",
    "gn:population":0,
    "gn:timezone":"America/Managua",
    "iso:country":"NI",
    "name:und_x_variant":[
        "Caser\u00edo La Piedra",
        "La Piedra"
    ],
    "wof:name":"La Piedra",
    "wof:placetype":"locality"
},
  "geometry": {"coordinates":[-86.01494,12.04758],"type":"Point"}
}