{
  "type": "Feature",
  "properties": {
    "gn:admin1_code":"17.0",
    "gn:asciiname":"Sang Sang",
    "gn:country_code":"NI",
    "gn:dem":65,
    "gn:feature_class":"P",
    "gn:feature_code":"PPL",
    "gn:name":"Sang Sang",
    "gn:population":0,
    "gn:timezone":"America/Managua",
    "iso:country":"NI",
    "name:und_x_variant":[
        "Sansang",
        "Sang Sang"
    ],
    "wof:name":"Sang Sang",
    "wof:placetype":"locality"
},
  "geometry": {"coordinates":[-84.63418,14.66551],"type":"Point"}
}