{
  "type": "Feature",
  "properties": {
    "iso:country":"NI",
    "name:cat_x_preferred":[
        "Le\u00f3n Viejo"
    ],
    "name:ces_x_preferred":[
        "Le\u00f3n Viejo"
    ],
    "name:dan_x_preferred":[
        "Le\u00f3n Viejo"
    ],
    "name:deu_x_preferred":[
        "Le\u00f3n Viejo"
    ],
    "name:fin_x_preferred":[
        "Le\u00f3n Viejo"
    ],
    "name:heb_x_preferred":[
        "\u05dc\u05d0\u05d5\u05df \u05d4\u05e2\u05ea\u05d9\u05e7\u05d4"
    ],
    "name:hrv_x_preferred":[
        "Le\u00f3n Viejo"
    ],
    "name:kat_x_preferred":[
        "\u10da\u10d4\u10dd\u10dc-\u10d5\u10d8\u10d4\u10ee\u10dd"
    ],
    "name:lit_x_preferred":[
        "Senasis Leonas"
    ],
    "name:spa_x_preferred":[
        "Le\u00f3n Viejo"
    ],
    "qs:gn_pop":0,
    "qs:name":"Leon Viejo",
    "qs:name_adm0":"Nicaragua",
    "qs:name_adm1":"Le\u00f3n",
    "qs:photos":90,
    "qs:photos_1k":18,
    "qs:photos_9k":1,
    "qs:photos_9r":3,
    "qs:photos_all":90,
    "qs:photos_sr":3,
    "qs:placetype":"Town",
    "qs:pop_sr":"0",
    "qs:woe_adm0":23424915,
    "wd:wordcount":415,
    "wof:name":"Leon Viejo",
    "wof:placetype":"locality"
},
  "geometry": {"coordinates":[-86.615009,12.416459],"type":"Point"}
}