{
  "type": "Feature",
  "properties": {
    "gn:admin1_code":"3.0",
    "gn:asciiname":"San Lucas",
    "gn:country_code":"NI",
    "gn:dem":54,
    "gn:feature_class":"P",
    "gn:feature_code":"PPL",
    "gn:name":"San Lucas",
    "gn:population":0,
    "gn:timezone":"America/Managua",
    "iso:country":"NI",
    "name:ceb_x_preferred":[
        "San Lucas"
    ],
    "name:deu_x_preferred":[
        "San Lucas"
    ],
    "name:epo_x_preferred":[
        "San Lucas"
    ],
    "name:fra_x_preferred":[
        "San Lucas"
    ],
    "name:glg_x_preferred":[
        "San Lucas"
    ],
    "name:ita_x_preferred":[
        "San Lucas"
    ],
    "name:nds_x_preferred":[
        "San Lucas"
    ],
    "name:nld_x_preferred":[
        "San Lucas"
    ],
    "name:pol_x_preferred":[
        "San Lucas"
    ],
    "name:por_x_preferred":[
        "San Lucas"
    ],
    "name:rus_x_preferred":[
        "\u0421\u0430\u043d-\u041b\u0443\u043a\u0430\u0441"
    ],
    "name:sco_x_preferred":[
        "San Lucas"
    ],
    "name:spa_x_preferred":[
        "San Lucas"
    ],
    "name:swe_x_preferred":[
        "San Lucas"
    ],
    "name:vie_x_preferred":[
        "San Lucas"
    ],
    "wof:name":"San Lucas",
    "wof:placetype":"locality"
},
  "geometry": {"coordinates":[-86.87687,12.69896],"type":"Point"}
}