{
  "type": "Feature",
  "properties": {
    "gn:admin1_code":"3.0",
    "gn:asciiname":"San Lucas",
    "gn:country_code":"NI",
    "gn:dem":54,
    "gn:feature_class":"P",
    "gn:feature_code":"PPL",
    "gn:name":"San Lucas",
    "gn:population":0,
    "gn:timezone":"America/Managua",
    "iso:country":"NI",
    "wof:name":"San Lucas",
    "wof:placetype":"locality"
},
  "geometry": {"coordinates":[-86.87687,12.69896],"type":"Point"}
}