{
  "type": "Feature",
  "properties": {
    "gn:admin1_code":"12.0",
    "gn:asciiname":"Escocia",
    "gn:country_code":"NI",
    "gn:dem":915,
    "gn:feature_class":"P",
    "gn:feature_code":"PPL",
    "gn:name":"Escocia",
    "gn:population":0,
    "gn:timezone":"America/Managua",
    "iso:country":"NI",
    "wof:name":"Escocia",
    "wof:placetype":"locality"
},
  "geometry": {"coordinates":[-85.66331,12.92619],"type":"Point"}
}