{
  "type": "Feature",
  "properties": {
    "gn:admin1_code":"3.0",
    "gn:asciiname":"Monte Rosa",
    "gn:country_code":"NI",
    "gn:dem":39,
    "gn:feature_class":"P",
    "gn:feature_code":"PPL",
    "gn:name":"Monte Rosa",
    "gn:population":0,
    "gn:timezone":"America/Managua",
    "iso:country":"NI",
    "name:als_x_preferred":[
        "Monte Rosa"
    ],
    "name:bre_x_preferred":[
        "Monte Rosa"
    ],
    "name:cat_x_preferred":[
        "Mont Rosa"
    ],
    "name:ces_x_preferred":[
        "Monte Rosa"
    ],
    "name:dan_x_preferred":[
        "Monte Rosa"
    ],
    "name:deu_x_preferred":[
        "Monte Rosa"
    ],
    "name:ell_x_preferred":[
        "\u039c\u03cc\u03bd\u03c4\u03b5 \u03a1\u03cc\u03b6\u03b1"
    ],
    "name:epo_x_preferred":[
        "Monte-Rosa-Masivo"
    ],
    "name:eus_x_preferred":[
        "Monte Rosa"
    ],
    "name:fas_x_preferred":[
        "\u0645\u0648\u0646\u062a\u0647 \u0631\u0648\u0632\u0627"
    ],
    "name:fin_x_preferred":[
        "Monte Rosan massiivi"
    ],
    "name:fra_x_preferred":[
        "Mont Rose"
    ],
    "name:hun_x_preferred":[
        "Monte Rosa"
    ],
    "name:hye_x_preferred":[
        "\u0544\u0578\u0576\u057f\u0565 \u054c\u0578\u0566\u0561"
    ],
    "name:ita_x_preferred":[
        "Monte Rosa"
    ],
    "name:jpn_x_preferred":[
        "\u30e2\u30f3\u30c6\u30fb\u30ed\u30fc\u30b6"
    ],
    "name:kaz_x_preferred":[
        "\u041c\u043e\u043d\u0442\u0435-\u0420\u043e\u0437\u0430"
    ],
    "name:kor_x_preferred":[
        "\ubaac\ud14c\ub85c\uc0ac\uc0b0"
    ],
    "name:lat_x_preferred":[
        "Silvius mons"
    ],
    "name:lit_x_preferred":[
        "Monte Roza"
    ],
    "name:lmo_x_preferred":[
        "Mont Roeusa"
    ],
    "name:nld_x_preferred":[
        "Monte Rosa"
    ],
    "name:nno_x_preferred":[
        "Monte Rosa"
    ],
    "name:nor_x_preferred":[
        "Monte Rosa"
    ],
    "name:pms_x_preferred":[
        "Mont R\u00f2sa"
    ],
    "name:pnb_x_preferred":[
        "\u062c\u062a \u062f\u06cc \u0688\u0627\u0679"
    ],
    "name:pol_x_preferred":[
        "Monte Rosa"
    ],
    "name:roh_x_preferred":[
        "Monte Rosa"
    ],
    "name:ron_x_preferred":[
        "Monte Rosa"
    ],
    "name:rus_x_preferred":[
        "\u041c\u043e\u043d\u0442\u0435-\u0420\u043e\u0437\u0430"
    ],
    "name:sco_x_preferred":[
        "Monte Rosa"
    ],
    "name:slv_x_preferred":[
        "Monte Rosa"
    ],
    "name:spa_x_preferred":[
        "Macizo del Monte Rosa"
    ],
    "name:srp_x_preferred":[
        "\u041c\u043e\u043d\u0442\u0435 \u0420\u043e\u0437\u0430"
    ],
    "name:swa_x_preferred":[
        "Monte Rosa"
    ],
    "name:swe_x_preferred":[
        "Monte Rosa"
    ],
    "name:ukr_x_preferred":[
        "\u041c\u043e\u043d\u0442\u0435-\u0420\u043e\u0437\u0430"
    ],
    "name:und_x_variant":[
        "Ingenio Monterrosa",
        "Monte Rosa"
    ],
    "name:zho_x_preferred":[
        "\u7f57\u838e\u5cf0"
    ],
    "wof:name":"Monte Rosa",
    "wof:placetype":"locality"
},
  "geometry": {"coordinates":[-87.23419,12.70524],"type":"Point"}
}