{
  "type": "Feature",
  "properties": {
    "gn:admin1_code":"3.0",
    "gn:asciiname":"Monte Rosa",
    "gn:country_code":"NI",
    "gn:dem":39,
    "gn:feature_class":"P",
    "gn:feature_code":"PPL",
    "gn:name":"Monte Rosa",
    "gn:population":0,
    "gn:timezone":"America/Managua",
    "iso:country":"NI",
    "name:und_x_variant":[
        "Ingenio Monterrosa",
        "Monte Rosa"
    ],
    "wof:name":"Monte Rosa",
    "wof:placetype":"locality"
},
  "geometry": {"coordinates":[-87.23419,12.70524],"type":"Point"}
}