{
  "type": "Feature",
  "properties": {
    "gn:admin1_code":"10.0",
    "gn:asciiname":"La Historia",
    "gn:country_code":"NI",
    "gn:dem":844,
    "gn:feature_class":"P",
    "gn:feature_code":"PPL",
    "gn:name":"La Historia",
    "gn:population":0,
    "gn:timezone":"America/Managua",
    "iso:country":"NI",
    "name:spa_x_preferred":[
        "La historia"
    ],
    "wof:name":"La Historia",
    "wof:placetype":"locality"
},
  "geometry": {"coordinates":[-86.26764,12.01413],"type":"Point"}
}