{
  "type": "Feature",
  "properties": {
    "gn:admin1_code":"8.0",
    "gn:asciiname":"Los Zarzales",
    "gn:country_code":"NI",
    "gn:dem":82,
    "gn:feature_class":"P",
    "gn:feature_code":"PPL",
    "gn:name":"Los Zarzales",
    "gn:population":0,
    "gn:timezone":"America/Managua",
    "iso:country":"NI",
    "name:und_x_variant":[
        "Caser\u00edo Los Zarzales",
        "Zarzales",
        "Los Zarzales"
    ],
    "wof:name":"Los Zarzales",
    "wof:placetype":"locality"
},
  "geometry": {"coordinates":[-86.44098000000002,12.66187],"type":"Point"}
}