{
  "type": "Feature",
  "properties": {
    "iso:country":"NI",
    "qs:gn_country":"NI",
    "qs:gn_fcode":"PPL",
    "qs:gn_pop":0,
    "qs:name":"Santa Ana",
    "qs:name_adm0":"Nicaragua",
    "qs:name_adm1":"Managua",
    "qs:photos":601,
    "qs:photos_1k":122,
    "qs:photos_9k":3,
    "qs:photos_9r":5,
    "qs:photos_all":601,
    "qs:photos_sr":8,
    "qs:placetype":"Town",
    "qs:pop_sr":"3",
    "qs:woe_adm0":23424915,
    "wof:name":"Santa Ana",
    "wof:placetype":"locality"
},
  "geometry": {"coordinates":[-86.34614000000001,12.09654],"type":"Point"}
}