{
  "type": "Feature",
  "properties": {
    "gn:admin1_code":"10.0",
    "gn:asciiname":"Cofradia",
    "gn:country_code":"NI",
    "gn:dem":83,
    "gn:feature_class":"P",
    "gn:feature_code":"PPL",
    "gn:name":"Cofrad\u00eda",
    "gn:population":0,
    "gn:timezone":"America/Managua",
    "iso:country":"NI",
    "name:und_x_variant":[
        "Cofrad\u00edas",
        "Cofrad\u00eda"
    ],
    "wof:name":"Cofradia",
    "wof:placetype":"locality"
},
  "geometry": {"coordinates":[-86.12319000000002,12.11541],"type":"Point"}
}